Workbook

Sheet Financing Inputs
B1: Inputs
B2: ($ in 'mm)
B4: Sources & Uses | N4: Business Purchase Assumptions
B5: Sources | H5: Uses | N5: Deal Close | T5: 45657
B7: Equity 1 | F7: =+SUM(L7:L9)-F11-F8 -> 269.875 | H7: Equity Purchase Price | L7: =IF(L43=1,T11,T13) -> 2159 | N7: Total Outstaning Shares | T7: 200
B8: Equity 2 | F8: =(SUM($L$7:$L$9)-F11)*T26 -> 269.875 | H8: Funding Fees | L8: =CHOOSE(L18,0,L39,0,0,0) -> 0 | N8: Current Share Price | T8: 10
B9: Assumed Existing Debt 1 | F9: 300 | H9: Other Closing Fees | L9: =T29*T11 -> 0 | N9: Premium on current share price (%) | T9: 0.08
B10: Assumed Existing Debt 2 | F10: =IF(L48=1,23.831,0) -> 0 | H10: Existing Debt 1 | L10: =F9 -> 300 | N10: Implied Stock Price | T10: =T8*(1+T9) -> 10.8
B11: Debt | F11: =L7*CHOOSE(L18,L26,L37,0,0) -> 1619.25 | H11: Existing Debt 2 | L11: =F10 -> 0 | N11: Equity Value Offered | T11: =T10*T7 -> 2160
N12: Net Debt | T12: -1
N13: Enterprise Value | T13: =T12+T11 -> 2159
B14: Total Sources | F14: =SUM(F7:F13) -> 2459 | H14: Total Uses | L14: =SUM(L7:L11) -> 2459 | N14: 2024E EBITDA | T14: =_xlfn.XLOOKUP(T5,Financials!$T$6:$AN$6,Financials!$T$29:$AN$29,0,0) -> 312.97923
N15: 2024E EBITDA Multiple | T15: =IFERROR(T11/T14,"na") -> 6.9014164
B16: Debt Assumptions
N17: Exit Assumptions
B18: Debt Facility Selector | L18: 1 | N18: Investment Horizon | T18: 10
B19: 1 = Debt 1 | N19: Exit Date | T19: =EOMONTH(T5,T18*12) -> 49309
B20: 2 = Debt 2 | N20: EBITDA at Exit | T20: =_xlfn.XLOOKUP(T19,Financials!$T$6:$AN$6,Financials!$T$29:$AN$29,0,0) -> 362.48471
B21: 3 = No Debt | N21: EBITDA Multiple | T21: 5
N22: Business Proceeds | T22: =T20*T21 -> 1812.4235
B24: Debt 1 | N24: Inputs for Ownership %
B25: * Structured as a Mortgage | N25: Equity 1 | T25: 0.5
B26: Loan to Value (Purchase Price) | L26: 0.75 | N26: Equity 2 | T26: =1-T25 -> 0.5
B27: Fixed Coupon | L27: 0.09
B28: Amortization Profile (Years) | L28: 18 | N28: Other Assumptions
N29: Other Closing Fees | T29: 0
B30: Debt 2
B31: * Structured as a Corporate Loan | N31: Toggle to Fund Sr. Unsec. Notes at Maturity | T31: 3
N32: 1 = Cashflow + Equity (if required)
B33: Coupon | L33: 0.031 | N33: 2 = 100% Equity
B34: Step up Interest rate | J34: 46539 | L34: 0.01 | N34: 3 = Refinance by Debt (Toggle in cell T52)
B35: Step up Interest rate | J35: 46905 | L35: 0.005
B36: Amortization per Year | J36: =J35 -> 46905 | L36: =1/7 -> 0.14285714 | N36: Refinance of Senior Unsecured Notes Selector | T36: 1
B37: Loan to Value (Purchase Price) | L37: 0.55 | N37: 1 = Debt 1
B38: Funding Fees (%) | L38: 0.0075 | N38: 2 = Debt 2
B39: Total Funding Fees | L39: =IF(L18=2,L38*F11,0) -> 0
B41: Existing Debt Assumptions
B43: Rollover of Debt 1 | K43: (1 = Yes, 0 = No) >>> | L43: 0
B44: Interest Rate | L44: 0.08
B45: Amount O/S as of Dec 31, 2024 | L45: 200
B46: Maturity Date | L46: 47118
B48: Rollover of Debt 2 | K48: (1 = Yes, 0 = No) >>> | L48: =L43 -> 0
B49: Interest Rate | L49: 0.05
B50: Amount O/S as of Dec 31, 2024 | L50: 24
B51: Amortization per year | L51: =L50/3 -> 8
B52: Maturity Date | L52: 46446

Sheet Operating Inputs
B2: Operating Inputs
B4: Scenario Selector>>> | D4: 3 | F4: <<< ( 1 : Downside Case, 2 : Base Case, 3 : Upside Case)
F6: Downside Case | AB6: Base Case | AX6: Upside Case | BU6: Selected Case
B7: Particulars | F7: ='Financing Inputs'!$T$5 -> 45657 | H7: =EOMONTH(F7,12) -> 46022 | J7: =EOMONTH(H7,12) -> 46387 | L7: =EOMONTH(J7,12) -> 46752 | N7: =EOMONTH(L7,12) -> 47118 | P7: =EOMONTH(N7,12) -> 47483 | R7: =EOMONTH(P7,12) -> 47848 | T7: =EOMONTH(R7,12) -> 48213 | V7: =EOMONTH(T7,12) -> 48579 | X7: =EOMONTH(V7,12) -> 48944 | Z7: =EOMONTH(X7,12) -> 49309 | AB7: ='Financing Inputs'!$T$5 -> 45657 | AD7: 46022 | AF7: =EOMONTH(AD7,12) -> 46387 | AH7: =EOMONTH(AF7,12) -> 46752 | AJ7: =EOMONTH(AH7,12) -> 47118 | AL7: =EOMONTH(AJ7,12) -> 47483 | AN7: =EOMONTH(AL7,12) -> 47848 | AP7: =EOMONTH(AN7,12) -> 48213 | AR7: =EOMONTH(AP7,12) -> 48579 | AT7: =EOMONTH(AR7,12) -> 48944 | AV7: =EOMONTH(AT7,12) -> 49309 | AX7: ='Financing Inputs'!$T$5 -> 45657 | AZ7: 46022 | BB7: =EOMONTH(AZ7,12) -> 46387 | BD7: =EOMONTH(BB7,12) -> 46752 | BF7: =EOMONTH(BD7,12) -> 47118 | BH7: =EOMONTH(BF7,12) -> 47483 | BJ7: =EOMONTH(BH7,12) -> 47848 | BL7: =EOMONTH(BJ7,12) -> 48213 | BN7: =EOMONTH(BL7,12) -> 48579 | BP7: =EOMONTH(BN7,12) -> 48944 | BR7: =EOMONTH(BP7,12) -> 49309 | BU7: ='Financing Inputs'!T5 -> 45657 | BW7: =EOMONTH(BU7,12) -> 46022 | BY7: =EOMONTH(BW7,12) -> 46387 | CA7: =EOMONTH(BY7,12) -> 46752 | CC7: =EOMONTH(CA7,12) -> 47118 | CE7: =EOMONTH(CC7,12) -> 47483 | CG7: =EOMONTH(CE7,12) -> 47848 | CI7: =EOMONTH(CG7,12) -> 48213 | CK7: =EOMONTH(CI7,12) -> 48579 | CM7: =EOMONTH(CK7,12) -> 48944 | CO7: =EOMONTH(CM7,12) -> 49309
B10: Revenue Assumptions
B11: Segment 1 | D11: % Yr/Yr Growth | F11: 0.095 | H11: 0.08 | J11: 0.07 | L11: 0.06 | N11: 0.05 | P11: 0.04 | R11: -0.03 | T11: =+R11 -> -0.03 | V11: =+T11 -> -0.03 | X11: =+V11 -> -0.03 | Z11: =+X11 -> -0.03 | AB11: 0.095 | AD11: 0.08 | AF11: 0.07 | AH11: 0.06 | AJ11: 0.05 | AL11: 0.04 | AN11: -0.03 | AP11: =AN11 -> -0.03 | AR11: =AP11 -> -0.03 | AT11: =AR11 -> -0.03 | AV11: =AT11 -> -0.03 | AX11: 0.095 | AZ11: 0.08 | BB11: 0.07 | BD11: 0.06 | BF11: 0.05 | BH11: 0.04 | BJ11: -0.03 | BL11: =+BJ11 -> -0.03 | BN11: =+BL11 -> -0.03 | BP11: =+BN11 -> -0.03 | BR11: =+BP11 -> -0.03 | BU11: =CHOOSE($D$4,F11,AB11,AX11) -> 0.095 | BW11: =CHOOSE($D$4,H11,AD11,AZ11) -> 0.08 | BY11: =CHOOSE($D$4,J11,AF11,BB11) -> 0.07 | CA11: =CHOOSE($D$4,L11,AH11,BD11) -> 0.06 | CC11: =CHOOSE($D$4,N11,AJ11,BF11) -> 0.05 | CE11: =CHOOSE($D$4,P11,AL11,BH11) -> 0.04 | CG11: =CHOOSE($D$4,R11,AN11,BJ11) -> -0.03 | CI11: =CHOOSE($D$4,T11,AP11,BL11) -> -0.03 | CK11: =CHOOSE($D$4,V11,AR11,BN11) -> -0.03 | CM11: =CHOOSE($D$4,X11,AT11,BP11) -> -0.03 | CO11: =CHOOSE($D$4,Z11,AV11,BR11) -> -0.03
B12: Segment 2 | D12: % Yr/Yr Growth | F12: 0.1 | H12: 0.1 | J12: 0.1 | L12: 0.1 | N12: 0.08 | P12: 0.08 | R12: -0.01 | T12: =+R12 -> -0.01 | V12: =+T12 -> -0.01 | X12: =+V12 -> -0.01 | Z12: =+X12 -> -0.01 | AB12: 0.1 | AD12: 0.1 | AF12: 0.1 | AH12: 0.1 | AJ12: 0.08 | AL12: 0.08 | AN12: -0.01 | AP12: =AN12 -> -0.01 | AR12: =AP12 -> -0.01 | AT12: =AR12 -> -0.01 | AV12: =AT12 -> -0.01 | AX12: 0.1 | AZ12: 0.1 | BB12: 0.1 | BD12: 0.1 | BF12: 0.08 | BH12: 0.08 | BJ12: -0.01 | BL12: =+BJ12 -> -0.01 | BN12: =+BL12 -> -0.01 | BP12: =+BN12 -> -0.01 | BR12: =+BP12 -> -0.01 | BU12: =CHOOSE($D$4,F12,AB12,AX12) -> 0.1 | BW12: =CHOOSE($D$4,H12,AD12,AZ12) -> 0.1 | BY12: =CHOOSE($D$4,J12,AF12,BB12) -> 0.1 | CA12: =CHOOSE($D$4,L12,AH12,BD12) -> 0.1 | CC12: =CHOOSE($D$4,N12,AJ12,BF12) -> 0.08 | CE12: =CHOOSE($D$4,P12,AL12,BH12) -> 0.08 | CG12: =CHOOSE($D$4,R12,AN12,BJ12) -> -0.01 | CI12: =CHOOSE($D$4,T12,AP12,BL12) -> -0.01 | CK12: =CHOOSE($D$4,V12,AR12,BN12) -> -0.01 | CM12: =CHOOSE($D$4,X12,AT12,BP12) -> -0.01 | CO12: =CHOOSE($D$4,Z12,AV12,BR12) -> -0.01
B13: Segment 3 | D13: % Yr/Yr Growth | F13: -0.28 | H13: -0.23 | J13: 0.02 | L13: 0.02 | N13: 0.02 | P13: 0.02 | R13: 0.02 | T13: =+R13 -> 0.02 | V13: =+T13 -> 0.02 | X13: =+V13 -> 0.02 | Z13: =+X13 -> 0.02 | AB13: -0.28 | AD13: -0.23 | AF13: 0.02 | AH13: 0.02 | AJ13: 0.02 | AL13: 0.02 | AN13: 0.02 | AP13: =AN13 -> 0.02 | AR13: =AP13 -> 0.02 | AT13: =AR13 -> 0.02 | AV13: =AT13 -> 0.02 | AX13: -0.28 | AZ13: -0.23 | BB13: 0.02 | BD13: 0.02 | BF13: 0.02 | BH13: 0.02 | BJ13: 0.02 | BL13: =+BJ13 -> 0.02 | BN13: =+BL13 -> 0.02 | BP13: =+BN13 -> 0.02 | BR13: =+BP13 -> 0.02 | BU13: =CHOOSE($D$4,F13,AB13,AX13) -> -0.28 | BW13: =CHOOSE($D$4,H13,AD13,AZ13) -> -0.23 | BY13: =CHOOSE($D$4,J13,AF13,BB13) -> 0.02 | CA13: =CHOOSE($D$4,L13,AH13,BD13) -> 0.02 | CC13: =CHOOSE($D$4,N13,AJ13,BF13) -> 0.02 | CE13: =CHOOSE($D$4,P13,AL13,BH13) -> 0.02 | CG13: =CHOOSE($D$4,R13,AN13,BJ13) -> 0.02 | CI13: =CHOOSE($D$4,T13,AP13,BL13) -> 0.02 | CK13: =CHOOSE($D$4,V13,AR13,BN13) -> 0.02 | CM13: =CHOOSE($D$4,X13,AT13,BP13) -> 0.02 | CO13: =CHOOSE($D$4,Z13,AV13,BR13) -> 0.02
B14: Segment 4 | D14: % Yr/Yr Growth | F14: 0.02 | H14: 0 | J14: 0 | L14: 0 | N14: 0 | P14: 0 | R14: 0 | T14: =+R14 -> 0 | V14: =+T14 -> 0 | X14: =+V14 -> 0 | Z14: =+X14 -> 0 | AB14: 0.02 | AD14: 0 | AF14: 0 | AH14: 0 | AJ14: 0 | AL14: 0 | AN14: 0 | AP14: =AN14 -> 0 | AR14: =AP14 -> 0 | AT14: =AR14 -> 0 | AV14: =AT14 -> 0 | AX14: 0.02 | AZ14: 0 | BB14: 0 | BD14: 0 | BF14: 0 | BH14: 0 | BJ14: 0 | BL14: =+BJ14 -> 0 | BN14: =+BL14 -> 0 | BP14: =+BN14 -> 0 | BR14: =+BP14 -> 0 | BU14: =CHOOSE($D$4,F14,AB14,AX14) -> 0.02 | BW14: =CHOOSE($D$4,H14,AD14,AZ14) -> 0 | BY14: =CHOOSE($D$4,J14,AF14,BB14) -> 0 | CA14: =CHOOSE($D$4,L14,AH14,BD14) -> 0 | CC14: =CHOOSE($D$4,N14,AJ14,BF14) -> 0 | CE14: =CHOOSE($D$4,P14,AL14,BH14) -> 0 | CG14: =CHOOSE($D$4,R14,AN14,BJ14) -> 0 | CI14: =CHOOSE($D$4,T14,AP14,BL14) -> 0 | CK14: =CHOOSE($D$4,V14,AR14,BN14) -> 0 | CM14: =CHOOSE($D$4,X14,AT14,BP14) -> 0 | CO14: =CHOOSE($D$4,Z14,AV14,BR14) -> 0
B15: Segment 5 | D15: % Yr/Yr Growth | F15: 0.04 | H15: 0.04 | J15: 0.04 | L15: 0.04 | N15: 0.04 | P15: 0.04 | R15: 0.04 | T15: =+R15 -> 0.04 | V15: =+T15 -> 0.04 | X15: =+V15 -> 0.04 | Z15: =+X15 -> 0.04 | AB15: 0.04 | AD15: 0.04 | AF15: 0.04 | AH15: 0.04 | AJ15: 0.04 | AL15: 0.04 | AN15: 0.04 | AP15: =AN15 -> 0.04 | AR15: =AP15 -> 0.04 | AT15: =AR15 -> 0.04 | AV15: =AT15 -> 0.04 | AX15: 0.04 | AZ15: 0.04 | BB15: 0.04 | BD15: 0.04 | BF15: 0.04 | BH15: 0.04 | BJ15: 0.04 | BL15: =+BJ15 -> 0.04 | BN15: =+BL15 -> 0.04 | BP15: =+BN15 -> 0.04 | BR15: =+BP15 -> 0.04 | BU15: =CHOOSE($D$4,F15,AB15,AX15) -> 0.04 | BW15: =CHOOSE($D$4,H15,AD15,AZ15) -> 0.04 | BY15: =CHOOSE($D$4,J15,AF15,BB15) -> 0.04 | CA15: =CHOOSE($D$4,L15,AH15,BD15) -> 0.04 | CC15: =CHOOSE($D$4,N15,AJ15,BF15) -> 0.04 | CE15: =CHOOSE($D$4,P15,AL15,BH15) -> 0.04 | CG15: =CHOOSE($D$4,R15,AN15,BJ15) -> 0.04 | CI15: =CHOOSE($D$4,T15,AP15,BL15) -> 0.04 | CK15: =CHOOSE($D$4,V15,AR15,BN15) -> 0.04 | CM15: =CHOOSE($D$4,X15,AT15,BP15) -> 0.04 | CO15: =CHOOSE($D$4,Z15,AV15,BR15) -> 0.04
B17: Gross Margin (%) | D17: % Margin | F17: 0.3 | H17: =+F17 -> 0.3 | J17: =+H17 -> 0.3 | L17: =+J17 -> 0.3 | N17: =+L17 -> 0.3 | P17: =+N17 -> 0.3 | R17: =+P17 -> 0.3 | T17: =+R17 -> 0.3 | V17: =+T17 -> 0.3 | X17: =+V17 -> 0.3 | Z17: =+X17 -> 0.3 | AB17: 0.3 | AD17: =+AB17 -> 0.3 | AF17: =+AD17 -> 0.3 | AH17: =+AF17 -> 0.3 | AJ17: =+AH17 -> 0.3 | AL17: =+AJ17 -> 0.3 | AN17: =+AL17 -> 0.3 | AP17: =+AN17 -> 0.3 | AR17: =+AP17 -> 0.3 | AT17: =+AR17 -> 0.3 | AV17: =+AT17 -> 0.3 | AX17: 0.3 | AZ17: =+AX17 -> 0.3 | BB17: =+AZ17 -> 0.3 | BD17: =+BB17 -> 0.3 | BF17: =+BD17 -> 0.3 | BH17: =+BF17 -> 0.3 | BJ17: =+BH17 -> 0.3 | BL17: =+BJ17 -> 0.3 | BN17: =+BL17 -> 0.3 | BP17: =+BN17 -> 0.3 | BR17: =+BP17 -> 0.3 | BU17: =CHOOSE($D$4,F17,AB17,AX17) -> 0.3 | BW17: =CHOOSE($D$4,H17,AD17,AZ17) -> 0.3 | BY17: =CHOOSE($D$4,J17,AF17,BB17) -> 0.3 | CA17: =CHOOSE($D$4,L17,AH17,BD17) -> 0.3 | CC17: =CHOOSE($D$4,N17,AJ17,BF17) -> 0.3 | CE17: =CHOOSE($D$4,P17,AL17,BH17) -> 0.3 | CG17: =CHOOSE($D$4,R17,AN17,BJ17) -> 0.3 | CI17: =CHOOSE($D$4,T17,AP17,BL17) -> 0.3 | CK17: =CHOOSE($D$4,V17,AR17,BN17) -> 0.3 | CM17: =CHOOSE($D$4,X17,AT17,BP17) -> 0.3 | CO17: =CHOOSE($D$4,Z17,AV17,BR17) -> 0.3
B19: Expenses Assumptions
B20: SG&A | D20: % of Total Revenue | F20: 0.108 | H20: 0.08 | J20: =+H20 -> 0.08 | L20: =+J20 -> 0.08 | N20: =+L20 -> 0.08 | P20: =+N20 -> 0.08 | R20: =+P20 -> 0.08 | T20: =+R20 -> 0.08 | V20: =+T20 -> 0.08 | X20: =+V20 -> 0.08 | Z20: =+X20 -> 0.08 | AB20: 0.068 | AD20: =+AB20 -> 0.068 | AF20: =+AD20 -> 0.068 | AH20: =+AF20 -> 0.068 | AJ20: =+AH20 -> 0.068 | AL20: =+AJ20 -> 0.068 | AN20: =+AL20 -> 0.068 | AP20: =+AN20 -> 0.068 | AR20: =+AP20 -> 0.068 | AT20: =+AR20 -> 0.068 | AV20: =+AT20 -> 0.068 | AX20: 0.048 | AZ20: =+AX20 -> 0.048 | BB20: =+AZ20 -> 0.048 | BD20: =+BB20 -> 0.048 | BF20: =+BD20 -> 0.048 | BH20: =+BF20 -> 0.048 | BJ20: =+BH20 -> 0.048 | BL20: =+BJ20 -> 0.048 | BN20: =+BL20 -> 0.048 | BP20: =+BN20 -> 0.048 | BR20: =+BP20 -> 0.048 | BU20: =CHOOSE($D$4,F20,AB20,AX20) -> 0.048 | BW20: =CHOOSE($D$4,H20,AD20,AZ20) -> 0.048 | BY20: =CHOOSE($D$4,J20,AF20,BB20) -> 0.048 | CA20: =CHOOSE($D$4,L20,AH20,BD20) -> 0.048 | CC20: =CHOOSE($D$4,N20,AJ20,BF20) -> 0.048 | CE20: =CHOOSE($D$4,P20,AL20,BH20) -> 0.048 | CG20: =CHOOSE($D$4,R20,AN20,BJ20) -> 0.048 | CI20: =CHOOSE($D$4,T20,AP20,BL20) -> 0.048 | CK20: =CHOOSE($D$4,V20,AR20,BN20) -> 0.048 | CM20: =CHOOSE($D$4,X20,AT20,BP20) -> 0.048 | CO20: =CHOOSE($D$4,Z20,AV20,BR20) -> 0.048
B22: Capital Expenditure | D22: in $'mm | F22: 30.02 | H22: =+F22 -> 30.02 | J22: =+H22 -> 30.02 | L22: =+J22 -> 30.02 | N22: =+L22 -> 30.02 | P22: =+N22 -> 30.02 | R22: =+P22 -> 30.02 | T22: =+R22 -> 30.02 | V22: =+T22 -> 30.02 | X22: =+V22 -> 30.02 | Z22: =+X22 -> 30.02 | AB22: 35 | AD22: =+AB22 -> 35 | AF22: =+AD22 -> 35 | AH22: =+AF22 -> 35 | AJ22: =+AH22 -> 35 | AL22: =+AJ22 -> 35 | AN22: =+AL22 -> 35 | AP22: =+AN22 -> 35 | AR22: =+AP22 -> 35 | AT22: =+AR22 -> 35 | AV22: =+AT22 -> 35 | AX22: 40 | AZ22: =+AX22 -> 40 | BB22: =+AZ22 -> 40 | BD22: =+BB22 -> 40 | BF22: =+BD22 -> 40 | BH22: =+BF22 -> 40 | BJ22: =+BH22 -> 40 | BL22: =+BJ22 -> 40 | BN22: =+BL22 -> 40 | BP22: =+BN22 -> 40 | BR22: =+BP22 -> 40 | BU22: =CHOOSE($D$4,F22,AB22,AX22) -> 40 | BW22: =CHOOSE($D$4,H22,AD22,AZ22) -> 40 | BY22: =CHOOSE($D$4,J22,AF22,BB22) -> 40 | CA22: =CHOOSE($D$4,L22,AH22,BD22) -> 40 | CC22: =CHOOSE($D$4,N22,AJ22,BF22) -> 40 | CE22: =CHOOSE($D$4,P22,AL22,BH22) -> 40 | CG22: =CHOOSE($D$4,R22,AN22,BJ22) -> 40 | CI22: =CHOOSE($D$4,T22,AP22,BL22) -> 40 | CK22: =CHOOSE($D$4,V22,AR22,BN22) -> 40 | CM22: =CHOOSE($D$4,X22,AT22,BP22) -> 40 | CO22: =CHOOSE($D$4,Z22,AV22,BR22) -> 40
B23: Capital Expenditure 2 | D23: in $'mm | F23: 25.02 | H23: =+F23 -> 25.02 | J23: =+H23 -> 25.02 | L23: =+J23 -> 25.02 | N23: =+L23 -> 25.02 | P23: =+N23 -> 25.02 | R23: =+P23 -> 25.02 | T23: =+R23 -> 25.02 | V23: =+T23 -> 25.02 | X23: =+V23 -> 25.02 | Z23: =+X23 -> 25.02 | AB23: 30 | AD23: =+AB23 -> 30 | AF23: =+AD23 -> 30 | AH23: =+AF23 -> 30 | AJ23: =+AH23 -> 30 | AL23: =+AJ23 -> 30 | AN23: =+AL23 -> 30 | AP23: =+AN23 -> 30 | AR23: =+AP23 -> 30 | AT23: =+AR23 -> 30 | AV23: =+AT23 -> 30 | AX23: 45 | AZ23: =+AX23 -> 45 | BB23: =+AZ23 -> 45 | BD23: =+BB23 -> 45 | BF23: =+BD23 -> 45 | BH23: =+BF23 -> 45 | BJ23: =+BH23 -> 45 | BL23: =+BJ23 -> 45 | BN23: =+BL23 -> 45 | BP23: =+BN23 -> 45 | BR23: =+BP23 -> 45 | BU23: =CHOOSE($D$4,F23,AB23,AX23) -> 45 | BW23: =CHOOSE($D$4,H23,AD23,AZ23) -> 45 | BY23: =CHOOSE($D$4,J23,AF23,BB23) -> 45 | CA23: =CHOOSE($D$4,L23,AH23,BD23) -> 45 | CC23: =CHOOSE($D$4,N23,AJ23,BF23) -> 45 | CE23: =CHOOSE($D$4,P23,AL23,BH23) -> 45 | CG23: =CHOOSE($D$4,R23,AN23,BJ23) -> 45 | CI23: =CHOOSE($D$4,T23,AP23,BL23) -> 45 | CK23: =CHOOSE($D$4,V23,AR23,BN23) -> 45 | CM23: =CHOOSE($D$4,X23,AT23,BP23) -> 45 | CO23: =CHOOSE($D$4,Z23,AV23,BR23) -> 45
B25: Cash Tax | D25: % of Profit Before Tax | F25: 0.23 | H25: =F25 -> 0.23 | J25: =+H25 -> 0.23 | L25: =+J25 -> 0.23 | N25: =+L25 -> 0.23 | P25: =+N25 -> 0.23 | R25: =+P25 -> 0.23 | T25: =+R25 -> 0.23 | V25: =+T25 -> 0.23 | X25: =+V25 -> 0.23 | Z25: =+X25 -> 0.23 | AB25: 0.21 | AD25: =AB25 -> 0.21 | AF25: =+AD25 -> 0.21 | AH25: =+AF25 -> 0.21 | AJ25: =+AH25 -> 0.21 | AL25: =+AJ25 -> 0.21 | AN25: =+AL25 -> 0.21 | AP25: =+AN25 -> 0.21 | AR25: =+AP25 -> 0.21 | AT25: =+AR25 -> 0.21 | AV25: =+AT25 -> 0.21 | AX25: 0.21 | AZ25: =AX25 -> 0.21 | BB25: =+AZ25 -> 0.21 | BD25: =+BB25 -> 0.21 | BF25: =+BD25 -> 0.21 | BH25: =+BF25 -> 0.21 | BJ25: =+BH25 -> 0.21 | BL25: =+BJ25 -> 0.21 | BN25: =+BL25 -> 0.21 | BP25: =+BN25 -> 0.21 | BR25: =+BP25 -> 0.21 | BU25: =CHOOSE($D$4,F25,AB25,AX25) -> 0.21 | BW25: =CHOOSE($D$4,H25,AD25,AZ25) -> 0.21 | BY25: =CHOOSE($D$4,J25,AF25,BB25) -> 0.21 | CA25: =CHOOSE($D$4,L25,AH25,BD25) -> 0.21 | CC25: =CHOOSE($D$4,N25,AJ25,BF25) -> 0.21 | CE25: =CHOOSE($D$4,P25,AL25,BH25) -> 0.21 | CG25: =CHOOSE($D$4,R25,AN25,BJ25) -> 0.21 | CI25: =CHOOSE($D$4,T25,AP25,BL25) -> 0.21 | CK25: =CHOOSE($D$4,V25,AR25,BN25) -> 0.21 | CM25: =CHOOSE($D$4,X25,AT25,BP25) -> 0.21 | CO25: =CHOOSE($D$4,Z25,AV25,BR25) -> 0.21
B27: Working Capital Sources / (Uses) | D27: in $'mm | F27: 0.02 | H27: =+F27 -> 0.02 | J27: =+H27 -> 0.02 | L27: =+J27 -> 0.02 | N27: =+L27 -> 0.02 | P27: =+N27 -> 0.02 | R27: =+P27 -> 0.02 | T27: =+R27 -> 0.02 | V27: =+T27 -> 0.02 | X27: =+V27 -> 0.02 | Z27: =+X27 -> 0.02 | AB27: 10 | AD27: =+AB27 -> 10 | AF27: =+AD27 -> 10 | AH27: =+AF27 -> 10 | AJ27: =+AH27 -> 10 | AL27: =+AJ27 -> 10 | AN27: =+AL27 -> 10 | AP27: =+AN27 -> 10 | AR27: =+AP27 -> 10 | AT27: =+AR27 -> 10 | AV27: =+AT27 -> 10 | AX27: 20 | AZ27: =+AX27 -> 20 | BB27: =+AZ27 -> 20 | BD27: =+BB27 -> 20 | BF27: =+BD27 -> 20 | BH27: =+BF27 -> 20 | BJ27: =+BH27 -> 20 | BL27: =+BJ27 -> 20 | BN27: =+BL27 -> 20 | BP27: =+BN27 -> 20 | BR27: =+BP27 -> 20 | BU27: =CHOOSE($D$4,F27,AB27,AX27) -> 20 | BW27: =CHOOSE($D$4,H27,AD27,AZ27) -> 20 | BY27: =CHOOSE($D$4,J27,AF27,BB27) -> 20 | CA27: =CHOOSE($D$4,L27,AH27,BD27) -> 20 | CC27: =CHOOSE($D$4,N27,AJ27,BF27) -> 20 | CE27: =CHOOSE($D$4,P27,AL27,BH27) -> 20 | CG27: =CHOOSE($D$4,R27,AN27,BJ27) -> 20 | CI27: =CHOOSE($D$4,T27,AP27,BL27) -> 20 | CK27: =CHOOSE($D$4,V27,AR27,BN27) -> 20 | CM27: =CHOOSE($D$4,X27,AT27,BP27) -> 20 | CO27: =CHOOSE($D$4,Z27,AV27,BR27) -> 20

Sheet Financials
B2: ABC ltd
H4: Historical Financials | T4: Projected Financials
H6: 43465 | J6: =EOMONTH(H6,12) -> 43830 | L6: =EOMONTH(J6,12) -> 44196 | N6: =EOMONTH(L6,12) -> 44561 | P6: =EOMONTH(N6,12) -> 44926 | R6: =EOMONTH(P6,12) -> 45291 | T6: ='Financing Inputs'!T5 -> 45657 | V6: =EOMONTH(T6,12) -> 46022 | X6: =EOMONTH(V6,12) -> 46387 | Z6: =EOMONTH(X6,12) -> 46752 | AB6: =EOMONTH(Z6,12) -> 47118 | AD6: =EOMONTH(AB6,12) -> 47483 | AF6: =EOMONTH(AD6,12) -> 47848 | AH6: =EOMONTH(AF6,12) -> 48213 | AJ6: =EOMONTH(AH6,12) -> 48579 | AL6: =EOMONTH(AJ6,12) -> 48944 | AN6: =EOMONTH(AL6,12) -> 49309
B8: Financial Overview
B9: Total Revenue | H9: =H197 -> 552.31385 | J9: =J197 -> 702.8271 | L9: =L197 -> 714.31355 | N9: =N197 -> 696.87725 | P9: =P197 -> 640.9916 | R9: =R197 -> 1225.2416 | T9: =T123 -> 1241.9811 | V9: =V123 -> 1284.1343 | X9: =X123 -> 1371.6797 | Z9: =Z123 -> 1457.3677 | AB9: =AB123 -> 1532.927 | AD9: =AD123 -> 1603.2589 | AF9: =AF123 -> 1568.5568 | AH9: =AH123 -> 1534.7542 | AJ9: =AJ123 -> 1501.8197 | AL9: =AL123 -> 1469.7222 | AN9: =AN123 -> 1438.4314
B10: % Yr/Yr Growth | H10: na | J10: =IFERROR((J9/H9-1),"na") -> 0.27251399 | L10: =IFERROR((L9/J9-1),"na") -> 0.016343209 | N10: =IFERROR((N9/L9-1),"na") -> -0.024409869 | P10: =IFERROR((P9/N9-1),"na") -> -0.080194396 | R10: =IFERROR((R9/P9-1),"na") -> 0.9114784 | T10: =IFERROR((T9/R9-1),"na") -> 0.013662179 | V10: =IFERROR((V9/T9-1),"na") -> 0.033940343 | X10: =IFERROR((X9/V9-1),"na") -> 0.068174631 | Z10: =IFERROR((Z9/X9-1),"na") -> 0.062469406 | AB10: =IFERROR((AB9/Z9-1),"na") -> 0.051846376 | AD10: =IFERROR((AD9/AB9-1),"na") -> 0.045880839 | AF10: =IFERROR((AF9/AD9-1),"na") -> -0.021644752 | AH10: =IFERROR((AH9/AF9-1),"na") -> -0.021550101 | AJ10: =IFERROR((AJ9/AH9-1),"na") -> -0.021459181 | AL10: =IFERROR((AL9/AJ9-1),"na") -> -0.02137242 | AN10: =IFERROR((AN9/AL9-1),"na") -> -0.021290272
B12: Cost of Goods Sold | H12: =H198-H22 -> 389.9484 | J12: =J198-J22 -> 482.2314 | L12: =L198-L22 -> 476.28345 | N12: =N198-N22 -> 493.94015 | P12: =P198-P22 -> 491.92995 | R12: =R198-R22 -> 878.9932 | T12: =IF(AND(T$6>='Financing Inputs'!$T$5,T$6<='Financing Inputs'!$T$19),T9*(1-'Operating Inputs'!BU$17),0) -> 869.38675 | V12: =IF(AND(V$6>='Financing Inputs'!$T$5,V$6<='Financing Inputs'!$T$19),V9*(1-'Operating Inputs'!BW$17),0) -> 898.89403 | X12: =IF(AND(X$6>='Financing Inputs'!$T$5,X$6<='Financing Inputs'!$T$19),X9*(1-'Operating Inputs'!BY$17),0) -> 960.1758 | Z12: =IF(AND(Z$6>='Financing Inputs'!$T$5,Z$6<='Financing Inputs'!$T$19),Z9*(1-'Operating Inputs'!CA$17),0) -> 1020.1574 | AB12: =IF(AND(AB$6>='Financing Inputs'!$T$5,AB$6<='Financing Inputs'!$T$19),AB9*(1-'Operating Inputs'!CC$17),0) -> 1073.0489 | AD12: =IF(AND(AD$6>='Financing Inputs'!$T$5,AD$6<='Financing Inputs'!$T$19),AD9*(1-'Operating Inputs'!CE$17),0) -> 1122.2813 | AF12: =IF(AND(AF$6>='Financing Inputs'!$T$5,AF$6<='Financing Inputs'!$T$19),AF9*(1-'Operating Inputs'!CG$17),0) -> 1097.9898 | AH12: =IF(AND(AH$6>='Financing Inputs'!$T$5,AH$6<='Financing Inputs'!$T$19),AH9*(1-'Operating Inputs'!CI$17),0) -> 1074.328 | AJ12: =IF(AND(AJ$6>='Financing Inputs'!$T$5,AJ$6<='Financing Inputs'!$T$19),AJ9*(1-'Operating Inputs'!CK$17),0) -> 1051.2738 | AL12: =IF(AND(AL$6>='Financing Inputs'!$T$5,AL$6<='Financing Inputs'!$T$19),AL9*(1-'Operating Inputs'!CM$17),0) -> 1028.8055 | AN12: =IF(AND(AN$6>='Financing Inputs'!$T$5,AN$6<='Financing Inputs'!$T$19),AN9*(1-'Operating Inputs'!CO$17),0) -> 1006.902
B13: Gross Profit | H13: =+H9-H12 -> 162.36545 | J13: =+J9-J12 -> 220.5957 | L13: =+L9-L12 -> 238.0301 | N13: =+N9-N12 -> 202.9371 | P13: =+P9-P12 -> 149.06165 | R13: =+R9-R12 -> 346.2484 | T13: =+T9-T12 -> 372.59432 | V13: =+V9-V12 -> 385.2403 | X13: =+X9-X12 -> 411.50392 | Z13: =+Z9-Z12 -> 437.21032 | AB13: =+AB9-AB12 -> 459.87809 | AD13: =+AD9-AD12 -> 480.97768 | AF13: =+AF9-AF12 -> 470.56704 | AH13: =+AH9-AH12 -> 460.42627 | AJ13: =+AJ9-AJ12 -> 450.5459 | AL13: =+AL9-AL12 -> 440.91665 | AN13: =+AN9-AN12 -> 431.52941
B14: % Margin | H14: =IFERROR(H13/H$9,"na") -> 0.29397316 | J14: =IFERROR(J13/J$9,"na") -> 0.31386909 | L14: =IFERROR(L13/L$9,"na") -> 0.33322915 | N14: =IFERROR(N13/N$9,"na") -> 0.29120925 | P14: =IFERROR(P13/P$9,"na") -> 0.23254852 | R14: =IFERROR(R13/R$9,"na") -> 0.28259602 | T14: =IFERROR(T13/T$9,"na") -> 0.3 | V14: =IFERROR(V13/V$9,"na") -> 0.3 | X14: =IFERROR(X13/X$9,"na") -> 0.3 | Z14: =IFERROR(Z13/Z$9,"na") -> 0.3 | AB14: =IFERROR(AB13/AB$9,"na") -> 0.3 | AD14: =IFERROR(AD13/AD$9,"na") -> 0.3 | AF14: =IFERROR(AF13/AF$9,"na") -> 0.3 | AH14: =IFERROR(AH13/AH$9,"na") -> 0.3 | AJ14: =IFERROR(AJ13/AJ$9,"na") -> 0.3 | AL14: =IFERROR(AL13/AL$9,"na") -> 0.3 | AN14: =IFERROR(AN13/AN$9,"na") -> 0.3
B16: SG&A | H16: =-H203-H20 -> 49.761 | J16: =-J203-J20 -> 57.3439 | L16: =-L203-L20 -> 55.4534 | N16: =-N203-N20 -> 49.8902 | P16: =-P203-P20 -> 52.972 | R16: =-R203-R20 -> 83.52115 | T16: =T9*T17 -> 59.615091 | V16: =V9*V17 -> 61.638448 | X16: =X9*X17 -> 65.840626 | Z16: =Z9*Z17 -> 69.953651 | AB16: =AB9*AB17 -> 73.580495 | AD16: =AD9*AD17 -> 76.956429 | AF16: =AF9*AF17 -> 75.290727 | AH16: =AH9*AH17 -> 73.668204 | AJ16: =AJ9*AJ17 -> 72.087345 | AL16: =AL9*AL17 -> 70.546664 | AN16: =AN9*AN17 -> 69.044706
B17: % of Revenues | H17: =IFERROR(H16/H$9,"na") -> 0.090095514 | J17: =IFERROR(J16/J$9,"na") -> 0.081590337 | L17: =IFERROR(L16/L$9,"na") -> 0.077631735 | N17: =IFERROR(N16/N$9,"na") -> 0.071591087 | P17: =IFERROR(P16/P$9,"na") -> 0.082640709 | R17: =IFERROR(R16/R$9,"na") -> 0.068167086 | T17: =IF(AND(T$6>='Financing Inputs'!$T$5,T$6<='Financing Inputs'!$T$19),'Operating Inputs'!BU$20,0) -> 0.048 | V17: =IF(AND(V$6>='Financing Inputs'!$T$5,V$6<='Financing Inputs'!$T$19),'Operating Inputs'!BW$20,0) -> 0.048 | X17: =IF(AND(X$6>='Financing Inputs'!$T$5,X$6<='Financing Inputs'!$T$19),'Operating Inputs'!BY$20,0) -> 0.048 | Z17: =IF(AND(Z$6>='Financing Inputs'!$T$5,Z$6<='Financing Inputs'!$T$19),'Operating Inputs'!CA$20,0) -> 0.048 | AB17: =IF(AND(AB$6>='Financing Inputs'!$T$5,AB$6<='Financing Inputs'!$T$19),'Operating Inputs'!CC$20,0) -> 0.048 | AD17: =IF(AND(AD$6>='Financing Inputs'!$T$5,AD$6<='Financing Inputs'!$T$19),'Operating Inputs'!CE$20,0) -> 0.048 | AF17: =IF(AND(AF$6>='Financing Inputs'!$T$5,AF$6<='Financing Inputs'!$T$19),'Operating Inputs'!CG$20,0) -> 0.048 | AH17: =IF(AND(AH$6>='Financing Inputs'!$T$5,AH$6<='Financing Inputs'!$T$19),'Operating Inputs'!CI$20,0) -> 0.048 | AJ17: =IF(AND(AJ$6>='Financing Inputs'!$T$5,AJ$6<='Financing Inputs'!$T$19),'Operating Inputs'!CK$20,0) -> 0.048 | AL17: =IF(AND(AL$6>='Financing Inputs'!$T$5,AL$6<='Financing Inputs'!$T$19),'Operating Inputs'!CM$20,0) -> 0.048 | AN17: =IF(AND(AN$6>='Financing Inputs'!$T$5,AN$6<='Financing Inputs'!$T$19),'Operating Inputs'!CO$20,0) -> 0.048
B18: Goodwill impairment | H18: =-H204 -> 0 | J18: =-J204 -> 0 | L18: =-L204 -> 0 | N18: =-N204 -> 6.35455 | P18: =-P204 -> 0 | R18: =-R204 -> 0 | T18: 0 | V18: 0 | X18: 0 | Z18: 0 | AB18: 0 | AD18: 0 | AF18: 0 | AH18: 0 | AJ18: 0 | AL18: 0 | AN18: 0
B19: % of Revenues | H19: =IFERROR(H18/H$9,"na") -> 0 | J19: =IFERROR(J18/J$9,"na") -> 0 | L19: =IFERROR(L18/L$9,"na") -> 0 | N19: =IFERROR(N18/N$9,"na") -> 0.0091186073 | P19: =IFERROR(P18/P$9,"na") -> 0 | R19: =IFERROR(R18/R$9,"na") -> 0 | T19: =IFERROR(T18/T$9,"na") -> 0 | V19: =IFERROR(V18/V$9,"na") -> 0 | X19: =IFERROR(X18/X$9,"na") -> 0 | Z19: =IFERROR(Z18/Z$9,"na") -> 0 | AB19: =IFERROR(AB18/AB$9,"na") -> 0 | AD19: =IFERROR(AD18/AD$9,"na") -> 0 | AF19: =IFERROR(AF18/AF$9,"na") -> 0 | AH19: =IFERROR(AH18/AH$9,"na") -> 0 | AJ19: =IFERROR(AJ18/AJ$9,"na") -> 0 | AL19: =IFERROR(AL18/AL$9,"na") -> 0 | AN19: =IFERROR(AN18/AN$9,"na") -> 0
B20: Share Based Compensation | H20: =H225 -> 10.33315 | J20: =J225 -> 9.42875 | L20: =L225 -> 10.89555 | N20: =N225 -> 8.1396 | P20: =P225 -> 7.30455 | R20: =R225 -> 6.1845 | T20: =R20 -> 6.1845 | V20: 0 | X20: 0 | Z20: 0 | AB20: 0 | AD20: 0 | AF20: 0 | AH20: 0 | AJ20: 0 | AL20: 0 | AN20: 0
B21: % of Revenues | H21: =IFERROR(H20/H$9,"na") -> 0.018708837 | J21: =IFERROR(J20/J$9,"na") -> 0.013415462 | L21: =IFERROR(L20/L$9,"na") -> 0.015253176 | N21: =IFERROR(N20/N$9,"na") -> 0.011680106 | P21: =IFERROR(P20/P$9,"na") -> 0.011395703 | R21: =IFERROR(R20/R$9,"na") -> 0.0050475759 | T21: =IFERROR(T20/T$9,"na") -> 0.0049795445 | V21: =IFERROR(V20/V$9,"na") -> 0 | X21: =IFERROR(X20/X$9,"na") -> 0 | Z21: =IFERROR(Z20/Z$9,"na") -> 0 | AB21: =IFERROR(AB20/AB$9,"na") -> 0 | AD21: =IFERROR(AD20/AD$9,"na") -> 0 | AF21: =IFERROR(AF20/AF$9,"na") -> 0 | AH21: =IFERROR(AH20/AH$9,"na") -> 0 | AJ21: =IFERROR(AJ20/AJ$9,"na") -> 0 | AL21: =IFERROR(AL20/AL$9,"na") -> 0 | AN21: =IFERROR(AN20/AN$9,"na") -> 0
B22: Depreciation and amortization | H22: =H222 -> 103.30775 | J22: =J222 -> 104.9959 | L22: =L222 -> 107.084 | N22: =N222 -> 127.02355 | P22: =P222 -> 134.4383 | R22: =R222 -> 155.9102 | T22: =IF(AND(T$6>='Financing Inputs'!$T$5,T$6<='Financing Inputs'!$T$19),$R$22,0) -> 155.9102 | V22: =IF(AND(V$6>='Financing Inputs'!$T$5,V$6<='Financing Inputs'!$T$19),$R$22,0) -> 155.9102 | X22: =IF(AND(X$6>='Financing Inputs'!$T$5,X$6<='Financing Inputs'!$T$19),$R$22,0) -> 155.9102 | Z22: =IF(AND(Z$6>='Financing Inputs'!$T$5,Z$6<='Financing Inputs'!$T$19),$R$22,0) -> 155.9102 | AB22: =IF(AND(AB$6>='Financing Inputs'!$T$5,AB$6<='Financing Inputs'!$T$19),$R$22,0) -> 155.9102 | AD22: =IF(AND(AD$6>='Financing Inputs'!$T$5,AD$6<='Financing Inputs'!$T$19),$R$22,0) -> 155.9102 | AF22: =IF(AND(AF$6>='Financing Inputs'!$T$5,AF$6<='Financing Inputs'!$T$19),$R$22,0) -> 155.9102 | AH22: =IF(AND(AH$6>='Financing Inputs'!$T$5,AH$6<='Financing Inputs'!$T$19),$R$22,0) -> 155.9102 | AJ22: =IF(AND(AJ$6>='Financing Inputs'!$T$5,AJ$6<='Financing Inputs'!$T$19),$R$22,0) -> 155.9102 | AL22: =IF(AND(AL$6>='Financing Inputs'!$T$5,AL$6<='Financing Inputs'!$T$19),$R$22,0) -> 155.9102 | AN22: =IF(AND(AN$6>='Financing Inputs'!$T$5,AN$6<='Financing Inputs'!$T$19),$R$22,0) -> 155.9102
B23: Operating Income | H23: =+H13-H16-H20-H18-H22 -> -1.03645 | J23: =+J13-J16-J20-J18-J22 -> 48.82715 | L23: =+L13-L16-L20-L18-L22 -> 64.59715 | N23: =+N13-N16-N20-N18-N22 -> 11.5292 | P23: =+P13-P16-P20-P18-P22 -> -45.6532 | R23: =+R13-R16-R20-R18-R22 -> 100.63255 | T23: =+T13-T16-T20-T18-T22 -> 150.88453 | V23: =+V13-V16-V20-V18-V22 -> 167.69165 | X23: =+X13-X16-X20-X18-X22 -> 189.75309 | Z23: =+Z13-Z16-Z20-Z18-Z22 -> 211.34647 | AB23: =+AB13-AB16-AB20-AB18-AB22 -> 230.3874 | AD23: =+AD13-AD16-AD20-AD18-AD22 -> 248.11105 | AF23: =+AF13-AF16-AF20-AF18-AF22 -> 239.36611 | AH23: =+AH13-AH16-AH20-AH18-AH22 -> 230.84787 | AJ23: =+AJ13-AJ16-AJ20-AJ18-AJ22 -> 222.54836 | AL23: =+AL13-AL16-AL20-AL18-AL22 -> 214.45978 | AN23: =+AN13-AN16-AN20-AN18-AN22 -> 206.57451
B24: % Margin | H24: =IFERROR(H23/H$9,"na") -> -0.0018765599 | J24: =IFERROR(J23/J$9,"na") -> 0.069472492 | L24: =IFERROR(L23/L$9,"na") -> 0.090432486 | N24: =IFERROR(N23/N$9,"na") -> 0.01654409 | P24: =IFERROR(P23/P$9,"na") -> -0.071222774 | R24: =IFERROR(R23/R$9,"na") -> 0.082132822 | T24: =IFERROR(T23/T$9,"na") -> 0.12148698 | V24: =IFERROR(V23/V$9,"na") -> 0.13058731 | X24: =IFERROR(X23/X$9,"na") -> 0.13833629 | Z24: =IFERROR(Z23/Z$9,"na") -> 0.14501931 | AB24: =IFERROR(AB23/AB$9,"na") -> 0.15029248 | AD24: =IFERROR(AD23/AD$9,"na") -> 0.1547542 | AF24: =IFERROR(AF23/AF$9,"na") -> 0.15260277 | AH24: =IFERROR(AH23/AH$9,"na") -> 0.15041357 | AJ24: =IFERROR(AJ23/AJ$9,"na") -> 0.14818581 | AL24: =IFERROR(AL23/AL$9,"na") -> 0.14591859 | AN24: =IFERROR(AN23/AN$9,"na") -> 0.14361096
B26: +Depreciation and amortization | H26: =H22 -> 103.30775 | J26: =J22 -> 104.9959 | L26: =L22 -> 107.084 | N26: =N22 -> 127.02355 | P26: =P22 -> 134.4383 | R26: =R22 -> 155.9102 | T26: =T22 -> 155.9102 | V26: =V22 -> 155.9102 | X26: =X22 -> 155.9102 | Z26: =Z22 -> 155.9102 | AB26: =AB22 -> 155.9102 | AD26: =AD22 -> 155.9102 | AF26: =AF22 -> 155.9102 | AH26: =AH22 -> 155.9102 | AJ26: =AJ22 -> 155.9102 | AL26: =AL22 -> 155.9102 | AN26: =AN22 -> 155.9102
B27: +Goodwill Impairment / Write-off | H27: =H18 -> 0 | J27: =J18 -> 0 | L27: =L18 -> 0 | N27: =N18 -> 6.35455 | P27: =P18 -> 0 | R27: =R18 -> 0 | T27: =T18 -> 0 | V27: =V18 -> 0 | X27: =X18 -> 0 | Z27: =Z18 -> 0 | AB27: =AB18 -> 0 | AD27: =AD18 -> 0 | AF27: =AF18 -> 0 | AH27: =AH18 -> 0 | AJ27: =AJ18 -> 0 | AL27: =AL18 -> 0 | AN27: =AN18 -> 0
B28: +Share Based Compensation | H28: =H20 -> 10.33315 | J28: =J20 -> 9.42875 | L28: =L20 -> 10.89555 | N28: =N20 -> 8.1396 | P28: =P20 -> 7.30455 | R28: =R20 -> 6.1845 | T28: =T20 -> 6.1845 | V28: =V20 -> 0 | X28: =X20 -> 0 | Z28: =Z20 -> 0 | AB28: =AB20 -> 0 | AD28: =AD20 -> 0 | AF28: =AF20 -> 0 | AH28: =AH20 -> 0 | AJ28: =AJ20 -> 0 | AL28: =AL20 -> 0 | AN28: =AN20 -> 0
B29: EBITDA | H29: =+H23+H26+H27+H28 -> 112.60445 | J29: =+J23+J26+J27+J28 -> 163.2518 | L29: =+L23+L26+L27+L28 -> 182.5767 | N29: =+N23+N26+N27+N28 -> 153.0469 | P29: =+P23+P26+P27+P28 -> 96.08965 | R29: =+R23+R26+R27+R28 -> 262.72725 | T29: =+T23+T26+T27+T28 -> 312.97923 | V29: =+V23+V26+V27+V28 -> 323.60185 | X29: =+X23+X26+X27+X28 -> 345.66329 | Z29: =+Z23+Z26+Z27+Z28 -> 367.25667 | AB29: =+AB23+AB26+AB27+AB28 -> 386.2976 | AD29: =+AD23+AD26+AD27+AD28 -> 404.02125 | AF29: =+AF23+AF26+AF27+AF28 -> 395.27631 | AH29: =+AH23+AH26+AH27+AH28 -> 386.75807 | AJ29: =+AJ23+AJ26+AJ27+AJ28 -> 378.45856 | AL29: =+AL23+AL26+AL27+AL28 -> 370.36998 | AN29: =+AN23+AN26+AN27+AN28 -> 362.48471
B30: % Margin | H30: =IFERROR(H29/H$9,"na") -> 0.20387765 | J30: =IFERROR(J29/J$9,"na") -> 0.23227875 | L30: =IFERROR(L29/L$9,"na") -> 0.25559742 | N30: =IFERROR(N29/N$9,"na") -> 0.21961816 | P30: =IFERROR(P29/P$9,"na") -> 0.14990781 | R30: =IFERROR(R29/R$9,"na") -> 0.21442893 | T30: =IFERROR(T29/T$9,"na") -> 0.252 | V30: =IFERROR(V29/V$9,"na") -> 0.252 | X30: =IFERROR(X29/X$9,"na") -> 0.252 | Z30: =IFERROR(Z29/Z$9,"na") -> 0.252 | AB30: =IFERROR(AB29/AB$9,"na") -> 0.252 | AD30: =IFERROR(AD29/AD$9,"na") -> 0.252 | AF30: =IFERROR(AF29/AF$9,"na") -> 0.252 | AH30: =IFERROR(AH29/AH$9,"na") -> 0.252 | AJ30: =IFERROR(AJ29/AJ$9,"na") -> 0.252 | AL30: =IFERROR(AL29/AL$9,"na") -> 0.252 | AN30: =IFERROR(AN29/AN$9,"na") -> 0.252
B31: % Yr/Yr Growth | H31: na | J31: =IFERROR((J29/H29-1),"na") -> 0.44978107 | L31: =IFERROR((L29/J29-1),"na") -> 0.11837481 | N31: =IFERROR((N29/L29-1),"na") -> -0.16173915 | P31: =IFERROR((P29/N29-1),"na") -> -0.37215553 | R31: =IFERROR((R29/P29-1),"na") -> 1.7341889 | T31: =IFERROR((T29/R29-1),"na") -> 0.19127053 | V31: =IFERROR((V29/T29-1),"na") -> 0.033940343 | X31: =IFERROR((X29/V29-1),"na") -> 0.068174631 | Z31: =IFERROR((Z29/X29-1),"na") -> 0.062469406 | AB31: =IFERROR((AB29/Z29-1),"na") -> 0.051846376 | AD31: =IFERROR((AD29/AB29-1),"na") -> 0.045880839 | AF31: =IFERROR((AF29/AD29-1),"na") -> -0.021644752 | AH31: =IFERROR((AH29/AF29-1),"na") -> -0.021550101 | AJ31: =IFERROR((AJ29/AH29-1),"na") -> -0.021459181 | AL31: =IFERROR((AL29/AJ29-1),"na") -> -0.02137242 | AN31: =IFERROR((AN29/AL29-1),"na") -> -0.021290272
B33: Capital Expenditures | H33: =H247 -> -219.57065 | J33: =J247 -> -130.22885 | L33: =L247 -> -133.8113 | N33: =N247 -> -19.2318 | P33: =P247 -> -7.9059 | R33: =R247 -> -18.6086 | T33: =-IF(AND(T$6>='Financing Inputs'!$T$5,T$6<='Financing Inputs'!$T$19),'Operating Inputs'!BU$22,0) -> -40 | V33: =-IF(AND(V$6>='Financing Inputs'!$T$5,V$6<='Financing Inputs'!$T$19),'Operating Inputs'!BW$22,0) -> -40 | X33: =-IF(AND(X$6>='Financing Inputs'!$T$5,X$6<='Financing Inputs'!$T$19),'Operating Inputs'!BY$22,0) -> -40 | Z33: =-IF(AND(Z$6>='Financing Inputs'!$T$5,Z$6<='Financing Inputs'!$T$19),'Operating Inputs'!CA$22,0) -> -40 | AB33: =-IF(AND(AB$6>='Financing Inputs'!$T$5,AB$6<='Financing Inputs'!$T$19),'Operating Inputs'!CC$22,0) -> -40 | AD33: =-IF(AND(AD$6>='Financing Inputs'!$T$5,AD$6<='Financing Inputs'!$T$19),'Operating Inputs'!CE$22,0) -> -40 | AF33: =-IF(AND(AF$6>='Financing Inputs'!$T$5,AF$6<='Financing Inputs'!$T$19),'Operating Inputs'!CG$22,0) -> -40 | AH33: =-IF(AND(AH$6>='Financing Inputs'!$T$5,AH$6<='Financing Inputs'!$T$19),'Operating Inputs'!CI$22,0) -> -40 | AJ33: =-IF(AND(AJ$6>='Financing Inputs'!$T$5,AJ$6<='Financing Inputs'!$T$19),'Operating Inputs'!CK$22,0) -> -40 | AL33: =-IF(AND(AL$6>='Financing Inputs'!$T$5,AL$6<='Financing Inputs'!$T$19),'Operating Inputs'!CM$22,0) -> -40 | AN33: =-IF(AND(AN$6>='Financing Inputs'!$T$5,AN$6<='Financing Inputs'!$T$19),'Operating Inputs'!CO$22,0) -> -40
B34: Deferred Recertification and Dry Dock costs, net | H34: =+H240 -> 0 | J34: =+J240 -> 0 | L34: =+L240 -> 0 | N34: =+N240 -> 0 | P34: =+P240 -> -9.139 | R34: =+R240 -> -59.3959 | T34: =-IF(AND(T$6>='Financing Inputs'!$T$5,T$6<='Financing Inputs'!$T$19),'Operating Inputs'!BU$23,0) -> -45 | V34: =-IF(AND(V$6>='Financing Inputs'!$T$5,V$6<='Financing Inputs'!$T$19),'Operating Inputs'!BW$23,0) -> -45 | X34: =-IF(AND(X$6>='Financing Inputs'!$T$5,X$6<='Financing Inputs'!$T$19),'Operating Inputs'!BY$23,0) -> -45 | Z34: =-IF(AND(Z$6>='Financing Inputs'!$T$5,Z$6<='Financing Inputs'!$T$19),'Operating Inputs'!CA$23,0) -> -45 | AB34: =-IF(AND(AB$6>='Financing Inputs'!$T$5,AB$6<='Financing Inputs'!$T$19),'Operating Inputs'!CC$23,0) -> -45 | AD34: =-IF(AND(AD$6>='Financing Inputs'!$T$5,AD$6<='Financing Inputs'!$T$19),'Operating Inputs'!CE$23,0) -> -45 | AF34: =-IF(AND(AF$6>='Financing Inputs'!$T$5,AF$6<='Financing Inputs'!$T$19),'Operating Inputs'!CG$23,0) -> -45 | AH34: =-IF(AND(AH$6>='Financing Inputs'!$T$5,AH$6<='Financing Inputs'!$T$19),'Operating Inputs'!CI$23,0) -> -45 | AJ34: =-IF(AND(AJ$6>='Financing Inputs'!$T$5,AJ$6<='Financing Inputs'!$T$19),'Operating Inputs'!CK$23,0) -> -45 | AL34: =-IF(AND(AL$6>='Financing Inputs'!$T$5,AL$6<='Financing Inputs'!$T$19),'Operating Inputs'!CM$23,0) -> -45 | AN34: =-IF(AND(AN$6>='Financing Inputs'!$T$5,AN$6<='Financing Inputs'!$T$19),'Operating Inputs'!CO$23,0) -> -45
B35: Total Capital Expenditure | H35: =SUM(H33:H34) -> -219.57065 | J35: =SUM(J33:J34) -> -130.22885 | L35: =SUM(L33:L34) -> -133.8113 | N35: =SUM(N33:N34) -> -19.2318 | P35: =SUM(P33:P34) -> -17.0449 | R35: =SUM(R33:R34) -> -78.0045 | T35: =SUM(T33:T34) -> -85 | V35: =SUM(V33:V34) -> -85 | X35: =SUM(X33:X34) -> -85 | Z35: =SUM(Z33:Z34) -> -85 | AB35: =SUM(AB33:AB34) -> -85 | AD35: =SUM(AD33:AD34) -> -85 | AF35: =SUM(AF33:AF34) -> -85 | AH35: =SUM(AH33:AH34) -> -85 | AJ35: =SUM(AJ33:AJ34) -> -85 | AL35: =SUM(AL33:AL34) -> -85 | AN35: =SUM(AN33:AN34) -> -85
B36: Operating Cash Flow | H36: =+H29+H35 -> -106.9662 | J36: =+J29+J35 -> 33.02295 | L36: =+L29+L35 -> 48.7654 | N36: =+N29+N35 -> 133.8151 | P36: =+P29+P35 -> 79.04475 | R36: =+R29+R35 -> 184.72275 | T36: =+T29+T35 -> 227.97923 | V36: =+V29+V35 -> 238.60185 | X36: =+X29+X35 -> 260.66329 | Z36: =+Z29+Z35 -> 282.25667 | AB36: =+AB29+AB35 -> 301.2976 | AD36: =+AD29+AD35 -> 319.02125 | AF36: =+AF29+AF35 -> 310.27631 | AH36: =+AH29+AH35 -> 301.75807 | AJ36: =+AJ29+AJ35 -> 293.45856 | AL36: =+AL29+AL35 -> 285.36998 | AN36: =+AN29+AN35 -> 277.48471
B37: % Margin | H37: =IFERROR(H36/H$9,"na") -> -0.19366923 | J37: =IFERROR(J36/J$9,"na") -> 0.04698588 | L37: =IFERROR(L36/L$9,"na") -> 0.0682689 | N37: =IFERROR(N36/N$9,"na") -> 0.19202105 | P37: =IFERROR(P36/P$9,"na") -> 0.12331636 | R37: =IFERROR(R36/R$9,"na") -> 0.15076435 | T37: =IFERROR(T36/T$9,"na") -> 0.18356095 | V37: =IFERROR(V36/V$9,"na") -> 0.18580755 | X37: =IFERROR(X36/X$9,"na") -> 0.19003218 | Z37: =IFERROR(Z36/Z$9,"na") -> 0.19367567 | AB37: =IFERROR(AB36/AB$9,"na") -> 0.19655052 | AD37: =IFERROR(AD36/AD$9,"na") -> 0.19898299 | AF37: =IFERROR(AF36/AF$9,"na") -> 0.19781006 | AH37: =IFERROR(AH36/AH$9,"na") -> 0.19661654 | AJ37: =IFERROR(AJ36/AJ$9,"na") -> 0.19540199 | AL37: =IFERROR(AL36/AL$9,"na") -> 0.19416594 | AN37: =IFERROR(AN36/AN$9,"na") -> 0.19290785
B39: Cash Interest | H39: =H285 -> -7.5392 | J39: =J285 -> -4.2028 | L39: =L285 -> 1.4516 | N39: =N285 -> -17.4705 | P39: =P285 -> -19.0209 | R39: =R285 -> -14.0942 | T39: =Debt!H16+Debt!H23+Debt!H30+Debt!H37 -> 0 | V39: =Debt!J16+Debt!J23+Debt!J30+Debt!J37 -> -145.7325 | X39: =Debt!L16+Debt!L23+Debt!L30+Debt!L37 -> -142.20398 | Z39: =Debt!N16+Debt!N23+Debt!N30+Debt!N37 -> -138.3579 | AB39: =Debt!P16+Debt!P23+Debt!P30+Debt!P37 -> -134.16567 | AD39: =Debt!R16+Debt!R23+Debt!R30+Debt!R37 -> -129.59613 | AF39: =Debt!T16+Debt!T23+Debt!T30+Debt!T37 -> -124.61534 | AH39: =Debt!V16+Debt!V23+Debt!V30+Debt!V37 -> -119.18628 | AJ39: =Debt!X16+Debt!X23+Debt!X30+Debt!X37 -> -113.2686 | AL39: =Debt!Z16+Debt!Z23+Debt!Z30+Debt!Z37 -> -106.81834 | AN39: =Debt!AB16+Debt!AB23+Debt!AB30+Debt!AB37 -> -99.787543
B40: Refinance Interest Expense | T40: =Debt!H46+Debt!H54 -> 0 | V40: =Debt!J46+Debt!J54 -> 0 | X40: =Debt!L46+Debt!L54 -> 0 | Z40: =Debt!N46+Debt!N54 -> 0 | AB40: =Debt!P46+Debt!P54 -> 0 | AD40: =Debt!R46+Debt!R54 -> 0 | AF40: =Debt!T46+Debt!T54 -> 0 | AH40: =Debt!V46+Debt!V54 -> 0 | AJ40: =Debt!X46+Debt!X54 -> 0 | AL40: =Debt!Z46+Debt!Z54 -> 0 | AN40: =Debt!AB46+Debt!AB54 -> 0
B41: Cash Taxes (Paid) / Benefits | H41: =H291 -> -18.84895 | J41: =J291 -> -3.6727 | L41: =L291 -> -8.3885 | N41: =N291 -> -6.9407 | P41: =P291 -> 11.7477 | R41: =R291 -> -6.8761 | T41: =-IF(AND(T$6>='Financing Inputs'!$T$5,T$6<='Financing Inputs'!$T$19),'Operating Inputs'!BU$25,0)*(T23+T39+T40) -> -31.685751 | V41: =-IF(AND(V$6>='Financing Inputs'!$T$5,V$6<='Financing Inputs'!$T$19),'Operating Inputs'!BW$25,0)*(V23+V39+V40) -> -4.6114219 | X41: =-IF(AND(X$6>='Financing Inputs'!$T$5,X$6<='Financing Inputs'!$T$19),'Operating Inputs'!BY$25,0)*(X23+X39+X40) -> -9.9853124 | Z41: =-IF(AND(Z$6>='Financing Inputs'!$T$5,Z$6<='Financing Inputs'!$T$19),'Operating Inputs'!CA$25,0)*(Z23+Z39+Z40) -> -15.3276 | AB41: =-IF(AND(AB$6>='Financing Inputs'!$T$5,AB$6<='Financing Inputs'!$T$19),'Operating Inputs'!CC$25,0)*(AB23+AB39+AB40) -> -20.206563 | AD41: =-IF(AND(AD$6>='Financing Inputs'!$T$5,AD$6<='Financing Inputs'!$T$19),'Operating Inputs'!CE$25,0)*(AD23+AD39+AD40) -> -24.888133 | AF41: =-IF(AND(AF$6>='Financing Inputs'!$T$5,AF$6<='Financing Inputs'!$T$19),'Operating Inputs'!CG$25,0)*(AF23+AF39+AF40) -> -24.097662 | AH41: =-IF(AND(AH$6>='Financing Inputs'!$T$5,AH$6<='Financing Inputs'!$T$19),'Operating Inputs'!CI$25,0)*(AH23+AH39+AH40) -> -23.448934 | AJ41: =-IF(AND(AJ$6>='Financing Inputs'!$T$5,AJ$6<='Financing Inputs'!$T$19),'Operating Inputs'!CK$25,0)*(AJ23+AJ39+AJ40) -> -22.948749 | AL41: =-IF(AND(AL$6>='Financing Inputs'!$T$5,AL$6<='Financing Inputs'!$T$19),'Operating Inputs'!CM$25,0)*(AL23+AL39+AL40) -> -22.604704 | AN41: =-IF(AND(AN$6>='Financing Inputs'!$T$5,AN$6<='Financing Inputs'!$T$19),'Operating Inputs'!CO$25,0)*(AN23+AN39+AN40) -> -22.425262
B42: Working Capital Source / (Use) | H42: =+H236+H237+H239+H241 -> -35.1443 | J42: =+J236+J237+J239+J241 -> 33.95395 | L42: =+L236+L237+L239+L241 -> -14.89125 | N42: =+N236+N237+N239+N241 -> -38.7353 | P42: =+P236+P237+P239+P241 -> 49.98045 | R42: =+R236+R237+R239+R241 -> -43.59645 | T42: =IF(AND(T$6>='Financing Inputs'!$T$5,T$6<='Financing Inputs'!$T$19),'Operating Inputs'!BU$27,0) -> 20 | V42: =IF(AND(V$6>='Financing Inputs'!$T$5,V$6<='Financing Inputs'!$T$19),'Operating Inputs'!BW$27,0) -> 20 | X42: =IF(AND(X$6>='Financing Inputs'!$T$5,X$6<='Financing Inputs'!$T$19),'Operating Inputs'!BY$27,0) -> 20 | Z42: =IF(AND(Z$6>='Financing Inputs'!$T$5,Z$6<='Financing Inputs'!$T$19),'Operating Inputs'!CA$27,0) -> 20 | AB42: =IF(AND(AB$6>='Financing Inputs'!$T$5,AB$6<='Financing Inputs'!$T$19),'Operating Inputs'!CC$27,0) -> 20 | AD42: =IF(AND(AD$6>='Financing Inputs'!$T$5,AD$6<='Financing Inputs'!$T$19),'Operating Inputs'!CE$27,0) -> 20 | AF42: =IF(AND(AF$6>='Financing Inputs'!$T$5,AF$6<='Financing Inputs'!$T$19),'Operating Inputs'!CG$27,0) -> 20 | AH42: =IF(AND(AH$6>='Financing Inputs'!$T$5,AH$6<='Financing Inputs'!$T$19),'Operating Inputs'!CI$27,0) -> 20 | AJ42: =IF(AND(AJ$6>='Financing Inputs'!$T$5,AJ$6<='Financing Inputs'!$T$19),'Operating Inputs'!CK$27,0) -> 20 | AL42: =IF(AND(AL$6>='Financing Inputs'!$T$5,AL$6<='Financing Inputs'!$T$19),'Operating Inputs'!CM$27,0) -> 20 | AN42: =IF(AND(AN$6>='Financing Inputs'!$T$5,AN$6<='Financing Inputs'!$T$19),'Operating Inputs'!CO$27,0) -> 20
B43: Free Cash Flow | H43: =+H36+H39+H40+H41+H42 -> -168.49865 | J43: =+J36+J39+J40+J41+J42 -> 59.1014 | L43: =+L36+L39+L40+L41+L42 -> 26.93725 | N43: =+N36+N39+N40+N41+N42 -> 70.6686 | P43: =+P36+P39+P40+P41+P42 -> 121.752 | R43: =+R36+R39+R40+R41+R42 -> 120.156 | T43: =+T36+T39+T40+T41+T42 -> 216.29348 | V43: =+V36+V39+V40+V41+V42 -> 108.25793 | X43: =+X36+X39+X40+X41+X42 -> 128.47399 | Z43: =+Z36+Z39+Z40+Z41+Z42 -> 148.57117 | AB43: =+AB36+AB39+AB40+AB41+AB42 -> 166.92537 | AD43: =+AD36+AD39+AD40+AD41+AD42 -> 184.53699 | AF43: =+AF36+AF39+AF40+AF41+AF42 -> 181.56331 | AH43: =+AH36+AH39+AH40+AH41+AH42 -> 179.12286 | AJ43: =+AJ36+AJ39+AJ40+AJ41+AJ42 -> 177.24121 | AL43: =+AL36+AL39+AL40+AL41+AL42 -> 175.94694 | AN43: =+AN36+AN39+AN40+AN41+AN42 -> 175.2719
B45: Share Issued / (Repurchases) | H45: =H266 -> 208.5288 | J45: =J266 -> 0 | L45: =L266 -> 0 | N45: =N266 -> 0 | P45: =P266 -> 0 | R45: =R266 -> -11.3886 | T45: 0 | V45: 0 | X45: 0 | Z45: 0 | AB45: 0 | AD45: 0 | AF45: 0 | AH45: 0 | AJ45: 0 | AL45: 0 | AN45: 0
B46: Free Cash Flow Post-Equity Returns | H46: =+H43+H45 -> 40.03015 | J46: =+J43+J45 -> 59.1014 | L46: =+L43+L45 -> 26.93725 | N46: =+N43+N45 -> 70.6686 | P46: =+P43+P45 -> 121.752 | R46: =+R43+R45 -> 108.7674 | T46: =+T43+T45 -> 216.29348 | V46: =+V43+V45 -> 108.25793 | X46: =+X43+X45 -> 128.47399 | Z46: =+Z43+Z45 -> 148.57117 | AB46: =+AB43+AB45 -> 166.92537 | AD46: =+AD43+AD45 -> 184.53699 | AF46: =+AF43+AF45 -> 181.56331 | AH46: =+AH43+AH45 -> 179.12286 | AJ46: =+AJ43+AJ45 -> 177.24121 | AL46: =+AL43+AL45 -> 175.94694 | AN46: =+AN43+AN45 -> 175.2719
B48: Business Purchase | T48: =-IF(T$6='Financing Inputs'!$T$5,'Financing Inputs'!$L$7,0) -> -2159 | V48: =-IF(V$6='Financing Inputs'!$T$5,'Financing Inputs'!$L$7,0) -> 0 | X48: =-IF(X$6='Financing Inputs'!$T$5,'Financing Inputs'!$L$7,0) -> 0 | Z48: =-IF(Z$6='Financing Inputs'!$T$5,'Financing Inputs'!$L$7,0) -> 0 | AB48: =-IF(AB$6='Financing Inputs'!$T$5,'Financing Inputs'!$L$7,0) -> 0 | AD48: =-IF(AD$6='Financing Inputs'!$T$5,'Financing Inputs'!$L$7,0) -> 0 | AF48: =-IF(AF$6='Financing Inputs'!$T$5,'Financing Inputs'!$L$7,0) -> 0 | AH48: =-IF(AH$6='Financing Inputs'!$T$5,'Financing Inputs'!$L$7,0) -> 0 | AJ48: =-IF(AJ$6='Financing Inputs'!$T$5,'Financing Inputs'!$L$7,0) -> 0 | AL48: =-IF(AL$6='Financing Inputs'!$T$5,'Financing Inputs'!$L$7,0) -> 0 | AN48: =-IF(AN$6='Financing Inputs'!$T$5,'Financing Inputs'!$L$7,0) -> 0
B49: Business Sale | T49: =IF(T$6='Financing Inputs'!$T$19,'Financing Inputs'!$T$22,0) -> 0 | V49: =IF(V$6='Financing Inputs'!$T$19,'Financing Inputs'!$T$22,0) -> 0 | X49: =IF(X$6='Financing Inputs'!$T$19,'Financing Inputs'!$T$22,0) -> 0 | Z49: =IF(Z$6='Financing Inputs'!$T$19,'Financing Inputs'!$T$22,0) -> 0 | AB49: =IF(AB$6='Financing Inputs'!$T$19,'Financing Inputs'!$T$22,0) -> 0 | AD49: =IF(AD$6='Financing Inputs'!$T$19,'Financing Inputs'!$T$22,0) -> 0 | AF49: =IF(AF$6='Financing Inputs'!$T$19,'Financing Inputs'!$T$22,0) -> 0 | AH49: =IF(AH$6='Financing Inputs'!$T$19,'Financing Inputs'!$T$22,0) -> 0 | AJ49: =IF(AJ$6='Financing Inputs'!$T$19,'Financing Inputs'!$T$22,0) -> 0 | AL49: =IF(AL$6='Financing Inputs'!$T$19,'Financing Inputs'!$T$22,0) -> 0 | AN49: =IF(AN$6='Financing Inputs'!$T$19,'Financing Inputs'!$T$22,0) -> 1812.4235
B50: Equity 1 Issuance | T50: =IF(T$6='Financing Inputs'!$T$5,'Financing Inputs'!$F$7,0)-IF('Financing Inputs'!$T$31<>1,IF(T46+T53+T56<0,(T46+T53+T56)*'Financing Inputs'!$T$25,0),0)-IF('Financing Inputs'!$T$31=2,(Debt!H28+Debt!H35)*'Financing Inputs'!$T$25,0)-IF('Financing Inputs'!$T$31=1,IF(T46+T53+T54+T56<0,(T46+T53+T54+T56)*'Financing Inputs'!$T$25,0))-IF(T46+T53+IF('Financing Inputs'!$T$31=1,T54,0)+T56,0) -> 269.875 | V50: =IF(V$6='Financing Inputs'!$T$5,'Financing Inputs'!$F$7,0)-IF('Financing Inputs'!$T$31<>1,IF(V46+V53+V56<0,(V46+V53+V56)*'Financing Inputs'!$T$25,0),0)-IF('Financing Inputs'!$T$31=2,(Debt!J28+Debt!J35)*'Financing Inputs'!$T$25,0)-IF('Financing Inputs'!$T$31=1,IF(V46+V53+V54+V56<0,(V46+V53+V54+V56)*'Financing Inputs'!$T$25,0))-IF(V46+V53+IF('Financing Inputs'!$T$31=1,V54,0)+V56,0) -> 0 | X50: =IF(X$6='Financing Inputs'!$T$5,'Financing Inputs'!$F$7,0)-IF('Financing Inputs'!$T$31<>1,IF(X46+X53+X56<0,(X46+X53+X56)*'Financing Inputs'!$T$25,0),0)-IF('Financing Inputs'!$T$31=2,(Debt!L28+Debt!L35)*'Financing Inputs'!$T$25,0)-IF('Financing Inputs'!$T$31=1,IF(X46+X53+X54+X56<0,(X46+X53+X54+X56)*'Financing Inputs'!$T$25,0))-IF(X46+X53+IF('Financing Inputs'!$T$31=1,X54,0)+X56,0) -> 0 | Z50: =IF(Z$6='Financing Inputs'!$T$5,'Financing Inputs'!$F$7,0)-IF('Financing Inputs'!$T$31<>1,IF(Z46+Z53+Z56<0,(Z46+Z53+Z56)*'Financing Inputs'!$T$25,0),0)-IF('Financing Inputs'!$T$31=2,(Debt!N28+Debt!N35)*'Financing Inputs'!$T$25,0)-IF('Financing Inputs'!$T$31=1,IF(Z46+Z53+Z54+Z56<0,(Z46+Z53+Z54+Z56)*'Financing Inputs'!$T$25,0))-IF(Z46+Z53+IF('Financing Inputs'!$T$31=1,Z54,0)+Z56,0) -> 0 | AB50: =IF(AB$6='Financing Inputs'!$T$5,'Financing Inputs'!$F$7,0)-IF('Financing Inputs'!$T$31<>1,IF(AB46+AB53+AB56<0,(AB46+AB53+AB56)*'Financing Inputs'!$T$25,0),0)-IF('Financing Inputs'!$T$31=2,(Debt!P28+Debt!P35)*'Financing Inputs'!$T$25,0)-IF('Financing Inputs'!$T$31=1,IF(AB46+AB53+AB54+AB56<0,(AB46+AB53+AB54+AB56)*'Financing Inputs'!$T$25,0))-IF(AB46+AB53+IF('Financing Inputs'!$T$31=1,AB54,0)+AB56,0) -> 0 | AD50: =IF(AD$6='Financing Inputs'!$T$5,'Financing Inputs'!$F$7,0)-IF('Financing Inputs'!$T$31<>1,IF(AD46+AD53+AD56<0,(AD46+AD53+AD56)*'Financing Inputs'!$T$25,0),0)-IF('Financing Inputs'!$T$31=2,(Debt!R28+Debt!R35)*'Financing Inputs'!$T$25,0)-IF('Financing Inputs'!$T$31=1,IF(AD46+AD53+AD54+AD56<0,(AD46+AD53+AD54+AD56)*'Financing Inputs'!$T$25,0))-IF(AD46+AD53+IF('Financing Inputs'!$T$31=1,AD54,0)+AD56,0) -> 0 | AF50: =IF(AF$6='Financing Inputs'!$T$5,'Financing Inputs'!$F$7,0)-IF('Financing Inputs'!$T$31<>1,IF(AF46+AF53+AF56<0,(AF46+AF53+AF56)*'Financing Inputs'!$T$25,0),0)-IF('Financing Inputs'!$T$31=2,(Debt!T28+Debt!T35)*'Financing Inputs'!$T$25,0)-IF('Financing Inputs'!$T$31=1,IF(AF46+AF53+AF54+AF56<0,(AF46+AF53+AF54+AF56)*'Financing Inputs'!$T$25,0))-IF(AF46+AF53+IF('Financing Inputs'!$T$31=1,AF54,0)+AF56,0) -> 0 | AH50: =IF(AH$6='Financing Inputs'!$T$5,'Financing Inputs'!$F$7,0)-IF('Financing Inputs'!$T$31<>1,IF(AH46+AH53+AH56<0,(AH46+AH53+AH56)*'Financing Inputs'!$T$25,0),0)-IF('Financing Inputs'!$T$31=2,(Debt!V28+Debt!V35)*'Financing Inputs'!$T$25,0)-IF('Financing Inputs'!$T$31=1,IF(AH46+AH53+AH54+AH56<0,(AH46+AH53+AH54+AH56)*'Financing Inputs'!$T$25,0))-IF(AH46+AH53+IF('Financing Inputs'!$T$31=1,AH54,0)+AH56,0) -> 0 | AJ50: =IF(AJ$6='Financing Inputs'!$T$5,'Financing Inputs'!$F$7,0)-IF('Financing Inputs'!$T$31<>1,IF(AJ46+AJ53+AJ56<0,(AJ46+AJ53+AJ56)*'Financing Inputs'!$T$25,0),0)-IF('Financing Inputs'!$T$31=2,(Debt!X28+Debt!X35)*'Financing Inputs'!$T$25,0)-IF('Financing Inputs'!$T$31=1,IF(AJ46+AJ53+AJ54+AJ56<0,(AJ46+AJ53+AJ54+AJ56)*'Financing Inputs'!$T$25,0))-IF(AJ46+AJ53+IF('Financing Inputs'!$T$31=1,AJ54,0)+AJ56,0) -> 0 | AL50: =IF(AL$6='Financing Inputs'!$T$5,'Financing Inputs'!$F$7,0)-IF('Financing Inputs'!$T$31<>1,IF(AL46+AL53+AL56<0,(AL46+AL53+AL56)*'Financing Inputs'!$T$25,0),0)-IF('Financing Inputs'!$T$31=2,(Debt!Z28+Debt!Z35)*'Financing Inputs'!$T$25,0)-IF('Financing Inputs'!$T$31=1,IF(AL46+AL53+AL54+AL56<0,(AL46+AL53+AL54+AL56)*'Financing Inputs'!$T$25,0))-IF(AL46+AL53+IF('Financing Inputs'!$T$31=1,AL54,0)+AL56,0) -> 0 | AN50: =IF(AN$6='Financing Inputs'!$T$5,'Financing Inputs'!$F$7,0)-IF('Financing Inputs'!$T$31<>1,IF(AN46+AN53+AN56<0,(AN46+AN53+AN56)*'Financing Inputs'!$T$25,0),0)-IF('Financing Inputs'!$T$31=2,(Debt!AB28+Debt!AB35)*'Financing Inputs'!$T$25,0)-IF('Financing Inputs'!$T$31=1,IF(AN46+AN53+AN54+AN56<0,(AN46+AN53+AN54+AN56)*'Financing Inputs'!$T$25,0))-IF(AN46+AN53+IF('Financing Inputs'!$T$31=1,AN54,0)+AN56,0) -> 0
B51: Equity 2 Issuance | T51: =IF(T$6='Financing Inputs'!$T$5,'Financing Inputs'!$F$8,0) -> 269.875 | V51: =IF(V$6='Financing Inputs'!$T$5,'Financing Inputs'!$F$8,0) -> 0 | X51: =IF(X$6='Financing Inputs'!$T$5,'Financing Inputs'!$F$8,0) -> 0 | Z51: =IF(Z$6='Financing Inputs'!$T$5,'Financing Inputs'!$F$8,0) -> 0 | AB51: =IF(AB$6='Financing Inputs'!$T$5,'Financing Inputs'!$F$8,0) -> 0 | AD51: =IF(AD$6='Financing Inputs'!$T$5,'Financing Inputs'!$F$8,0) -> 0 | AF51: =IF(AF$6='Financing Inputs'!$T$5,'Financing Inputs'!$F$8,0) -> 0 | AH51: =IF(AH$6='Financing Inputs'!$T$5,'Financing Inputs'!$F$8,0) -> 0 | AJ51: =IF(AJ$6='Financing Inputs'!$T$5,'Financing Inputs'!$F$8,0) -> 0 | AL51: =IF(AL$6='Financing Inputs'!$T$5,'Financing Inputs'!$F$8,0) -> 0 | AN51: =IF(AN$6='Financing Inputs'!$T$5,'Financing Inputs'!$F$8,0) -> 0
B52: Debt Issuance | T52: =IF(T$6='Financing Inputs'!$T$5,'Financing Inputs'!$F$11,0) -> 1619.25 | V52: =IF(V$6='Financing Inputs'!$T$5,'Financing Inputs'!$F$11,0) -> 0 | X52: =IF(X$6='Financing Inputs'!$T$5,'Financing Inputs'!$F$11,0) -> 0 | Z52: =IF(Z$6='Financing Inputs'!$T$5,'Financing Inputs'!$F$11,0) -> 0 | AB52: =IF(AB$6='Financing Inputs'!$T$5,'Financing Inputs'!$F$11,0) -> 0 | AD52: =IF(AD$6='Financing Inputs'!$T$5,'Financing Inputs'!$F$11,0) -> 0 | AF52: =IF(AF$6='Financing Inputs'!$T$5,'Financing Inputs'!$F$11,0) -> 0 | AH52: =IF(AH$6='Financing Inputs'!$T$5,'Financing Inputs'!$F$11,0) -> 0 | AJ52: =IF(AJ$6='Financing Inputs'!$T$5,'Financing Inputs'!$F$11,0) -> 0 | AL52: =IF(AL$6='Financing Inputs'!$T$5,'Financing Inputs'!$F$11,0) -> 0 | AN52: =IF(AN$6='Financing Inputs'!$T$5,'Financing Inputs'!$F$11,0) -> 0
B53: Debt Amortization | T53: =Debt!H13+Debt!H20+Debt!H34 -> 0 | V53: =Debt!J13+Debt!J20+Debt!J34 -> -39.205752 | X53: =Debt!L13+Debt!L20+Debt!L34 -> -42.734269 | Z53: =Debt!N13+Debt!N20+Debt!N34 -> -46.580354 | AB53: =Debt!P13+Debt!P20+Debt!P34 -> -50.772585 | AD53: =Debt!R13+Debt!R20+Debt!R34 -> -55.342118 | AF53: =Debt!T13+Debt!T20+Debt!T34 -> -60.322909 | AH53: =Debt!V13+Debt!V20+Debt!V34 -> -65.75197 | AJ53: =Debt!X13+Debt!X20+Debt!X34 -> -71.669648 | AL53: =Debt!Z13+Debt!Z20+Debt!Z34 -> -78.119916 | AN53: =Debt!AB13+Debt!AB20+Debt!AB34 -> -85.150709
B54: Debt Balloon Payment | T54: =Debt!H14+Debt!H21+Debt!H28+Debt!H35 -> 0 | V54: =Debt!J14+Debt!J21+Debt!J28+Debt!J35 -> 0 | X54: =Debt!L14+Debt!L21+Debt!L28+Debt!L35 -> 0 | Z54: =Debt!N14+Debt!N21+Debt!N28+Debt!N35 -> 0 | AB54: =Debt!P14+Debt!P21+Debt!P28+Debt!P35 -> 0 | AD54: =Debt!R14+Debt!R21+Debt!R28+Debt!R35 -> 0 | AF54: =Debt!T14+Debt!T21+Debt!T28+Debt!T35 -> 0 | AH54: =Debt!V14+Debt!V21+Debt!V28+Debt!V35 -> 0 | AJ54: =Debt!X14+Debt!X21+Debt!X28+Debt!X35 -> 0 | AL54: =Debt!Z14+Debt!Z21+Debt!Z28+Debt!Z35 -> 0 | AN54: =Debt!AB14+Debt!AB21+Debt!AB28+Debt!AB35 -> -1023.5998
B55: Refinance Debt Issuance | T55: =Debt!H42+Debt!H50 -> 0 | V55: =Debt!J42+Debt!J50 -> 0 | X55: =Debt!L42+Debt!L50 -> 0 | Z55: =Debt!N42+Debt!N50 -> 0 | AB55: =Debt!P42+Debt!P50 -> 0 | AD55: =Debt!R42+Debt!R50 -> 0 | AF55: =Debt!T42+Debt!T50 -> 0 | AH55: =Debt!V42+Debt!V50 -> 0 | AJ55: =Debt!X42+Debt!X50 -> 0 | AL55: =Debt!Z42+Debt!Z50 -> 0 | AN55: =Debt!AB42+Debt!AB50 -> 0
B56: Refinance Debt Amortization | T56: =Debt!H43+Debt!H51 -> 0 | V56: =Debt!J43+Debt!J51 -> 0 | X56: =Debt!L43+Debt!L51 -> 0 | Z56: =Debt!N43+Debt!N51 -> 0 | AB56: =Debt!P43+Debt!P51 -> 0 | AD56: =Debt!R43+Debt!R51 -> 0 | AF56: =Debt!T43+Debt!T51 -> 0 | AH56: =Debt!V43+Debt!V51 -> 0 | AJ56: =Debt!X43+Debt!X51 -> 0 | AL56: =Debt!Z43+Debt!Z51 -> 0 | AN56: =Debt!AB43+Debt!AB51 -> 0
B57: Refinance Debt Balloon Payment | T57: =Debt!H44+Debt!H52 -> 0 | V57: =Debt!J44+Debt!J52 -> 0 | X57: =Debt!L44+Debt!L52 -> 0 | Z57: =Debt!N44+Debt!N52 -> 0 | AB57: =Debt!P44+Debt!P52 -> 0 | AD57: =Debt!R44+Debt!R52 -> 0 | AF57: =Debt!T44+Debt!T52 -> 0 | AH57: =Debt!V44+Debt!V52 -> 0 | AJ57: =Debt!X44+Debt!X52 -> 0 | AL57: =Debt!Z44+Debt!Z52 -> 0 | AN57: =Debt!AB44+Debt!AB52 -> 0
B58: Funding Fees | T58: =-IF(T$6='Financing Inputs'!$T$5,'Financing Inputs'!$L$8,0) -> 0 | V58: =-IF(V$6='Financing Inputs'!$T$5,'Financing Inputs'!$L$8,0) -> 0 | X58: =-IF(X$6='Financing Inputs'!$T$5,'Financing Inputs'!$L$8,0) -> 0 | Z58: =-IF(Z$6='Financing Inputs'!$T$5,'Financing Inputs'!$L$8,0) -> 0 | AB58: =-IF(AB$6='Financing Inputs'!$T$5,'Financing Inputs'!$L$8,0) -> 0 | AD58: =-IF(AD$6='Financing Inputs'!$T$5,'Financing Inputs'!$L$8,0) -> 0 | AF58: =-IF(AF$6='Financing Inputs'!$T$5,'Financing Inputs'!$L$8,0) -> 0 | AH58: =-IF(AH$6='Financing Inputs'!$T$5,'Financing Inputs'!$L$8,0) -> 0 | AJ58: =-IF(AJ$6='Financing Inputs'!$T$5,'Financing Inputs'!$L$8,0) -> 0 | AL58: =-IF(AL$6='Financing Inputs'!$T$5,'Financing Inputs'!$L$8,0) -> 0 | AN58: =-IF(AN$6='Financing Inputs'!$T$5,'Financing Inputs'!$L$8,0) -> 0
B59: Other Closing Fees | T59: =-IF(T$6='Financing Inputs'!$T$5,'Financing Inputs'!$L$9,0) -> 0 | V59: =-IF(V$6='Financing Inputs'!$T$5,'Financing Inputs'!$L$9,0) -> 0 | X59: =-IF(X$6='Financing Inputs'!$T$5,'Financing Inputs'!$L$9,0) -> 0 | Z59: =-IF(Z$6='Financing Inputs'!$T$5,'Financing Inputs'!$L$9,0) -> 0 | AB59: =-IF(AB$6='Financing Inputs'!$T$5,'Financing Inputs'!$L$9,0) -> 0 | AD59: =-IF(AD$6='Financing Inputs'!$T$5,'Financing Inputs'!$L$9,0) -> 0 | AF59: =-IF(AF$6='Financing Inputs'!$T$5,'Financing Inputs'!$L$9,0) -> 0 | AH59: =-IF(AH$6='Financing Inputs'!$T$5,'Financing Inputs'!$L$9,0) -> 0 | AJ59: =-IF(AJ$6='Financing Inputs'!$T$5,'Financing Inputs'!$L$9,0) -> 0 | AL59: =-IF(AL$6='Financing Inputs'!$T$5,'Financing Inputs'!$L$9,0) -> 0 | AN59: =-IF(AN$6='Financing Inputs'!$T$5,'Financing Inputs'!$L$9,0) -> 0
B60: Free Cash Flow Pre Dividend Pre Mgmt. Fees | T60: =ROUND(IF(T$6='Financing Inputs'!$T$5,0,T46)+SUM(T48:T59),5) -> 0 | V60: =ROUND(IF(V$6='Financing Inputs'!$T$5,0,V46)+SUM(V48:V59),5) -> 69.05218 | X60: =ROUND(IF(X$6='Financing Inputs'!$T$5,0,X46)+SUM(X48:X59),5) -> 85.73972 | Z60: =ROUND(IF(Z$6='Financing Inputs'!$T$5,0,Z46)+SUM(Z48:Z59),5) -> 101.99082 | AB60: =ROUND(IF(AB$6='Financing Inputs'!$T$5,0,AB46)+SUM(AB48:AB59),5) -> 116.15278 | AD60: =ROUND(IF(AD$6='Financing Inputs'!$T$5,0,AD46)+SUM(AD48:AD59),5) -> 129.19487 | AF60: =ROUND(IF(AF$6='Financing Inputs'!$T$5,0,AF46)+SUM(AF48:AF59),5) -> 121.2404 | AH60: =ROUND(IF(AH$6='Financing Inputs'!$T$5,0,AH46)+SUM(AH48:AH59),5) -> 113.37088 | AJ60: =ROUND(IF(AJ$6='Financing Inputs'!$T$5,0,AJ46)+SUM(AJ48:AJ59),5) -> 105.57156 | AL60: =ROUND(IF(AL$6='Financing Inputs'!$T$5,0,AL46)+SUM(AL48:AL59),5) -> 97.82703 | AN60: =ROUND(IF(AN$6='Financing Inputs'!$T$5,0,AN46)+SUM(AN48:AN59),5) -> 878.94495
B62: Equity 1's Dividend | F62: ='Financing Inputs'!T25 -> 0.5 | T62: =IF(IF('Financing Inputs'!$T$31=2,T50+T51,0)+T46+T49+T53+T54+T56+T55<0,T60,T60*$F$62) -> 0 | V62: =IF(IF('Financing Inputs'!$T$31=2,V50+V51,0)+V46+V49+V53+V54+V56+V55<0,V60,V60*$F$62) -> 34.52609 | X62: =IF(IF('Financing Inputs'!$T$31=2,X50+X51,0)+X46+X49+X53+X54+X56+X55<0,X60,X60*$F$62) -> 42.86986 | Z62: =IF(IF('Financing Inputs'!$T$31=2,Z50+Z51,0)+Z46+Z49+Z53+Z54+Z56+Z55<0,Z60,Z60*$F$62) -> 50.99541 | AB62: =IF(IF('Financing Inputs'!$T$31=2,AB50+AB51,0)+AB46+AB49+AB53+AB54+AB56+AB55<0,AB60,AB60*$F$62) -> 58.07639 | AD62: =IF(IF('Financing Inputs'!$T$31=2,AD50+AD51,0)+AD46+AD49+AD53+AD54+AD56+AD55<0,AD60,AD60*$F$62) -> 64.597435 | AF62: =IF(IF('Financing Inputs'!$T$31=2,AF50+AF51,0)+AF46+AF49+AF53+AF54+AF56+AF55<0,AF60,AF60*$F$62) -> 60.6202 | AH62: =IF(IF('Financing Inputs'!$T$31=2,AH50+AH51,0)+AH46+AH49+AH53+AH54+AH56+AH55<0,AH60,AH60*$F$62) -> 56.68544 | AJ62: =IF(IF('Financing Inputs'!$T$31=2,AJ50+AJ51,0)+AJ46+AJ49+AJ53+AJ54+AJ56+AJ55<0,AJ60,AJ60*$F$62) -> 52.78578 | AL62: =IF(IF('Financing Inputs'!$T$31=2,AL50+AL51,0)+AL46+AL49+AL53+AL54+AL56+AL55<0,AL60,AL60*$F$62) -> 48.913515 | AN62: =IF(IF('Financing Inputs'!$T$31=2,AN50+AN51,0)+AN46+AN49+AN53+AN54+AN56+AN55<0,AN60,AN60*$F$62) -> 439.47247
B63: Equity 2's Dividend | F63: ='Financing Inputs'!T26 -> 0.5 | T63: =IF(IF('Financing Inputs'!$T$31=2,T50+T51,0)+T46+T49+T53+T54+T56+T55<0,T60,T60*$F$63) -> 0 | V63: =IF(IF('Financing Inputs'!$T$31=2,V50+V51,0)+V46+V49+V53+V54+V56+V55<0,V60,V60*$F$63) -> 34.52609 | X63: =IF(IF('Financing Inputs'!$T$31=2,X50+X51,0)+X46+X49+X53+X54+X56+X55<0,X60,X60*$F$63) -> 42.86986 | Z63: =IF(IF('Financing Inputs'!$T$31=2,Z50+Z51,0)+Z46+Z49+Z53+Z54+Z56+Z55<0,Z60,Z60*$F$63) -> 50.99541 | AB63: =IF(IF('Financing Inputs'!$T$31=2,AB50+AB51,0)+AB46+AB49+AB53+AB54+AB56+AB55<0,AB60,AB60*$F$63) -> 58.07639 | AD63: =IF(IF('Financing Inputs'!$T$31=2,AD50+AD51,0)+AD46+AD49+AD53+AD54+AD56+AD55<0,AD60,AD60*$F$63) -> 64.597435 | AF63: =IF(IF('Financing Inputs'!$T$31=2,AF50+AF51,0)+AF46+AF49+AF53+AF54+AF56+AF55<0,AF60,AF60*$F$63) -> 60.6202 | AH63: =IF(IF('Financing Inputs'!$T$31=2,AH50+AH51,0)+AH46+AH49+AH53+AH54+AH56+AH55<0,AH60,AH60*$F$63) -> 56.68544 | AJ63: =IF(IF('Financing Inputs'!$T$31=2,AJ50+AJ51,0)+AJ46+AJ49+AJ53+AJ54+AJ56+AJ55<0,AJ60,AJ60*$F$63) -> 52.78578 | AL63: =IF(IF('Financing Inputs'!$T$31=2,AL50+AL51,0)+AL46+AL49+AL53+AL54+AL56+AL55<0,AL60,AL60*$F$63) -> 48.913515 | AN63: =IF(IF('Financing Inputs'!$T$31=2,AN50+AN51,0)+AN46+AN49+AN53+AN54+AN56+AN55<0,AN60,AN60*$F$63) -> 439.47247
B65: Equity 1
B66: Equity Invested | F66: =-SUMIF(T66:AN66,"<0") -> 269.875 | T66: =-T50 -> -269.875 | V66: =-V50 -> 0 | X66: =-X50 -> 0 | Z66: =-Z50 -> 0 | AB66: =-AB50 -> 0 | AD66: =-AD50 -> 0 | AF66: =-AF50 -> 0 | AH66: =-AH50 -> 0 | AJ66: =-AJ50 -> 0 | AL66: =-AL50 -> 0 | AN66: =-AN50 -> 0
B67: Equity Returned | F67: =SUM(T67:AN67)+SUMIF(T66:AN66,">0") -> 909.54259 | T67: =T62 -> 0 | V67: =V62 -> 34.52609 | X67: =X62 -> 42.86986 | Z67: =Z62 -> 50.99541 | AB67: =AB62 -> 58.07639 | AD67: =AD62 -> 64.597435 | AF67: =AF62 -> 60.6202 | AH67: =AH62 -> 56.68544 | AJ67: =AJ62 -> 52.78578 | AL67: =AL62 -> 48.913515 | AN67: =AN62 -> 439.47247
B68: Net Cash Impact | T68: =SUM(T66:T67) -> -269.875 | V68: =SUM(V66:V67) -> 34.52609 | X68: =SUM(X66:X67) -> 42.86986 | Z68: =SUM(Z66:Z67) -> 50.99541 | AB68: =SUM(AB66:AB67) -> 58.07639 | AD68: =SUM(AD66:AD67) -> 64.597435 | AF68: =SUM(AF66:AF67) -> 60.6202 | AH68: =SUM(AH66:AH67) -> 56.68544 | AJ68: =SUM(AJ66:AJ67) -> 52.78578 | AL68: =SUM(AL66:AL67) -> 48.913515 | AN68: =SUM(AN66:AN67) -> 439.47247
B70: IRR | F70: =XIRR(T68:AN68,$T$6:$AN$6) -> 0.20067279
B72: Equity 2
B73: Equity Invested | F73: =-SUMIF(T73:AN73,"<0") -> 269.875 | T73: =-T51 -> -269.875 | V73: =-V51 -> 0 | X73: =-X51 -> 0 | Z73: =-Z51 -> 0 | AB73: =-AB51 -> 0 | AD73: =-AD51 -> 0 | AF73: =-AF51 -> 0 | AH73: =-AH51 -> 0 | AJ73: =-AJ51 -> 0 | AL73: =-AL51 -> 0 | AN73: =-AN51 -> 0
B74: Equity Returned | F74: =SUM(T74:AN74)+SUMIF(T73:AN73,">0") -> 909.54259 | T74: =T63 -> 0 | V74: =V63 -> 34.52609 | X74: =X63 -> 42.86986 | Z74: =Z63 -> 50.99541 | AB74: =AB63 -> 58.07639 | AD74: =AD63 -> 64.597435 | AF74: =AF63 -> 60.6202 | AH74: =AH63 -> 56.68544 | AJ74: =AJ63 -> 52.78578 | AL74: =AL63 -> 48.913515 | AN74: =AN63 -> 439.47247
B75: Net Cash Impact | T75: =SUM(T73:T74) -> -269.875 | V75: =SUM(V73:V74) -> 34.52609 | X75: =SUM(X73:X74) -> 42.86986 | Z75: =SUM(Z73:Z74) -> 50.99541 | AB75: =SUM(AB73:AB74) -> 58.07639 | AD75: =SUM(AD73:AD74) -> 64.597435 | AF75: =SUM(AF73:AF74) -> 60.6202 | AH75: =SUM(AH73:AH74) -> 56.68544 | AJ75: =SUM(AJ73:AJ74) -> 52.78578 | AL75: =SUM(AL73:AL74) -> 48.913515 | AN75: =SUM(AN73:AN74) -> 439.47247
B77: IRR | F77: =XIRR(T75:AN75,$T$6:$AN$6) -> 0.20067279
B80: Total Debt | T80: =Debt!H15+Debt!H22+Debt!H29+Debt!H36+Debt!H45+Debt!H53 -> 1619.25 | V80: =Debt!J15+Debt!J22+Debt!J29+Debt!J36+Debt!J45+Debt!J53 -> 1580.0442 | X80: =Debt!L15+Debt!L22+Debt!L29+Debt!L36+Debt!L45+Debt!L53 -> 1537.31 | Z80: =Debt!N15+Debt!N22+Debt!N29+Debt!N36+Debt!N45+Debt!N53 -> 1490.7296 | AB80: =Debt!P15+Debt!P22+Debt!P29+Debt!P36+Debt!P45+Debt!P53 -> 1439.957 | AD80: =Debt!R15+Debt!R22+Debt!R29+Debt!R36+Debt!R45+Debt!R53 -> 1384.6149 | AF80: =Debt!T15+Debt!T22+Debt!T29+Debt!T36+Debt!T45+Debt!T53 -> 1324.292 | AH80: =Debt!V15+Debt!V22+Debt!V29+Debt!V36+Debt!V45+Debt!V53 -> 1258.54 | AJ80: =Debt!X15+Debt!X22+Debt!X29+Debt!X36+Debt!X45+Debt!X53 -> 1186.8704 | AL80: =Debt!Z15+Debt!Z22+Debt!Z29+Debt!Z36+Debt!Z45+Debt!Z53 -> 1108.7505 | AN80: =Debt!AB15+Debt!AB22+Debt!AB29+Debt!AB36+Debt!AB45+Debt!AB53 -> 0
B82: Other Cash Flow Items (which are not part of FCF Calculation) :
B83: Acquisitions | H83: =H252+H265+H246 -> 0 | J83: =J252+J265+J246 -> 0 | L83: =L252+L265+L246 -> -3.87695 | N83: =N252+N265+N246 -> 0 | P83: =P252+P265+P246 -> -2.23725 | R83: =R252+R265+R246 -> 0
B84: Proceeds from sale of assets | H84: =H249 -> 9.5 | J84: =J249 -> 0.02375 | L84: =L249 -> 2.4225 | N84: =N249 -> 0.91485 | P84: =P249 -> 0.04845 | R84: =R249 -> 0.34675
B85: Change in Debt, net | H85: =SUM(H256:H261) -> -129.86025 | J85: =SUM(J256:J261) -> -39.3471 | L85: =SUM(L256:L261) -> -40.8633 | N85: =SUM(N256:N261) -> -28.0858 | P85: =SUM(P256:P261) -> -86.4101 | R85: =SUM(R256:R261) -> 27.6431
B86: Debt issuance costs | H86: =H264 -> -3.53115 | J86: =J264 -> -3.67365 | L86: =L264 -> -1.5067 | N86: =N264 -> -7.35965 | P86: =P264 -> -1.27015 | R86: =R264 -> -6.47615
B87: Unrealized gain on foreign currency / derivative contracts, net | H87: =H231+H229 -> -4.20185 | J87: =J231+J229 -> -0.8151 | L87: =L231+L229 -> -3.81045 | N87: =N231+N229 -> -3.1027 | P87: =P231+P229 -> 2.1394 | R87: =R231+R229 -> 7.8945
B88: Other income (expense), net | H88: =H208 -> -1.3623 | J88: =J208 -> -6.0078 | L88: =L208 -> 1.10675 | N88: =N208 -> 4.4878 | P88: =P208 -> -1.4155 | R88: =R208 -> -3.4105
B89: Distribution from equity investment, net | H89: =H248 -> 0 | J89: =J248 -> 0 | L89: =L248 -> 0 | N89: =N248 -> 0 | P89: =P248 -> 0 | R89: =R248 -> 0
B90: Acquisition and integration costs | H90: =H201 -> 0 | J90: =J201 -> 0 | K90: =K201 -> 0 | L90: =L201 -> 0 | N90: =N201 -> 0 | P90: =P201 -> 0 | R90: =R201 -> -0.513
B91: Proceeds from insurance recoveries | H91: =H250 -> 0 | J91: =J250 -> 0 | L91: =L250 -> 0 | N91: =N250 -> 0 | P91: =P250 -> 0 | R91: =R250 -> 0.5358
B92: Other investing Activities | H92: =H251 -> 0 | J92: =J251 -> 0.9918 | L92: =L251 -> 0 | N92: =N251 -> 0 | P92: =P251 -> 0 | R92: =R251 -> 0
B93: Capped call transactions | H93: =H262+H263 -> 0 | J93: =J262+J263 -> 0 | L93: =L262+L263 -> 0 | N93: =N262+N263 -> -10.09375 | P93: =P262+P263 -> 0 | R93: =R262+R263 -> 14.81145
B94: Payment of earn-out consideration | H94: =H269 -> 0 | J94: =J269 -> 0 | L94: =L269 -> 0 | N94: =N269 -> 0 | P94: =P269 -> 0 | R94: =R269 -> 0
B95: Payments related to tax withholding for share-based compensation | H95: =H267 -> -1.9399 | J95: =J267 -> -1.33665 | L95: =L267 -> -1.596 | N95: =N267 -> -5.0008 | P95: =P267 -> -1.90095 | R95: =R267 -> -1.66915
B96: Proceeds from issuance of ESPP shares | H96: =H268 -> 0.4104 | J96: =J268 -> 0.4807 | L96: =L268 -> 0.4389 | N96: =N268 -> 0.5909 | P96: =P268 -> 0.6213 | R96: =R268 -> 0.9329
B97: Effect of exchange rate changes on cash and cash equivalents and restricted cash | H97: =H272 -> 1.8544 | J97: =J272 -> -1.59315 | L97: =L272 -> 1.5542 | N97: =N272 -> 1.7271 | P97: =P272 -> -0.0399 | R97: =R272 -> -15.03565
B98: Total Other Cash Flow Items | H98: =SUM(H83:H97) -> -129.13065 | J98: =SUM(J83:J97) -> -51.2772 | L98: =SUM(L83:L97) -> -46.13105 | N98: =SUM(N83:N97) -> -45.92205 | P98: =SUM(P83:P97) -> -90.4647 | R98: =SUM(R83:R97) -> 25.06005
B100: Net Change in Cash | H100: =+H98+H46 -> -89.1005 | J100: =+J98+J46 -> 7.8242 | L100: =+L98+L46 -> -19.1938 | N100: =+N98+N46 -> 24.74655 | P100: =+P98+P46 -> 31.2873 | R100: =+R98+R46 -> 133.82745
B101: Beginning Cash Balance | H101: =+H275 -> 338.81465 | J101: =+J275 -> 253.2624 | L101: =+L275 -> 265.48605 | N101: =+N275 -> 249.43295 | P101: =+P275 -> 276.754 | R101: =+R275 -> 179.65545
B102: Ending Cash Balance | H102: =+H100+H101 -> 249.71415 | J102: =+J100+J101 -> 261.0866 | L102: =+L100+L101 -> 246.29225 | N102: =+N100+N101 -> 274.1795 | P102: =+P100+P101 -> 308.0413 | R102: =+R100+R101 -> 313.4829
B103: Parity | H103: =+ROUND(H102-H129,5) -> 0 | J103: =+ROUND(J102-J129,5) -> 0 | L103: =+ROUND(L102-L129,5) -> 0 | N103: =+ROUND(N102-N129,5) -> 0 | P103: =+ROUND(P102-P129,5) -> 0 | R103: =+ROUND(R102-R129,5) -> 0
B105: Total Leverage | H105: =IFERROR((H147+H143)/H29,"na") -> 4.1814125 | J105: =IFERROR((J147+J143)/J29,"na") -> 2.5622949 | L105: =IFERROR((L147+L143)/L29,"na") -> 2.1117719 | N105: =IFERROR((N147+N143)/N29,"na") -> 2.1698241 | P105: =IFERROR((P147+P143)/P29,"na") -> 3.0155121 | R105: =IFERROR((R147+R143)/R29,"na") -> 1.3079568 | T105: =IFERROR((T80)/T29,"na") -> 5.173666 | V105: =IFERROR((V80)/V29,"na") -> 4.8826799 | X105: =IFERROR((X80)/X29,"na") -> 4.4474204 | Z105: =IFERROR((Z80)/Z29,"na") -> 4.0590948 | AB105: =IFERROR((AB80)/AB29,"na") -> 3.7275848 | AD105: =IFERROR((AD80)/AD29,"na") -> 3.4270844 | AF105: =IFERROR((AF80)/AF29,"na") -> 3.3502944 | AH105: =IFERROR((AH80)/AH29,"na") -> 3.2540757 | AJ105: =IFERROR((AJ80)/AJ29,"na") -> 3.1360644 | AL105: =IFERROR((AL80)/AL29,"na") -> 2.9936294 | AN105: =IFERROR((AN80)/AN29,"na") -> 0
B107: Operational Overview
B109: Revenue by Segments:
B110: Segement 1 | H110: 386.02395 | I110: 0 | J110: 532.5396 | K110: 0 | L110: 563.635 | M110: 0 | N110: 512.28655 | O110: 0 | P110: 490.7358 | Q110: 0 | R110: 696.12295 | T110: =IF(AND(T$6>='Financing Inputs'!$T$5,T$6<='Financing Inputs'!$T$19),R110*(1+T112),0) -> 762.25463 | V110: =IF(AND(V$6>='Financing Inputs'!$T$5,V$6<='Financing Inputs'!$T$19),T110*(1+V112),0) -> 823.235 | X110: =IF(AND(X$6>='Financing Inputs'!$T$5,X$6<='Financing Inputs'!$T$19),V110*(1+X112),0) -> 880.86145 | Z110: =IF(AND(Z$6>='Financing Inputs'!$T$5,Z$6<='Financing Inputs'!$T$19),X110*(1+Z112),0) -> 933.71314 | AB110: =IF(AND(AB$6>='Financing Inputs'!$T$5,AB$6<='Financing Inputs'!$T$19),Z110*(1+AB112),0) -> 980.39879 | AD110: =IF(AND(AD$6>='Financing Inputs'!$T$5,AD$6<='Financing Inputs'!$T$19),AB110*(1+AD112),0) -> 1019.6147 | AF110: =IF(AND(AF$6>='Financing Inputs'!$T$5,AF$6<='Financing Inputs'!$T$19),AD110*(1+AF112),0) -> 989.0263 | AH110: =IF(AND(AH$6>='Financing Inputs'!$T$5,AH$6<='Financing Inputs'!$T$19),AF110*(1+AH112),0) -> 959.35551 | AJ110: =IF(AND(AJ$6>='Financing Inputs'!$T$5,AJ$6<='Financing Inputs'!$T$19),AH110*(1+AJ112),0) -> 930.57485 | AL110: =IF(AND(AL$6>='Financing Inputs'!$T$5,AL$6<='Financing Inputs'!$T$19),AJ110*(1+AL112),0) -> 902.6576 | AN110: =IF(AND(AN$6>='Financing Inputs'!$T$5,AN$6<='Financing Inputs'!$T$19),AL110*(1+AN112),0) -> 875.57788
B111: % Sq/Sq Growth | H111: na | J111: =IFERROR((J110/H110-1),"na") -> 0.37955067 | L111: =IFERROR((L110/J110-1),"na") -> 0.058390775 | N111: =IFERROR((N110/L110-1),"na") -> -0.091102309 | P111: =IFERROR((P110/N110-1),"na") -> -0.042067765 | R111: =IFERROR((R110/P110-1),"na") -> 0.41852897 | T111: =IFERROR((T110/R110-1),"na") -> 0.095 | V111: =IFERROR((V110/T110-1),"na") -> 0.08 | X111: =IFERROR((X110/V110-1),"na") -> 0.07 | Z111: =IFERROR((Z110/X110-1),"na") -> 0.06 | AB111: =IFERROR((AB110/Z110-1),"na") -> 0.05 | AD111: =IFERROR((AD110/AB110-1),"na") -> 0.04 | AF111: =IFERROR((AF110/AD110-1),"na") -> -0.03 | AH111: =IFERROR((AH110/AF110-1),"na") -> -0.03 | AJ111: =IFERROR((AJ110/AH110-1),"na") -> -0.03 | AL111: =IFERROR((AL110/AJ110-1),"na") -> -0.03 | AN111: =IFERROR((AN110/AL110-1),"na") -> -0.03
B112: % Yr/Yr Growth | H112: na | J112: =IFERROR((J110/H110-1),"na") -> 0.37955067 | L112: =IFERROR((L110/J110-1),"na") -> 0.058390775 | N112: =IFERROR((N110/L110-1),"na") -> -0.091102309 | P112: =IFERROR((P110/N110-1),"na") -> -0.042067765 | R112: =IFERROR((R110/P110-1),"na") -> 0.41852897 | T112: =IF(AND(T$6>='Financing Inputs'!$T$5,T$6<='Financing Inputs'!$T$19),'Operating Inputs'!BU$11,0) -> 0.095 | V112: =IF(AND(V$6>='Financing Inputs'!$T$5,V$6<='Financing Inputs'!$T$19),'Operating Inputs'!BW$11,0) -> 0.08 | X112: =IF(AND(X$6>='Financing Inputs'!$T$5,X$6<='Financing Inputs'!$T$19),'Operating Inputs'!BY$11,0) -> 0.07 | Z112: =IF(AND(Z$6>='Financing Inputs'!$T$5,Z$6<='Financing Inputs'!$T$19),'Operating Inputs'!CA$11,0) -> 0.06 | AB112: =IF(AND(AB$6>='Financing Inputs'!$T$5,AB$6<='Financing Inputs'!$T$19),'Operating Inputs'!CC$11,0) -> 0.05 | AD112: =IF(AND(AD$6>='Financing Inputs'!$T$5,AD$6<='Financing Inputs'!$T$19),'Operating Inputs'!CE$11,0) -> 0.04 | AF112: =IF(AND(AF$6>='Financing Inputs'!$T$5,AF$6<='Financing Inputs'!$T$19),'Operating Inputs'!CG$11,0) -> -0.03 | AH112: =IF(AND(AH$6>='Financing Inputs'!$T$5,AH$6<='Financing Inputs'!$T$19),'Operating Inputs'!CI$11,0) -> -0.03 | AJ112: =IF(AND(AJ$6>='Financing Inputs'!$T$5,AJ$6<='Financing Inputs'!$T$19),'Operating Inputs'!CK$11,0) -> -0.03 | AL112: =IF(AND(AL$6>='Financing Inputs'!$T$5,AL$6<='Financing Inputs'!$T$19),'Operating Inputs'!CM$11,0) -> -0.03 | AN112: =IF(AND(AN$6>='Financing Inputs'!$T$5,AN$6<='Financing Inputs'!$T$19),'Operating Inputs'!CO$11,0) -> -0.03
B113: Segement 2 | H113: 145.11725 | J113: 151.03955 | L113: 163.0884 | N113: 169.1171 | P113: 130.43025 | R113: 244.98125 | T113: =IF(AND(T$6>='Financing Inputs'!$T$5,T$6<='Financing Inputs'!$T$19),R113*(1+T115),0) -> 269.47938 | V113: =IF(AND(V$6>='Financing Inputs'!$T$5,V$6<='Financing Inputs'!$T$19),T113*(1+V115),0) -> 296.42731 | X113: =IF(AND(X$6>='Financing Inputs'!$T$5,X$6<='Financing Inputs'!$T$19),V113*(1+X115),0) -> 326.07004 | Z113: =IF(AND(Z$6>='Financing Inputs'!$T$5,Z$6<='Financing Inputs'!$T$19),X113*(1+Z115),0) -> 358.67705 | AB113: =IF(AND(AB$6>='Financing Inputs'!$T$5,AB$6<='Financing Inputs'!$T$19),Z113*(1+AB115),0) -> 387.37121 | AD113: =IF(AND(AD$6>='Financing Inputs'!$T$5,AD$6<='Financing Inputs'!$T$19),AB113*(1+AD115),0) -> 418.36091 | AF113: =IF(AND(AF$6>='Financing Inputs'!$T$5,AF$6<='Financing Inputs'!$T$19),AD113*(1+AF115),0) -> 414.1773 | AH113: =IF(AND(AH$6>='Financing Inputs'!$T$5,AH$6<='Financing Inputs'!$T$19),AF113*(1+AH115),0) -> 410.03553 | AJ113: =IF(AND(AJ$6>='Financing Inputs'!$T$5,AJ$6<='Financing Inputs'!$T$19),AH113*(1+AJ115),0) -> 405.93517 | AL113: =IF(AND(AL$6>='Financing Inputs'!$T$5,AL$6<='Financing Inputs'!$T$19),AJ113*(1+AL115),0) -> 401.87582 | AN113: =IF(AND(AN$6>='Financing Inputs'!$T$5,AN$6<='Financing Inputs'!$T$19),AL113*(1+AN115),0) -> 397.85706
B114: % Sq/Sq Growth | H114: na | J114: =IFERROR((J113/H113-1),"na") -> 0.040810448 | L114: =IFERROR((L113/J113-1),"na") -> 0.079772814 | N114: =IFERROR((N113/L113-1),"na") -> 0.036965842 | P114: =IFERROR((P113/N113-1),"na") -> -0.22875777 | R114: =IFERROR((R113/P113-1),"na") -> 0.87825485 | T114: =IFERROR((T113/R113-1),"na") -> 0.1 | V114: =IFERROR((V113/T113-1),"na") -> 0.1 | X114: =IFERROR((X113/V113-1),"na") -> 0.1 | Z114: =IFERROR((Z113/X113-1),"na") -> 0.1 | AB114: =IFERROR((AB113/Z113-1),"na") -> 0.08 | AD114: =IFERROR((AD113/AB113-1),"na") -> 0.08 | AF114: =IFERROR((AF113/AD113-1),"na") -> -0.01 | AH114: =IFERROR((AH113/AF113-1),"na") -> -0.01 | AJ114: =IFERROR((AJ113/AH113-1),"na") -> -0.01 | AL114: =IFERROR((AL113/AJ113-1),"na") -> -0.01 | AN114: =IFERROR((AN113/AL113-1),"na") -> -0.01
B115: % Yr/Yr Growth | H115: na | J115: =IFERROR((J113/H113-1),"na") -> 0.040810448 | L115: =IFERROR((L113/J113-1),"na") -> 0.079772814 | N115: =IFERROR((N113/L113-1),"na") -> 0.036965842 | P115: =IFERROR((P113/N113-1),"na") -> -0.22875777 | R115: =IFERROR((R113/P113-1),"na") -> 0.87825485 | T115: =IF(AND(T$6>='Financing Inputs'!$T$5,T$6<='Financing Inputs'!$T$19),'Operating Inputs'!BU$12,0) -> 0.1 | V115: =IF(AND(V$6>='Financing Inputs'!$T$5,V$6<='Financing Inputs'!$T$19),'Operating Inputs'!BW$12,0) -> 0.1 | X115: =IF(AND(X$6>='Financing Inputs'!$T$5,X$6<='Financing Inputs'!$T$19),'Operating Inputs'!BY$12,0) -> 0.1 | Z115: =IF(AND(Z$6>='Financing Inputs'!$T$5,Z$6<='Financing Inputs'!$T$19),'Operating Inputs'!CA$12,0) -> 0.1 | AB115: =IF(AND(AB$6>='Financing Inputs'!$T$5,AB$6<='Financing Inputs'!$T$19),'Operating Inputs'!CC$12,0) -> 0.08 | AD115: =IF(AND(AD$6>='Financing Inputs'!$T$5,AD$6<='Financing Inputs'!$T$19),'Operating Inputs'!CE$12,0) -> 0.08 | AF115: =IF(AND(AF$6>='Financing Inputs'!$T$5,AF$6<='Financing Inputs'!$T$19),'Operating Inputs'!CG$12,0) -> -0.01 | AH115: =IF(AND(AH$6>='Financing Inputs'!$T$5,AH$6<='Financing Inputs'!$T$19),'Operating Inputs'!CI$12,0) -> -0.01 | AJ115: =IF(AND(AJ$6>='Financing Inputs'!$T$5,AJ$6<='Financing Inputs'!$T$19),'Operating Inputs'!CK$12,0) -> -0.01 | AL115: =IF(AND(AL$6>='Financing Inputs'!$T$5,AL$6<='Financing Inputs'!$T$19),'Operating Inputs'!CM$12,0) -> -0.01 | AN115: =IF(AND(AN$6>='Financing Inputs'!$T$5,AN$6<='Financing Inputs'!$T$19),'Operating Inputs'!CO$12,0) -> -0.01
B116: Segement 3 | H116: 0 | R116: 261.2063 | T116: =IF(AND(T$6>='Financing Inputs'!$T$5,T$6<='Financing Inputs'!$T$19),R116*(1+T118),0) -> 188.06854 | V116: =IF(AND(V$6>='Financing Inputs'!$T$5,V$6<='Financing Inputs'!$T$19),T116*(1+V118),0) -> 144.81277 | X116: =IF(AND(X$6>='Financing Inputs'!$T$5,X$6<='Financing Inputs'!$T$19),V116*(1+X118),0) -> 147.70903 | Z116: =IF(AND(Z$6>='Financing Inputs'!$T$5,Z$6<='Financing Inputs'!$T$19),X116*(1+Z118),0) -> 150.66321 | AB116: =IF(AND(AB$6>='Financing Inputs'!$T$5,AB$6<='Financing Inputs'!$T$19),Z116*(1+AB118),0) -> 153.67647 | AD116: =IF(AND(AD$6>='Financing Inputs'!$T$5,AD$6<='Financing Inputs'!$T$19),AB116*(1+AD118),0) -> 156.75 | AF116: =IF(AND(AF$6>='Financing Inputs'!$T$5,AF$6<='Financing Inputs'!$T$19),AD116*(1+AF118),0) -> 159.885 | AH116: =IF(AND(AH$6>='Financing Inputs'!$T$5,AH$6<='Financing Inputs'!$T$19),AF116*(1+AH118),0) -> 163.0827 | AJ116: =IF(AND(AJ$6>='Financing Inputs'!$T$5,AJ$6<='Financing Inputs'!$T$19),AH116*(1+AJ118),0) -> 166.34436 | AL116: =IF(AND(AL$6>='Financing Inputs'!$T$5,AL$6<='Financing Inputs'!$T$19),AJ116*(1+AL118),0) -> 169.67124 | AN116: =IF(AND(AN$6>='Financing Inputs'!$T$5,AN$6<='Financing Inputs'!$T$19),AL116*(1+AN118),0) -> 173.06467
B117: % Sq/Sq Growth | H117: na | J117: =IFERROR((J116/H116-1),"na") -> na | L117: =IFERROR((L116/J116-1),"na") -> na | N117: =IFERROR((N116/L116-1),"na") -> na | P117: =IFERROR((P116/N116-1),"na") -> na | R117: =IFERROR((R116/P116-1),"na") -> na | T117: =IFERROR((T116/R116-1),"na") -> -0.28 | V117: =IFERROR((V116/T116-1),"na") -> -0.23 | X117: =IFERROR((X116/V116-1),"na") -> 0.02 | Z117: =IFERROR((Z116/X116-1),"na") -> 0.02 | AB117: =IFERROR((AB116/Z116-1),"na") -> 0.02 | AD117: =IFERROR((AD116/AB116-1),"na") -> 0.02 | AF117: =IFERROR((AF116/AD116-1),"na") -> 0.02 | AH117: =IFERROR((AH116/AF116-1),"na") -> 0.02 | AJ117: =IFERROR((AJ116/AH116-1),"na") -> 0.02 | AL117: =IFERROR((AL116/AJ116-1),"na") -> 0.02 | AN117: =IFERROR((AN116/AL116-1),"na") -> 0.02
B118: % Yr/Yr Growth | H118: na | J118: =IFERROR((J116/H116-1),"na") -> na | L118: =IFERROR((L116/J116-1),"na") -> na | N118: =IFERROR((N116/L116-1),"na") -> na | P118: =IFERROR((P116/N116-1),"na") -> na | R118: =IFERROR((R116/P116-1),"na") -> na | T118: =IF(AND(T$6>='Financing Inputs'!$T$5,T$6<='Financing Inputs'!$T$19),'Operating Inputs'!BU$13,0) -> -0.28 | V118: =IF(AND(V$6>='Financing Inputs'!$T$5,V$6<='Financing Inputs'!$T$19),'Operating Inputs'!BW$13,0) -> -0.23 | X118: =IF(AND(X$6>='Financing Inputs'!$T$5,X$6<='Financing Inputs'!$T$19),'Operating Inputs'!BY$13,0) -> 0.02 | Z118: =IF(AND(Z$6>='Financing Inputs'!$T$5,Z$6<='Financing Inputs'!$T$19),'Operating Inputs'!CA$13,0) -> 0.02 | AB118: =IF(AND(AB$6>='Financing Inputs'!$T$5,AB$6<='Financing Inputs'!$T$19),'Operating Inputs'!CC$13,0) -> 0.02 | AD118: =IF(AND(AD$6>='Financing Inputs'!$T$5,AD$6<='Financing Inputs'!$T$19),'Operating Inputs'!CE$13,0) -> 0.02 | AF118: =IF(AND(AF$6>='Financing Inputs'!$T$5,AF$6<='Financing Inputs'!$T$19),'Operating Inputs'!CG$13,0) -> 0.02 | AH118: =IF(AND(AH$6>='Financing Inputs'!$T$5,AH$6<='Financing Inputs'!$T$19),'Operating Inputs'!CI$13,0) -> 0.02 | AJ118: =IF(AND(AJ$6>='Financing Inputs'!$T$5,AJ$6<='Financing Inputs'!$T$19),'Operating Inputs'!CK$13,0) -> 0.02 | AL118: =IF(AND(AL$6>='Financing Inputs'!$T$5,AL$6<='Financing Inputs'!$T$19),'Operating Inputs'!CM$13,0) -> 0.02 | AN118: =IF(AND(AN$6>='Financing Inputs'!$T$5,AN$6<='Financing Inputs'!$T$19),'Operating Inputs'!CO$13,0) -> 0.02
B119: Segement 4 | H119: 61.1344 | J119: 61.18 | L119: 58.1495 | N119: 55.38785 | P119: 65.8806 | R119: 83.49075 | T119: =IF(AND(T$6>='Financing Inputs'!$T$5,T$6<='Financing Inputs'!$T$19),R119*(1+T121),0) -> 85.160565 | V119: =IF(AND(V$6>='Financing Inputs'!$T$5,V$6<='Financing Inputs'!$T$19),T119*(1+V121),0) -> 85.160565 | X119: =IF(AND(X$6>='Financing Inputs'!$T$5,X$6<='Financing Inputs'!$T$19),V119*(1+X121),0) -> 85.160565 | Z119: =IF(AND(Z$6>='Financing Inputs'!$T$5,Z$6<='Financing Inputs'!$T$19),X119*(1+Z121),0) -> 85.160565 | AB119: =IF(AND(AB$6>='Financing Inputs'!$T$5,AB$6<='Financing Inputs'!$T$19),Z119*(1+AB121),0) -> 85.160565 | AD119: =IF(AND(AD$6>='Financing Inputs'!$T$5,AD$6<='Financing Inputs'!$T$19),AB119*(1+AD121),0) -> 85.160565 | AF119: =IF(AND(AF$6>='Financing Inputs'!$T$5,AF$6<='Financing Inputs'!$T$19),AD119*(1+AF121),0) -> 85.160565 | AH119: =IF(AND(AH$6>='Financing Inputs'!$T$5,AH$6<='Financing Inputs'!$T$19),AF119*(1+AH121),0) -> 85.160565 | AJ119: =IF(AND(AJ$6>='Financing Inputs'!$T$5,AJ$6<='Financing Inputs'!$T$19),AH119*(1+AJ121),0) -> 85.160565 | AL119: =IF(AND(AL$6>='Financing Inputs'!$T$5,AL$6<='Financing Inputs'!$T$19),AJ119*(1+AL121),0) -> 85.160565 | AN119: =IF(AND(AN$6>='Financing Inputs'!$T$5,AN$6<='Financing Inputs'!$T$19),AL119*(1+AN121),0) -> 85.160565
B120: % Sq/Sq Growth | H120: na | J120: =IFERROR((J119/H119-1),"na") -> 0.00074589756 | L120: =IFERROR((L119/J119-1),"na") -> -0.049534161 | N120: =IFERROR((N119/L119-1),"na") -> -0.04749224 | P120: =IFERROR((P119/N119-1),"na") -> 0.18944137 | R120: =IFERROR((R119/P119-1),"na") -> 0.26730403 | T120: =IFERROR((T119/R119-1),"na") -> 0.02 | V120: =IFERROR((V119/T119-1),"na") -> 0 | X120: =IFERROR((X119/V119-1),"na") -> 0 | Z120: =IFERROR((Z119/X119-1),"na") -> 0 | AB120: =IFERROR((AB119/Z119-1),"na") -> 0 | AD120: =IFERROR((AD119/AB119-1),"na") -> 0 | AF120: =IFERROR((AF119/AD119-1),"na") -> 0 | AH120: =IFERROR((AH119/AF119-1),"na") -> 0 | AJ120: =IFERROR((AJ119/AH119-1),"na") -> 0 | AL120: =IFERROR((AL119/AJ119-1),"na") -> 0 | AN120: =IFERROR((AN119/AL119-1),"na") -> 0
B121: % Yr/Yr Growth | H121: na | J121: =IFERROR((J119/H119-1),"na") -> 0.00074589756 | L121: =IFERROR((L119/J119-1),"na") -> -0.049534161 | N121: =IFERROR((N119/L119-1),"na") -> -0.04749224 | P121: =IFERROR((P119/N119-1),"na") -> 0.18944137 | R121: =IFERROR((R119/P119-1),"na") -> 0.26730403 | T121: =IF(AND(T$6>='Financing Inputs'!$T$5,T$6<='Financing Inputs'!$T$19),'Operating Inputs'!BU$14,0) -> 0.02 | V121: =IF(AND(V$6>='Financing Inputs'!$T$5,V$6<='Financing Inputs'!$T$19),'Operating Inputs'!BW$14,0) -> 0 | X121: =IF(AND(X$6>='Financing Inputs'!$T$5,X$6<='Financing Inputs'!$T$19),'Operating Inputs'!BY$14,0) -> 0 | Z121: =IF(AND(Z$6>='Financing Inputs'!$T$5,Z$6<='Financing Inputs'!$T$19),'Operating Inputs'!CA$14,0) -> 0 | AB121: =IF(AND(AB$6>='Financing Inputs'!$T$5,AB$6<='Financing Inputs'!$T$19),'Operating Inputs'!CC$14,0) -> 0 | AD121: =IF(AND(AD$6>='Financing Inputs'!$T$5,AD$6<='Financing Inputs'!$T$19),'Operating Inputs'!CE$14,0) -> 0 | AF121: =IF(AND(AF$6>='Financing Inputs'!$T$5,AF$6<='Financing Inputs'!$T$19),'Operating Inputs'!CG$14,0) -> 0 | AH121: =IF(AND(AH$6>='Financing Inputs'!$T$5,AH$6<='Financing Inputs'!$T$19),'Operating Inputs'!CI$14,0) -> 0 | AJ121: =IF(AND(AJ$6>='Financing Inputs'!$T$5,AJ$6<='Financing Inputs'!$T$19),'Operating Inputs'!CK$14,0) -> 0 | AL121: =IF(AND(AL$6>='Financing Inputs'!$T$5,AL$6<='Financing Inputs'!$T$19),'Operating Inputs'!CM$14,0) -> 0 | AN121: =IF(AND(AN$6>='Financing Inputs'!$T$5,AN$6<='Financing Inputs'!$T$19),'Operating Inputs'!CO$14,0) -> 0
B122: Segement 5 | H122: -39.96175 | J122: -41.93205 | L122: -70.55935 | N122: -39.91425 | P122: -46.05505 | R122: -60.55965 | T122: =IF(AND(T$6>='Financing Inputs'!$T$5,T$6<='Financing Inputs'!$T$19),R122*(1+'Operating Inputs'!BU$15),0) -> -62.982036 | V122: =IF(AND(V$6>='Financing Inputs'!$T$5,V$6<='Financing Inputs'!$T$19),T122*(1+'Operating Inputs'!BW$15),0) -> -65.501317 | X122: =IF(AND(X$6>='Financing Inputs'!$T$5,X$6<='Financing Inputs'!$T$19),V122*(1+'Operating Inputs'!BY$15),0) -> -68.12137 | Z122: =IF(AND(Z$6>='Financing Inputs'!$T$5,Z$6<='Financing Inputs'!$T$19),X122*(1+'Operating Inputs'!CA$15),0) -> -70.846225 | AB122: =IF(AND(AB$6>='Financing Inputs'!$T$5,AB$6<='Financing Inputs'!$T$19),Z122*(1+'Operating Inputs'!CC$15),0) -> -73.680074 | AD122: =IF(AND(AD$6>='Financing Inputs'!$T$5,AD$6<='Financing Inputs'!$T$19),AB122*(1+'Operating Inputs'!CE$15),0) -> -76.627277 | AF122: =IF(AND(AF$6>='Financing Inputs'!$T$5,AF$6<='Financing Inputs'!$T$19),AD122*(1+'Operating Inputs'!CG$15),0) -> -79.692368 | AH122: =IF(AND(AH$6>='Financing Inputs'!$T$5,AH$6<='Financing Inputs'!$T$19),AF122*(1+'Operating Inputs'!CI$15),0) -> -82.880063 | AJ122: =IF(AND(AJ$6>='Financing Inputs'!$T$5,AJ$6<='Financing Inputs'!$T$19),AH122*(1+'Operating Inputs'!CK$15),0) -> -86.195265 | AL122: =IF(AND(AL$6>='Financing Inputs'!$T$5,AL$6<='Financing Inputs'!$T$19),AJ122*(1+'Operating Inputs'!CM$15),0) -> -89.643076 | AN122: =IF(AND(AN$6>='Financing Inputs'!$T$5,AN$6<='Financing Inputs'!$T$19),AL122*(1+'Operating Inputs'!CO$15),0) -> -93.228799
B123: Total Revenue | H123: =+H110+H113+H116+H119+H122 -> 552.31385 | J123: =+J110+J113+J116+J119+J122 -> 702.8271 | L123: =+L110+L113+L116+L119+L122 -> 714.31355 | N123: =+N110+N113+N116+N119+N122 -> 696.87725 | P123: =+P110+P113+P116+P119+P122 -> 640.9916 | R123: =+R110+R113+R116+R119+R122 -> 1225.2416 | T123: =+T110+T113+T116+T119+T122 -> 1241.9811 | V123: =+V110+V113+V116+V119+V122 -> 1284.1343 | X123: =+X110+X113+X116+X119+X122 -> 1371.6797 | Z123: =+Z110+Z113+Z116+Z119+Z122 -> 1457.3677 | AB123: =+AB110+AB113+AB116+AB119+AB122 -> 1532.927 | AD123: =+AD110+AD113+AD116+AD119+AD122 -> 1603.2589 | AF123: =+AF110+AF113+AF116+AF119+AF122 -> 1568.5568 | AH123: =+AH110+AH113+AH116+AH119+AH122 -> 1534.7542 | AJ123: =+AJ110+AJ113+AJ116+AJ119+AJ122 -> 1501.8197 | AL123: =+AL110+AL113+AL116+AL119+AL122 -> 1469.7222 | AN123: =+AN110+AN113+AN116+AN119+AN122 -> 1438.4314
...

Sheet Debt
B2: ABC ltd
H4: Projected Financials
B6: FYE - 12/31, in $mm | H6: ='Financing Inputs'!T5 -> 45657 | J6: =EOMONTH(H6,12) -> 46022 | L6: =EOMONTH(J6,12) -> 46387 | N6: =EOMONTH(L6,12) -> 46752 | P6: =EOMONTH(N6,12) -> 47118 | R6: =EOMONTH(P6,12) -> 47483 | T6: =EOMONTH(R6,12) -> 47848 | V6: =EOMONTH(T6,12) -> 48213 | X6: =EOMONTH(V6,12) -> 48579 | Z6: =EOMONTH(X6,12) -> 48944 | AB6: =EOMONTH(Z6,12) -> 49309
B8: Financial Overview
B10: Debt Calculation
B11: Debt Option - 1
B12: Opening Balance | J12: =H15 -> 1619.25 | L12: =J15 -> 1580.0442 | N12: =L15 -> 1537.31 | P12: =N15 -> 1490.7296 | R12: =P15 -> 1439.957 | T12: =R15 -> 1384.6149 | V12: =T15 -> 1324.292 | X12: =V15 -> 1258.54 | Z12: =X15 -> 1186.8704 | AB12: =Z15 -> 1108.7505
B13: Amortization | F13: =-IF('Financing Inputs'!$L$18=1,PMT('Financing Inputs'!$L$27,'Financing Inputs'!$L$28,'Financing Inputs'!$F$11),0) -> 184.93825 | J13: =-MIN(IF(Financials!BL$6>'Financing Inputs'!$T$19,0,Debt!$F$13+J16),J12) -> -39.205752 | L13: =-MIN(IF(Financials!BN$6>'Financing Inputs'!$T$19,0,Debt!$F$13+L16),L12) -> -42.734269 | N13: =-MIN(IF(Financials!BP$6>'Financing Inputs'!$T$19,0,Debt!$F$13+N16),N12) -> -46.580354 | P13: =-MIN(IF(Financials!BR$6>'Financing Inputs'!$T$19,0,Debt!$F$13+P16),P12) -> -50.772585 | R13: =-MIN(IF(Financials!BT$6>'Financing Inputs'!$T$19,0,Debt!$F$13+R16),R12) -> -55.342118 | T13: =-MIN(IF(Financials!BV$6>'Financing Inputs'!$T$19,0,Debt!$F$13+T16),T12) -> -60.322909 | V13: =-MIN(IF(Financials!BX$6>'Financing Inputs'!$T$19,0,Debt!$F$13+V16),V12) -> -65.75197 | X13: =-MIN(IF(Financials!BZ$6>'Financing Inputs'!$T$19,0,Debt!$F$13+X16),X12) -> -71.669648 | Z13: =-MIN(IF(Financials!CB$6>'Financing Inputs'!$T$19,0,Debt!$F$13+Z16),Z12) -> -78.119916 | AB13: =-MIN(IF(Financials!CD$6>'Financing Inputs'!$T$19,0,Debt!$F$13+AB16),AB12) -> -85.150709
B14: Balloon Payment | J14: =-IF(Financials!V$6='Financing Inputs'!$T$19,J12+J13,0) -> 0 | L14: =-IF(Financials!X$6='Financing Inputs'!$T$19,L12+L13,0) -> 0 | N14: =-IF(Financials!Z$6='Financing Inputs'!$T$19,N12+N13,0) -> 0 | P14: =-IF(Financials!AB$6='Financing Inputs'!$T$19,P12+P13,0) -> 0 | R14: =-IF(Financials!AD$6='Financing Inputs'!$T$19,R12+R13,0) -> 0 | T14: =-IF(Financials!AF$6='Financing Inputs'!$T$19,T12+T13,0) -> 0 | V14: =-IF(Financials!AH$6='Financing Inputs'!$T$19,V12+V13,0) -> 0 | X14: =-IF(Financials!AJ$6='Financing Inputs'!$T$19,X12+X13,0) -> 0 | Z14: =-IF(Financials!AL$6='Financing Inputs'!$T$19,Z12+Z13,0) -> 0 | AB14: =-IF(Financials!AN$6='Financing Inputs'!$T$19,AB12+AB13,0) -> -1023.5998
B15: Closing Balance | H15: =IF(AND('Financing Inputs'!$L$18=1,Financials!T$6='Financing Inputs'!$T$5),'Financing Inputs'!$F$11,SUM(H12:H14)) -> 1619.25 | J15: =IF(AND('Financing Inputs'!$L$18=1,Financials!V$6='Financing Inputs'!$T$5),'Financing Inputs'!$F$11,SUM(J12:J14)) -> 1580.0442 | L15: =IF(AND('Financing Inputs'!$L$18=1,Financials!X$6='Financing Inputs'!$T$5),'Financing Inputs'!$F$11,SUM(L12:L14)) -> 1537.31 | N15: =IF(AND('Financing Inputs'!$L$18=1,Financials!Z$6='Financing Inputs'!$T$5),'Financing Inputs'!$F$11,SUM(N12:N14)) -> 1490.7296 | P15: =IF(AND('Financing Inputs'!$L$18=1,Financials!AB$6='Financing Inputs'!$T$5),'Financing Inputs'!$F$11,SUM(P12:P14)) -> 1439.957 | R15: =IF(AND('Financing Inputs'!$L$18=1,Financials!AD$6='Financing Inputs'!$T$5),'Financing Inputs'!$F$11,SUM(R12:R14)) -> 1384.6149 | T15: =IF(AND('Financing Inputs'!$L$18=1,Financials!AF$6='Financing Inputs'!$T$5),'Financing Inputs'!$F$11,SUM(T12:T14)) -> 1324.292 | V15: =IF(AND('Financing Inputs'!$L$18=1,Financials!AH$6='Financing Inputs'!$T$5),'Financing Inputs'!$F$11,SUM(V12:V14)) -> 1258.54 | X15: =IF(AND('Financing Inputs'!$L$18=1,Financials!AJ$6='Financing Inputs'!$T$5),'Financing Inputs'!$F$11,SUM(X12:X14)) -> 1186.8704 | Z15: =IF(AND('Financing Inputs'!$L$18=1,Financials!AL$6='Financing Inputs'!$T$5),'Financing Inputs'!$F$11,SUM(Z12:Z14)) -> 1108.7505 | AB15: =IF(AND('Financing Inputs'!$L$18=1,Financials!AN$6='Financing Inputs'!$T$5),'Financing Inputs'!$F$11,SUM(AB12:AB14)) -> 0
B16: Interest Expense | F16: =IF('Financing Inputs'!$L$18=1,'Financing Inputs'!$L$27,0) -> 0.09 | J16: =-H15*Debt!$F$16 -> -145.7325 | L16: =-J15*Debt!$F$16 -> -142.20398 | N16: =-L15*Debt!$F$16 -> -138.3579 | P16: =-N15*Debt!$F$16 -> -134.16567 | R16: =-P15*Debt!$F$16 -> -129.59613 | T16: =-R15*Debt!$F$16 -> -124.61534 | V16: =-T15*Debt!$F$16 -> -119.18628 | X16: =-V15*Debt!$F$16 -> -113.2686 | Z16: =-X15*Debt!$F$16 -> -106.81834 | AB16: =-Z15*Debt!$F$16 -> -99.787543
B18: Debt Option - 2
B19: Opening Balance | J19: =H22 -> 0 | L19: =J22 -> 0 | N19: =L22 -> 0 | P19: =N22 -> 0 | R19: =P22 -> 0 | T19: =R22 -> 0 | V19: =T22 -> 0 | X19: =V22 -> 0 | Z19: =X22 -> 0 | AB19: =Z22 -> 0
B20: Amortization | F20: =IF('Financing Inputs'!$L$18=2,'Financing Inputs'!$F$11*'Financing Inputs'!$L$36,0) -> 0 | J20: =-MIN(IF(Financials!V$6>'Financing Inputs'!$J$36,IF(Financials!V$6>'Financing Inputs'!$T$19,0,Debt!$F$20),0)/IF(YEAR(Financials!V$6)=YEAR('Financing Inputs'!$J$36),IFERROR(12/(ROUND((YEARFRAC('Financing Inputs'!$J$36,Financials!V$6,1))*12,0)),1),1),J19) -> 0 | L20: =-MIN(IF(Financials!X$6>'Financing Inputs'!$J$36,IF(Financials!X$6>'Financing Inputs'!$T$19,0,Debt!$F$20),0)/IF(YEAR(Financials!X$6)=YEAR('Financing Inputs'!$J$36),IFERROR(12/(ROUND((YEARFRAC('Financing Inputs'!$J$36,Financials!X$6,1))*12,0)),1),1),L19) -> 0 | N20: =-MIN(IF(Financials!Z$6>'Financing Inputs'!$J$36,IF(Financials!Z$6>'Financing Inputs'!$T$19,0,Debt!$F$20),0)/IF(YEAR(Financials!Z$6)=YEAR('Financing Inputs'!$J$36),IFERROR(12/(ROUND((YEARFRAC('Financing Inputs'!$J$36,Financials!Z$6,1))*12,0)),1),1),N19) -> 0 | P20: =-MIN(IF(Financials!AB$6>'Financing Inputs'!$J$36,IF(Financials!AB$6>'Financing Inputs'!$T$19,0,Debt!$F$20),0)/IF(YEAR(Financials!AB$6)=YEAR('Financing Inputs'!$J$36),IFERROR(12/(ROUND((YEARFRAC('Financing Inputs'!$J$36,Financials!AB$6,1))*12,0)),1),1),P19) -> 0 | R20: =-MIN(IF(Financials!AD$6>'Financing Inputs'!$J$36,IF(Financials!AD$6>'Financing Inputs'!$T$19,0,Debt!$F$20),0)/IF(YEAR(Financials!AD$6)=YEAR('Financing Inputs'!$J$36),IFERROR(12/(ROUND((YEARFRAC('Financing Inputs'!$J$36,Financials!AD$6,1))*12,0)),1),1),R19) -> 0 | T20: =-MIN(IF(Financials!AF$6>'Financing Inputs'!$J$36,IF(Financials!AF$6>'Financing Inputs'!$T$19,0,Debt!$F$20),0)/IF(YEAR(Financials!AF$6)=YEAR('Financing Inputs'!$J$36),IFERROR(12/(ROUND((YEARFRAC('Financing Inputs'!$J$36,Financials!AF$6,1))*12,0)),1),1),T19) -> 0 | V20: =-MIN(IF(Financials!AH$6>'Financing Inputs'!$J$36,IF(Financials!AH$6>'Financing Inputs'!$T$19,0,Debt!$F$20),0)/IF(YEAR(Financials!AH$6)=YEAR('Financing Inputs'!$J$36),IFERROR(12/(ROUND((YEARFRAC('Financing Inputs'!$J$36,Financials!AH$6,1))*12,0)),1),1),V19) -> 0 | X20: =-MIN(IF(Financials!AJ$6>'Financing Inputs'!$J$36,IF(Financials!AJ$6>'Financing Inputs'!$T$19,0,Debt!$F$20),0)/IF(YEAR(Financials!AJ$6)=YEAR('Financing Inputs'!$J$36),IFERROR(12/(ROUND((YEARFRAC('Financing Inputs'!$J$36,Financials!AJ$6,1))*12,0)),1),1),X19) -> 0 | Z20: =-MIN(IF(Financials!AL$6>'Financing Inputs'!$J$36,IF(Financials!AL$6>'Financing Inputs'!$T$19,0,Debt!$F$20),0)/IF(YEAR(Financials!AL$6)=YEAR('Financing Inputs'!$J$36),IFERROR(12/(ROUND((YEARFRAC('Financing Inputs'!$J$36,Financials!AL$6,1))*12,0)),1),1),Z19) -> 0 | AB20: =-MIN(IF(Financials!AN$6>'Financing Inputs'!$J$36,IF(Financials!AN$6>'Financing Inputs'!$T$19,0,Debt!$F$20),0)/IF(YEAR(Financials!AN$6)=YEAR('Financing Inputs'!$J$36),IFERROR(12/(ROUND((YEARFRAC('Financing Inputs'!$J$36,Financials!AN$6,1))*12,0)),1),1),AB19) -> 0
B21: Balloon Payment | J21: =-IF(Financials!V$6='Financing Inputs'!$T$19,J19+J20,0) -> 0 | L21: =-IF(Financials!X$6='Financing Inputs'!$T$19,L19+L20,0) -> 0 | N21: =-IF(Financials!Z$6='Financing Inputs'!$T$19,N19+N20,0) -> 0 | P21: =-IF(Financials!AB$6='Financing Inputs'!$T$19,P19+P20,0) -> 0 | R21: =-IF(Financials!AD$6='Financing Inputs'!$T$19,R19+R20,0) -> 0 | T21: =-IF(Financials!AF$6='Financing Inputs'!$T$19,T19+T20,0) -> 0 | V21: =-IF(Financials!AH$6='Financing Inputs'!$T$19,V19+V20,0) -> 0 | X21: =-IF(Financials!AJ$6='Financing Inputs'!$T$19,X19+X20,0) -> 0 | Z21: =-IF(Financials!AL$6='Financing Inputs'!$T$19,Z19+Z20,0) -> 0 | AB21: =-IF(Financials!AN$6='Financing Inputs'!$T$19,AB19+AB20,0) -> 0
B22: Closing Balance | H22: =IF(AND('Financing Inputs'!$L$18=2,Financials!T$6='Financing Inputs'!$T$5),'Financing Inputs'!$F$11,SUM(H19:H21)) -> 0 | J22: =IF(AND('Financing Inputs'!$L$18=2,Financials!V$6='Financing Inputs'!$T$5),'Financing Inputs'!$F$11,SUM(J19:J21)) -> 0 | L22: =IF(AND('Financing Inputs'!$L$18=2,Financials!X$6='Financing Inputs'!$T$5),'Financing Inputs'!$F$11,SUM(L19:L21)) -> 0 | N22: =IF(AND('Financing Inputs'!$L$18=2,Financials!Z$6='Financing Inputs'!$T$5),'Financing Inputs'!$F$11,SUM(N19:N21)) -> 0 | P22: =IF(AND('Financing Inputs'!$L$18=2,Financials!AB$6='Financing Inputs'!$T$5),'Financing Inputs'!$F$11,SUM(P19:P21)) -> 0 | R22: =IF(AND('Financing Inputs'!$L$18=2,Financials!AD$6='Financing Inputs'!$T$5),'Financing Inputs'!$F$11,SUM(R19:R21)) -> 0 | T22: =IF(AND('Financing Inputs'!$L$18=2,Financials!AF$6='Financing Inputs'!$T$5),'Financing Inputs'!$F$11,SUM(T19:T21)) -> 0 | V22: =IF(AND('Financing Inputs'!$L$18=2,Financials!AH$6='Financing Inputs'!$T$5),'Financing Inputs'!$F$11,SUM(V19:V21)) -> 0 | X22: =IF(AND('Financing Inputs'!$L$18=2,Financials!AJ$6='Financing Inputs'!$T$5),'Financing Inputs'!$F$11,SUM(X19:X21)) -> 0 | Z22: =IF(AND('Financing Inputs'!$L$18=2,Financials!AL$6='Financing Inputs'!$T$5),'Financing Inputs'!$F$11,SUM(Z19:Z21)) -> 0 | AB22: =IF(AND('Financing Inputs'!$L$18=2,Financials!AN$6='Financing Inputs'!$T$5),'Financing Inputs'!$F$11,SUM(AB19:AB21)) -> 0
B23: Interest Expense | J23: =-H22*('Financing Inputs'!$L$33)-IF(Financials!V$6>'Financing Inputs'!$J$34,'Financing Inputs'!$L$34*H22,0)/IF(YEAR(Financials!V$6)=YEAR('Financing Inputs'!$J$34),IFERROR(12/(ROUND((YEARFRAC('Financing Inputs'!$J$34,Financials!V$6,1))*12,0)),1),1)-IF(Financials!V$6>'Financing Inputs'!$J$35,'Financing Inputs'!$L$35*H22,0)/IF(YEAR(Financials!V$6)=YEAR('Financing Inputs'!$J$35),IFERROR(12/(ROUND((YEARFRAC('Financing Inputs'!$J$35,Financials!V$6,1))*12,0)),1),1) -> 0 | L23: =-J22*('Financing Inputs'!$L$33)-IF(Financials!X$6>'Financing Inputs'!$J$34,'Financing Inputs'!$L$34*J22,0)/IF(YEAR(Financials!X$6)=YEAR('Financing Inputs'!$J$34),IFERROR(12/(ROUND((YEARFRAC('Financing Inputs'!$J$34,Financials!X$6,1))*12,0)),1),1)-IF(Financials!X$6>'Financing Inputs'!$J$35,'Financing Inputs'!$L$35*J22,0)/IF(YEAR(Financials!X$6)=YEAR('Financing Inputs'!$J$35),IFERROR(12/(ROUND((YEARFRAC('Financing Inputs'!$J$35,Financials!X$6,1))*12,0)),1),1) -> 0 | N23: =-L22*('Financing Inputs'!$L$33)-IF(Financials!Z$6>'Financing Inputs'!$J$34,'Financing Inputs'!$L$34*L22,0)/IF(YEAR(Financials!Z$6)=YEAR('Financing Inputs'!$J$34),IFERROR(12/(ROUND((YEARFRAC('Financing Inputs'!$J$34,Financials!Z$6,1))*12,0)),1),1)-IF(Financials!Z$6>'Financing Inputs'!$J$35,'Financing Inputs'!$L$35*L22,0)/IF(YEAR(Financials!Z$6)=YEAR('Financing Inputs'!$J$35),IFERROR(12/(ROUND((YEARFRAC('Financing Inputs'!$J$35,Financials!Z$6,1))*12,0)),1),1) -> 0 | P23: =-N22*('Financing Inputs'!$L$33)-IF(Financials!AB$6>'Financing Inputs'!$J$34,'Financing Inputs'!$L$34*N22,0)/IF(YEAR(Financials!AB$6)=YEAR('Financing Inputs'!$J$34),IFERROR(12/(ROUND((YEARFRAC('Financing Inputs'!$J$34,Financials!AB$6,1))*12,0)),1),1)-IF(Financials!AB$6>'Financing Inputs'!$J$35,'Financing Inputs'!$L$35*N22,0)/IF(YEAR(Financials!AB$6)=YEAR('Financing Inputs'!$J$35),IFERROR(12/(ROUND((YEARFRAC('Financing Inputs'!$J$35,Financials!AB$6,1))*12,0)),1),1) -> 0 | R23: =-P22*('Financing Inputs'!$L$33)-IF(Financials!AD$6>'Financing Inputs'!$J$34,'Financing Inputs'!$L$34*P22,0)/IF(YEAR(Financials!AD$6)=YEAR('Financing Inputs'!$J$34),IFERROR(12/(ROUND((YEARFRAC('Financing Inputs'!$J$34,Financials!AD$6,1))*12,0)),1),1)-IF(Financials!AD$6>'Financing Inputs'!$J$35,'Financing Inputs'!$L$35*P22,0)/IF(YEAR(Financials!AD$6)=YEAR('Financing Inputs'!$J$35),IFERROR(12/(ROUND((YEARFRAC('Financing Inputs'!$J$35,Financials!AD$6,1))*12,0)),1),1) -> 0 | T23: =-R22*('Financing Inputs'!$L$33)-IF(Financials!AF$6>'Financing Inputs'!$J$34,'Financing Inputs'!$L$34*R22,0)/IF(YEAR(Financials!AF$6)=YEAR('Financing Inputs'!$J$34),IFERROR(12/(ROUND((YEARFRAC('Financing Inputs'!$J$34,Financials!AF$6,1))*12,0)),1),1)-IF(Financials!AF$6>'Financing Inputs'!$J$35,'Financing Inputs'!$L$35*R22,0)/IF(YEAR(Financials!AF$6)=YEAR('Financing Inputs'!$J$35),IFERROR(12/(ROUND((YEARFRAC('Financing Inputs'!$J$35,Financials!AF$6,1))*12,0)),1),1) -> 0 | V23: =-T22*('Financing Inputs'!$L$33)-IF(Financials!AH$6>'Financing Inputs'!$J$34,'Financing Inputs'!$L$34*T22,0)/IF(YEAR(Financials!AH$6)=YEAR('Financing Inputs'!$J$34),IFERROR(12/(ROUND((YEARFRAC('Financing Inputs'!$J$34,Financials!AH$6,1))*12,0)),1),1)-IF(Financials!AH$6>'Financing Inputs'!$J$35,'Financing Inputs'!$L$35*T22,0)/IF(YEAR(Financials!AH$6)=YEAR('Financing Inputs'!$J$35),IFERROR(12/(ROUND((YEARFRAC('Financing Inputs'!$J$35,Financials!AH$6,1))*12,0)),1),1) -> 0 | X23: =-V22*('Financing Inputs'!$L$33)-IF(Financials!AJ$6>'Financing Inputs'!$J$34,'Financing Inputs'!$L$34*V22,0)/IF(YEAR(Financials!AJ$6)=YEAR('Financing Inputs'!$J$34),IFERROR(12/(ROUND((YEARFRAC('Financing Inputs'!$J$34,Financials!AJ$6,1))*12,0)),1),1)-IF(Financials!AJ$6>'Financing Inputs'!$J$35,'Financing Inputs'!$L$35*V22,0)/IF(YEAR(Financials!AJ$6)=YEAR('Financing Inputs'!$J$35),IFERROR(12/(ROUND((YEARFRAC('Financing Inputs'!$J$35,Financials!AJ$6,1))*12,0)),1),1) -> 0 | Z23: =-X22*('Financing Inputs'!$L$33)-IF(Financials!AL$6>'Financing Inputs'!$J$34,'Financing Inputs'!$L$34*X22,0)/IF(YEAR(Financials!AL$6)=YEAR('Financing Inputs'!$J$34),IFERROR(12/(ROUND((YEARFRAC('Financing Inputs'!$J$34,Financials!AL$6,1))*12,0)),1),1)-IF(Financials!AL$6>'Financing Inputs'!$J$35,'Financing Inputs'!$L$35*X22,0)/IF(YEAR(Financials!AL$6)=YEAR('Financing Inputs'!$J$35),IFERROR(12/(ROUND((YEARFRAC('Financing Inputs'!$J$35,Financials!AL$6,1))*12,0)),1),1) -> 0 | AB23: =-Z22*('Financing Inputs'!$L$33)-IF(Financials!AN$6>'Financing Inputs'!$J$34,'Financing Inputs'!$L$34*Z22,0)/IF(YEAR(Financials!AN$6)=YEAR('Financing Inputs'!$J$34),IFERROR(12/(ROUND((YEARFRAC('Financing Inputs'!$J$34,Financials!AN$6,1))*12,0)),1),1)-IF(Financials!AN$6>'Financing Inputs'!$J$35,'Financing Inputs'!$L$35*Z22,0)/IF(YEAR(Financials!AN$6)=YEAR('Financing Inputs'!$J$35),IFERROR(12/(ROUND((YEARFRAC('Financing Inputs'!$J$35,Financials!AN$6,1))*12,0)),1),1) -> 0
B25: Refinance Debt Option
B26: Debt 1
B27: Opening Balance | J27: =H29 -> 0 | L27: =J29 -> 0 | N27: =L29 -> 0 | P27: =N29 -> 0 | R27: =P29 -> 0 | T27: =R29 -> 0 | V27: =T29 -> 0 | X27: =V29 -> 0 | Z27: =X29 -> 0 | AB27: =Z29 -> 0
B28: Balloon Payment | J28: =-IF(OR(Financials!V$6='Financing Inputs'!$T$19,YEAR(Financials!V$6)=YEAR('Financing Inputs'!$L$46)),J27,0) -> 0 | L28: =-IF(OR(Financials!X$6='Financing Inputs'!$T$19,YEAR(Financials!X$6)=YEAR('Financing Inputs'!$L$46)),L27,0) -> 0 | N28: =-IF(OR(Financials!Z$6='Financing Inputs'!$T$19,YEAR(Financials!Z$6)=YEAR('Financing Inputs'!$L$46)),N27,0) -> 0 | P28: =-IF(OR(Financials!AB$6='Financing Inputs'!$T$19,YEAR(Financials!AB$6)=YEAR('Financing Inputs'!$L$46)),P27,0) -> 0 | R28: =-IF(OR(Financials!AD$6='Financing Inputs'!$T$19,YEAR(Financials!AD$6)=YEAR('Financing Inputs'!$L$46)),R27,0) -> 0 | T28: =-IF(OR(Financials!AF$6='Financing Inputs'!$T$19,YEAR(Financials!AF$6)=YEAR('Financing Inputs'!$L$46)),T27,0) -> 0 | V28: =-IF(OR(Financials!AH$6='Financing Inputs'!$T$19,YEAR(Financials!AH$6)=YEAR('Financing Inputs'!$L$46)),V27,0) -> 0 | X28: =-IF(OR(Financials!AJ$6='Financing Inputs'!$T$19,YEAR(Financials!AJ$6)=YEAR('Financing Inputs'!$L$46)),X27,0) -> 0 | Z28: =-IF(OR(Financials!AL$6='Financing Inputs'!$T$19,YEAR(Financials!AL$6)=YEAR('Financing Inputs'!$L$46)),Z27,0) -> 0 | AB28: =-IF(OR(Financials!AN$6='Financing Inputs'!$T$19,YEAR(Financials!AN$6)=YEAR('Financing Inputs'!$L$46)),AB27,0) -> 0
B29: Closing Balance | H29: =IF(AND('Financing Inputs'!$L$43=1,Financials!T$6='Financing Inputs'!$T$5),'Financing Inputs'!$L$45,SUM(H27:H28)) -> 0 | J29: =IF(AND('Financing Inputs'!$L$43=1,Financials!V$6='Financing Inputs'!$T$5),'Financing Inputs'!$L$45,SUM(J27:J28)) -> 0 | L29: =IF(AND('Financing Inputs'!$L$43=1,Financials!X$6='Financing Inputs'!$T$5),'Financing Inputs'!$L$45,SUM(L27:L28)) -> 0 | N29: =IF(AND('Financing Inputs'!$L$43=1,Financials!Z$6='Financing Inputs'!$T$5),'Financing Inputs'!$L$45,SUM(N27:N28)) -> 0 | P29: =IF(AND('Financing Inputs'!$L$43=1,Financials!AB$6='Financing Inputs'!$T$5),'Financing Inputs'!$L$45,SUM(P27:P28)) -> 0 | R29: =IF(AND('Financing Inputs'!$L$43=1,Financials!AD$6='Financing Inputs'!$T$5),'Financing Inputs'!$L$45,SUM(R27:R28)) -> 0 | T29: =IF(AND('Financing Inputs'!$L$43=1,Financials!AF$6='Financing Inputs'!$T$5),'Financing Inputs'!$L$45,SUM(T27:T28)) -> 0 | V29: =IF(AND('Financing Inputs'!$L$43=1,Financials!AH$6='Financing Inputs'!$T$5),'Financing Inputs'!$L$45,SUM(V27:V28)) -> 0 | X29: =IF(AND('Financing Inputs'!$L$43=1,Financials!AJ$6='Financing Inputs'!$T$5),'Financing Inputs'!$L$45,SUM(X27:X28)) -> 0 | Z29: =IF(AND('Financing Inputs'!$L$43=1,Financials!AL$6='Financing Inputs'!$T$5),'Financing Inputs'!$L$45,SUM(Z27:Z28)) -> 0 | AB29: =IF(AND('Financing Inputs'!$L$43=1,Financials!AN$6='Financing Inputs'!$T$5),'Financing Inputs'!$L$45,SUM(AB27:AB28)) -> 0
B30: Interest Expense | F30: =IF('Financing Inputs'!$L$43=1,'Financing Inputs'!$L$44,0) -> 0 | J30: =-(Debt!$F$30*H29)/IF(YEAR(Financials!BL$6)=YEAR('Financing Inputs'!$L$46),IFERROR(12/(12-ROUND((YEARFRAC(Financials!BL$6,'Financing Inputs'!$L$46,1)*12),0)),1),1) -> 0 | L30: =-(Debt!$F$30*J29)/IF(YEAR(Financials!BN$6)=YEAR('Financing Inputs'!$L$46),IFERROR(12/(12-ROUND((YEARFRAC(Financials!BN$6,'Financing Inputs'!$L$46,1)*12),0)),1),1) -> 0 | N30: =-(Debt!$F$30*L29)/IF(YEAR(Financials!BP$6)=YEAR('Financing Inputs'!$L$46),IFERROR(12/(12-ROUND((YEARFRAC(Financials!BP$6,'Financing Inputs'!$L$46,1)*12),0)),1),1) -> 0 | P30: =-(Debt!$F$30*N29)/IF(YEAR(Financials!BR$6)=YEAR('Financing Inputs'!$L$46),IFERROR(12/(12-ROUND((YEARFRAC(Financials!BR$6,'Financing Inputs'!$L$46,1)*12),0)),1),1) -> 0 | R30: =-(Debt!$F$30*P29)/IF(YEAR(Financials!BT$6)=YEAR('Financing Inputs'!$L$46),IFERROR(12/(12-ROUND((YEARFRAC(Financials!BT$6,'Financing Inputs'!$L$46,1)*12),0)),1),1) -> 0 | T30: =-(Debt!$F$30*R29)/IF(YEAR(Financials!BV$6)=YEAR('Financing Inputs'!$L$46),IFERROR(12/(12-ROUND((YEARFRAC(Financials!BV$6,'Financing Inputs'!$L$46,1)*12),0)),1),1) -> 0 | V30: =-(Debt!$F$30*T29)/IF(YEAR(Financials!BX$6)=YEAR('Financing Inputs'!$L$46),IFERROR(12/(12-ROUND((YEARFRAC(Financials!BX$6,'Financing Inputs'!$L$46,1)*12),0)),1),1) -> 0 | X30: =-(Debt!$F$30*V29)/IF(YEAR(Financials!BZ$6)=YEAR('Financing Inputs'!$L$46),IFERROR(12/(12-ROUND((YEARFRAC(Financials!BZ$6,'Financing Inputs'!$L$46,1)*12),0)),1),1) -> 0 | Z30: =-(Debt!$F$30*X29)/IF(YEAR(Financials!CB$6)=YEAR('Financing Inputs'!$L$46),IFERROR(12/(12-ROUND((YEARFRAC(Financials!CB$6,'Financing Inputs'!$L$46,1)*12),0)),1),1) -> 0 | AB30: =-(Debt!$F$30*Z29)/IF(YEAR(Financials!CD$6)=YEAR('Financing Inputs'!$L$46),IFERROR(12/(12-ROUND((YEARFRAC(Financials!CD$6,'Financing Inputs'!$L$46,1)*12),0)),1),1) -> 0
B32: Debt 2
B33: Opening Balance | J33: =H36 -> 0 | L33: =J36 -> 0 | N33: =L36 -> 0 | P33: =N36 -> 0 | R33: =P36 -> 0 | T33: =R36 -> 0 | V33: =T36 -> 0 | X33: =V36 -> 0 | Z33: =X36 -> 0 | AB33: =Z36 -> 0
B34: Amortization | F34: =IF('Financing Inputs'!$L$48=1,'Financing Inputs'!$L$51,0) -> 0 | J34: =-MIN(IF(Financials!BL$6>'Financing Inputs'!$T$19,0,Debt!$F$34),J33) -> 0 | L34: =-MIN(IF(Financials!BN$6>'Financing Inputs'!$T$19,0,Debt!$F$34),L33) -> 0 | N34: =-MIN(IF(Financials!BP$6>'Financing Inputs'!$T$19,0,Debt!$F$34),N33) -> 0 | P34: =-MIN(IF(Financials!BR$6>'Financing Inputs'!$T$19,0,Debt!$F$34),P33) -> 0 | R34: =-MIN(IF(Financials!BT$6>'Financing Inputs'!$T$19,0,Debt!$F$34),R33) -> 0 | T34: =-MIN(IF(Financials!BV$6>'Financing Inputs'!$T$19,0,Debt!$F$34),T33) -> 0 | V34: =-MIN(IF(Financials!BX$6>'Financing Inputs'!$T$19,0,Debt!$F$34),V33) -> 0 | X34: =-MIN(IF(Financials!BZ$6>'Financing Inputs'!$T$19,0,Debt!$F$34),X33) -> 0 | Z34: =-MIN(IF(Financials!CB$6>'Financing Inputs'!$T$19,0,Debt!$F$34),Z33) -> 0 | AB34: =-MIN(IF(Financials!CD$6>'Financing Inputs'!$T$19,0,Debt!$F$34),AB33) -> 0
B35: Balloon Payment | J35: =-IF(OR(Financials!V$6='Financing Inputs'!$T$19,YEAR(Financials!V$6)=YEAR('Financing Inputs'!$L$52)),J33+J34,0) -> 0 | L35: =-IF(OR(Financials!X$6='Financing Inputs'!$T$19,YEAR(Financials!X$6)=YEAR('Financing Inputs'!$L$52)),L33+L34,0) -> 0 | N35: =-IF(OR(Financials!Z$6='Financing Inputs'!$T$19,YEAR(Financials!Z$6)=YEAR('Financing Inputs'!$L$52)),N33+N34,0) -> 0 | P35: =-IF(OR(Financials!AB$6='Financing Inputs'!$T$19,YEAR(Financials!AB$6)=YEAR('Financing Inputs'!$L$52)),P33+P34,0) -> 0 | R35: =-IF(OR(Financials!AD$6='Financing Inputs'!$T$19,YEAR(Financials!AD$6)=YEAR('Financing Inputs'!$L$52)),R33+R34,0) -> 0 | T35: =-IF(OR(Financials!AF$6='Financing Inputs'!$T$19,YEAR(Financials!AF$6)=YEAR('Financing Inputs'!$L$52)),T33+T34,0) -> 0 | V35: =-IF(OR(Financials!AH$6='Financing Inputs'!$T$19,YEAR(Financials!AH$6)=YEAR('Financing Inputs'!$L$52)),V33+V34,0) -> 0 | X35: =-IF(OR(Financials!AJ$6='Financing Inputs'!$T$19,YEAR(Financials!AJ$6)=YEAR('Financing Inputs'!$L$52)),X33+X34,0) -> 0 | Z35: =-IF(OR(Financials!AL$6='Financing Inputs'!$T$19,YEAR(Financials!AL$6)=YEAR('Financing Inputs'!$L$52)),Z33+Z34,0) -> 0 | AB35: =-IF(OR(Financials!AN$6='Financing Inputs'!$T$19,YEAR(Financials!AN$6)=YEAR('Financing Inputs'!$L$52)),AB33+AB34,0) -> 0
B36: Closing Balance | H36: =IF(AND('Financing Inputs'!$L$48=1,Financials!T$6='Financing Inputs'!$T$5),'Financing Inputs'!$L$50,SUM(H33:H35)) -> 0 | J36: =IF(AND('Financing Inputs'!$L$48=1,Financials!V$6='Financing Inputs'!$T$5),'Financing Inputs'!$L$50,SUM(J33:J35)) -> 0 | L36: =IF(AND('Financing Inputs'!$L$48=1,Financials!X$6='Financing Inputs'!$T$5),'Financing Inputs'!$L$50,SUM(L33:L35)) -> 0 | N36: =IF(AND('Financing Inputs'!$L$48=1,Financials!Z$6='Financing Inputs'!$T$5),'Financing Inputs'!$L$50,SUM(N33:N35)) -> 0 | P36: =IF(AND('Financing Inputs'!$L$48=1,Financials!AB$6='Financing Inputs'!$T$5),'Financing Inputs'!$L$50,SUM(P33:P35)) -> 0 | R36: =IF(AND('Financing Inputs'!$L$48=1,Financials!AD$6='Financing Inputs'!$T$5),'Financing Inputs'!$L$50,SUM(R33:R35)) -> 0 | T36: =IF(AND('Financing Inputs'!$L$48=1,Financials!AF$6='Financing Inputs'!$T$5),'Financing Inputs'!$L$50,SUM(T33:T35)) -> 0 | V36: =IF(AND('Financing Inputs'!$L$48=1,Financials!AH$6='Financing Inputs'!$T$5),'Financing Inputs'!$L$50,SUM(V33:V35)) -> 0 | X36: =IF(AND('Financing Inputs'!$L$48=1,Financials!AJ$6='Financing Inputs'!$T$5),'Financing Inputs'!$L$50,SUM(X33:X35)) -> 0 | Z36: =IF(AND('Financing Inputs'!$L$48=1,Financials!AL$6='Financing Inputs'!$T$5),'Financing Inputs'!$L$50,SUM(Z33:Z35)) -> 0 | AB36: =IF(AND('Financing Inputs'!$L$48=1,Financials!AN$6='Financing Inputs'!$T$5),'Financing Inputs'!$L$50,SUM(AB33:AB35)) -> 0
B37: Interest Expense | F37: =IF('Financing Inputs'!$L$48=1,'Financing Inputs'!$L$49,0) -> 0 | J37: =-(Debt!$F$37*H36)/IF(YEAR(Financials!BL$6)=YEAR('Financing Inputs'!$L$52),IFERROR(12/(12-ROUND((YEARFRAC(Financials!BL$6,'Financing Inputs'!$L$52,1)*12),0)),1),1) -> 0 | L37: =-(Debt!$F$37*J36)/IF(YEAR(Financials!BN$6)=YEAR('Financing Inputs'!$L$52),IFERROR(12/(12-ROUND((YEARFRAC(Financials!BN$6,'Financing Inputs'!$L$52,1)*12),0)),1),1) -> 0 | N37: =-(Debt!$F$37*L36)/IF(YEAR(Financials!BP$6)=YEAR('Financing Inputs'!$L$52),IFERROR(12/(12-ROUND((YEARFRAC(Financials!BP$6,'Financing Inputs'!$L$52,1)*12),0)),1),1) -> 0 | P37: =-(Debt!$F$37*N36)/IF(YEAR(Financials!BR$6)=YEAR('Financing Inputs'!$L$52),IFERROR(12/(12-ROUND((YEARFRAC(Financials!BR$6,'Financing Inputs'!$L$52,1)*12),0)),1),1) -> 0 | R37: =-(Debt!$F$37*P36)/IF(YEAR(Financials!BT$6)=YEAR('Financing Inputs'!$L$52),IFERROR(12/(12-ROUND((YEARFRAC(Financials!BT$6,'Financing Inputs'!$L$52,1)*12),0)),1),1) -> 0 | T37: =-(Debt!$F$37*R36)/IF(YEAR(Financials!BV$6)=YEAR('Financing Inputs'!$L$52),IFERROR(12/(12-ROUND((YEARFRAC(Financials!BV$6,'Financing Inputs'!$L$52,1)*12),0)),1),1) -> 0 | V37: =-(Debt!$F$37*T36)/IF(YEAR(Financials!BX$6)=YEAR('Financing Inputs'!$L$52),IFERROR(12/(12-ROUND((YEARFRAC(Financials!BX$6,'Financing Inputs'!$L$52,1)*12),0)),1),1) -> 0 | X37: =-(Debt!$F$37*V36)/IF(YEAR(Financials!BZ$6)=YEAR('Financing Inputs'!$L$52),IFERROR(12/(12-ROUND((YEARFRAC(Financials!BZ$6,'Financing Inputs'!$L$52,1)*12),0)),1),1) -> 0 | Z37: =-(Debt!$F$37*X36)/IF(YEAR(Financials!CB$6)=YEAR('Financing Inputs'!$L$52),IFERROR(12/(12-ROUND((YEARFRAC(Financials!CB$6,'Financing Inputs'!$L$52,1)*12),0)),1),1) -> 0 | AB37: =-(Debt!$F$37*Z36)/IF(YEAR(Financials!CD$6)=YEAR('Financing Inputs'!$L$52),IFERROR(12/(12-ROUND((YEARFRAC(Financials!CD$6,'Financing Inputs'!$L$52,1)*12),0)),1),1) -> 0
B39: Refinance Debt Calculation
B40: Refinance Debt - 1
B41: Opening Balance | J41: =H45 -> 0 | L41: =J45 -> 0 | N41: =L45 -> 0 | P41: =N45 -> 0 | R41: =P45 -> 0 | T41: =R45 -> 0 | V41: =T45 -> 0 | X41: =V45 -> 0 | Z41: =X45 -> 0 | AB41: =Z45 -> 0
B42: Debt Addition | J42: =-IF(AND('Financing Inputs'!$T$31=3,'Financing Inputs'!$T$36=1),J$28,0) -> 0 | L42: =-IF(AND('Financing Inputs'!$T$31=3,'Financing Inputs'!$T$36=1),L$28,0) -> 0 | N42: =-IF(AND('Financing Inputs'!$T$31=3,'Financing Inputs'!$T$36=1),N$28,0) -> 0 | P42: =-IF(AND('Financing Inputs'!$T$31=3,'Financing Inputs'!$T$36=1),P$28,0) -> 0 | R42: =-IF(AND('Financing Inputs'!$T$31=3,'Financing Inputs'!$T$36=1),R$28,0) -> 0 | T42: =-IF(AND('Financing Inputs'!$T$31=3,'Financing Inputs'!$T$36=1),T$28,0) -> 0 | V42: =-IF(AND('Financing Inputs'!$T$31=3,'Financing Inputs'!$T$36=1),V$28,0) -> 0 | X42: =-IF(AND('Financing Inputs'!$T$31=3,'Financing Inputs'!$T$36=1),X$28,0) -> 0 | Z42: =-IF(AND('Financing Inputs'!$T$31=3,'Financing Inputs'!$T$36=1),Z$28,0) -> 0 | AB42: =-IF(AND('Financing Inputs'!$T$31=3,'Financing Inputs'!$T$36=1),AB$28,0) -> 0
B43: Amortization | F43: =-IF(AND('Financing Inputs'!$T$31=3,'Financing Inputs'!$T$36=1),PMT('Financing Inputs'!$L$27,'Financing Inputs'!$L$28,SUM(Debt!J42:AB42)),0) -> 0 | J43: =-MIN(IF(Financials!BL$6>'Financing Inputs'!$T$19,0,Debt!$F$43+J46),J41) -> 0 | L43: =-MIN(IF(Financials!BN$6>'Financing Inputs'!$T$19,0,Debt!$F$43+L46),L41) -> 0 | N43: =-MIN(IF(Financials!BP$6>'Financing Inputs'!$T$19,0,Debt!$F$43+N46),N41) -> 0 | P43: =-MIN(IF(Financials!BR$6>'Financing Inputs'!$T$19,0,Debt!$F$43+P46),P41) -> 0 | R43: =-MIN(IF(Financials!BT$6>'Financing Inputs'!$T$19,0,Debt!$F$43+R46),R41) -> 0 | T43: =-MIN(IF(Financials!BV$6>'Financing Inputs'!$T$19,0,Debt!$F$43+T46),T41) -> 0 | V43: =-MIN(IF(Financials!BX$6>'Financing Inputs'!$T$19,0,Debt!$F$43+V46),V41) -> 0 | X43: =-MIN(IF(Financials!BZ$6>'Financing Inputs'!$T$19,0,Debt!$F$43+X46),X41) -> 0 | Z43: =-MIN(IF(Financials!CB$6>'Financing Inputs'!$T$19,0,Debt!$F$43+Z46),Z41) -> 0 | AB43: =-MIN(IF(Financials!CD$6>'Financing Inputs'!$T$19,0,Debt!$F$43+AB46),AB41) -> 0
B44: Balloon Payment | J44: =-IF(Financials!V$6='Financing Inputs'!$T$19,J41+J43,0) -> 0 | L44: =-IF(Financials!X$6='Financing Inputs'!$T$19,L41+L43,0) -> 0 | N44: =-IF(Financials!Z$6='Financing Inputs'!$T$19,N41+N43,0) -> 0 | P44: =-IF(Financials!AB$6='Financing Inputs'!$T$19,P41+P43,0) -> 0 | R44: =-IF(Financials!AD$6='Financing Inputs'!$T$19,R41+R43,0) -> 0 | T44: =-IF(Financials!AF$6='Financing Inputs'!$T$19,T41+T43,0) -> 0 | V44: =-IF(Financials!AH$6='Financing Inputs'!$T$19,V41+V43,0) -> 0 | X44: =-IF(Financials!AJ$6='Financing Inputs'!$T$19,X41+X43,0) -> 0 | Z44: =-IF(Financials!AL$6='Financing Inputs'!$T$19,Z41+Z43,0) -> 0 | AB44: =-IF(Financials!AN$6='Financing Inputs'!$T$19,AB41+AB43,0) -> 0
B45: Closing Balance | H45: =SUM(H41:H44) -> 0 | J45: =SUM(J41:J44) -> 0 | L45: =SUM(L41:L44) -> 0 | N45: =SUM(N41:N44) -> 0 | P45: =SUM(P41:P44) -> 0 | R45: =SUM(R41:R44) -> 0 | T45: =SUM(T41:T44) -> 0 | V45: =SUM(V41:V44) -> 0 | X45: =SUM(X41:X44) -> 0 | Z45: =SUM(Z41:Z44) -> 0 | AB45: =SUM(AB41:AB44) -> 0
B46: Interest Expense | F46: =IF(AND('Financing Inputs'!$T$31=3,'Financing Inputs'!$T$36=1),'Financing Inputs'!$L$27,0) -> 0.09 | J46: =-H45*Debt!$F$46 -> 0 | L46: =-J45*Debt!$F$46 -> 0 | N46: =-L45*Debt!$F$46 -> 0 | P46: =-N45*Debt!$F$46 -> 0 | R46: =-P45*Debt!$F$46 -> 0 | T46: =-R45*Debt!$F$46 -> 0 | V46: =-T45*Debt!$F$46 -> 0 | X46: =-V45*Debt!$F$46 -> 0 | Z46: =-X45*Debt!$F$46 -> 0 | AB46: =-Z45*Debt!$F$46 -> 0
B48: Refinance Debt - 2
B49: Opening Balance | J49: =H53 -> 0 | L49: =J53 -> 0 | N49: =L53 -> 0 | P49: =N53 -> 0 | R49: =P53 -> 0 | T49: =R53 -> 0 | V49: =T53 -> 0 | X49: =V53 -> 0 | Z49: =X53 -> 0 | AB49: =Z53 -> 0
B50: Debt Addition | J50: =-IF(AND('Financing Inputs'!$T$31=3,'Financing Inputs'!$T$36=2),J$28,0) -> 0 | L50: =-IF(AND('Financing Inputs'!$T$31=3,'Financing Inputs'!$T$36=2),L$28,0) -> 0 | N50: =-IF(AND('Financing Inputs'!$T$31=3,'Financing Inputs'!$T$36=2),N$28,0) -> 0 | P50: =-IF(AND('Financing Inputs'!$T$31=3,'Financing Inputs'!$T$36=2),P$28,0) -> 0 | R50: =-IF(AND('Financing Inputs'!$T$31=3,'Financing Inputs'!$T$36=2),R$28,0) -> 0 | T50: =-IF(AND('Financing Inputs'!$T$31=3,'Financing Inputs'!$T$36=2),T$28,0) -> 0 | V50: =-IF(AND('Financing Inputs'!$T$31=3,'Financing Inputs'!$T$36=2),V$28,0) -> 0 | X50: =-IF(AND('Financing Inputs'!$T$31=3,'Financing Inputs'!$T$36=2),X$28,0) -> 0 | Z50: =-IF(AND('Financing Inputs'!$T$31=3,'Financing Inputs'!$T$36=2),Z$28,0) -> 0 | AB50: =-IF(AND('Financing Inputs'!$T$31=3,'Financing Inputs'!$T$36=2),AB$28,0) -> 0
B51: Amortization | F51: =IF(AND('Financing Inputs'!$T$31=3,'Financing Inputs'!$T$36=2),SUM(Debt!J50:AB50)*'Financing Inputs'!$L$36,0) -> 0 | J51: =-MIN(IF(Financials!V$6>'Financing Inputs'!$J$36,IF(Financials!V$6>'Financing Inputs'!$T$19,0,Debt!$F$51),0)/IF(YEAR(Financials!V$6)=YEAR('Financing Inputs'!$J$36),IFERROR(12/(ROUND((YEARFRAC('Financing Inputs'!$J$36,Financials!V$6,1))*12,0)),1),1),J49) -> 0 | L51: =-MIN(IF(Financials!X$6>'Financing Inputs'!$J$36,IF(Financials!X$6>'Financing Inputs'!$T$19,0,Debt!$F$51),0)/IF(YEAR(Financials!X$6)=YEAR('Financing Inputs'!$J$36),IFERROR(12/(ROUND((YEARFRAC('Financing Inputs'!$J$36,Financials!X$6,1))*12,0)),1),1),L49) -> 0 | N51: =-MIN(IF(Financials!Z$6>'Financing Inputs'!$J$36,IF(Financials!Z$6>'Financing Inputs'!$T$19,0,Debt!$F$51),0)/IF(YEAR(Financials!Z$6)=YEAR('Financing Inputs'!$J$36),IFERROR(12/(ROUND((YEARFRAC('Financing Inputs'!$J$36,Financials!Z$6,1))*12,0)),1),1),N49) -> 0 | P51: =-MIN(IF(Financials!AB$6>'Financing Inputs'!$J$36,IF(Financials!AB$6>'Financing Inputs'!$T$19,0,Debt!$F$51),0)/IF(YEAR(Financials!AB$6)=YEAR('Financing Inputs'!$J$36),IFERROR(12/(ROUND((YEARFRAC('Financing Inputs'!$J$36,Financials!AB$6,1))*12,0)),1),1),P49) -> 0 | R51: =-MIN(IF(Financials!AD$6>'Financing Inputs'!$J$36,IF(Financials!AD$6>'Financing Inputs'!$T$19,0,Debt!$F$51),0)/IF(YEAR(Financials!AD$6)=YEAR('Financing Inputs'!$J$36),IFERROR(12/(ROUND((YEARFRAC('Financing Inputs'!$J$36,Financials!AD$6,1))*12,0)),1),1),R49) -> 0 | T51: =-MIN(IF(Financials!AF$6>'Financing Inputs'!$J$36,IF(Financials!AF$6>'Financing Inputs'!$T$19,0,Debt!$F$51),0)/IF(YEAR(Financials!AF$6)=YEAR('Financing Inputs'!$J$36),IFERROR(12/(ROUND((YEARFRAC('Financing Inputs'!$J$36,Financials!AF$6,1))*12,0)),1),1),T49) -> 0 | V51: =-MIN(IF(Financials!AH$6>'Financing Inputs'!$J$36,IF(Financials!AH$6>'Financing Inputs'!$T$19,0,Debt!$F$51),0)/IF(YEAR(Financials!AH$6)=YEAR('Financing Inputs'!$J$36),IFERROR(12/(ROUND((YEARFRAC('Financing Inputs'!$J$36,Financials!AH$6,1))*12,0)),1),1),V49) -> 0 | X51: =-MIN(IF(Financials!AJ$6>'Financing Inputs'!$J$36,IF(Financials!AJ$6>'Financing Inputs'!$T$19,0,Debt!$F$51),0)/IF(YEAR(Financials!AJ$6)=YEAR('Financing Inputs'!$J$36),IFERROR(12/(ROUND((YEARFRAC('Financing Inputs'!$J$36,Financials!AJ$6,1))*12,0)),1),1),X49) -> 0 | Z51: =-MIN(IF(Financials!AL$6>'Financing Inputs'!$J$36,IF(Financials!AL$6>'Financing Inputs'!$T$19,0,Debt!$F$51),0)/IF(YEAR(Financials!AL$6)=YEAR('Financing Inputs'!$J$36),IFERROR(12/(ROUND((YEARFRAC('Financing Inputs'!$J$36,Financials!AL$6,1))*12,0)),1),1),Z49) -> 0 | AB51: =-MIN(IF(Financials!AN$6>'Financing Inputs'!$J$36,IF(Financials!AN$6>'Financing Inputs'!$T$19,0,Debt!$F$51),0)/IF(YEAR(Financials!AN$6)=YEAR('Financing Inputs'!$J$36),IFERROR(12/(ROUND((YEARFRAC('Financing Inputs'!$J$36,Financials!AN$6,1))*12,0)),1),1),AB49) -> 0
B52: Balloon Payment | J52: =-IF(Financials!V$6='Financing Inputs'!$T$19,J49+J51,0) -> 0 | L52: =-IF(Financials!X$6='Financing Inputs'!$T$19,L49+L51,0) -> 0 | N52: =-IF(Financials!Z$6='Financing Inputs'!$T$19,N49+N51,0) -> 0 | P52: =-IF(Financials!AB$6='Financing Inputs'!$T$19,P49+P51,0) -> 0 | R52: =-IF(Financials!AD$6='Financing Inputs'!$T$19,R49+R51,0) -> 0 | T52: =-IF(Financials!AF$6='Financing Inputs'!$T$19,T49+T51,0) -> 0 | V52: =-IF(Financials!AH$6='Financing Inputs'!$T$19,V49+V51,0) -> 0 | X52: =-IF(Financials!AJ$6='Financing Inputs'!$T$19,X49+X51,0) -> 0 | Z52: =-IF(Financials!AL$6='Financing Inputs'!$T$19,Z49+Z51,0) -> 0 | AB52: =-IF(Financials!AN$6='Financing Inputs'!$T$19,AB49+AB51,0) -> 0
B53: Closing Balance | H53: =SUM(H49:H52) -> 0 | J53: =SUM(J49:J52) -> 0 | L53: =SUM(L49:L52) -> 0 | N53: =SUM(N49:N52) -> 0 | P53: =SUM(P49:P52) -> 0 | R53: =SUM(R49:R52) -> 0 | T53: =SUM(T49:T52) -> 0 | V53: =SUM(V49:V52) -> 0 | X53: =SUM(X49:X52) -> 0 | Z53: =SUM(Z49:Z52) -> 0 | AB53: =SUM(AB49:AB52) -> 0
B54: Interest Expense | J54: =-H53*('Financing Inputs'!$L$33)-IF(Financials!V$6>'Financing Inputs'!$J$34,'Financing Inputs'!$L$34*H53,0)/IF(YEAR(Financials!V$6)=YEAR('Financing Inputs'!$J$34),IFERROR(12/(ROUND((YEARFRAC('Financing Inputs'!$J$34,Financials!V$6,1))*12,0)),1),1)-IF(Financials!V$6>'Financing Inputs'!$J$35,'Financing Inputs'!$L$35*H53,0)/IF(YEAR(Financials!V$6)=YEAR('Financing Inputs'!$J$35),IFERROR(12/(ROUND((YEARFRAC('Financing Inputs'!$J$35,Financials!V$6,1))*12,0)),1),1) -> 0 | L54: =-J53*('Financing Inputs'!$L$33)-IF(Financials!X$6>'Financing Inputs'!$J$34,'Financing Inputs'!$L$34*J53,0)/IF(YEAR(Financials!X$6)=YEAR('Financing Inputs'!$J$34),IFERROR(12/(ROUND((YEARFRAC('Financing Inputs'!$J$34,Financials!X$6,1))*12,0)),1),1)-IF(Financials!X$6>'Financing Inputs'!$J$35,'Financing Inputs'!$L$35*J53,0)/IF(YEAR(Financials!X$6)=YEAR('Financing Inputs'!$J$35),IFERROR(12/(ROUND((YEARFRAC('Financing Inputs'!$J$35,Financials!X$6,1))*12,0)),1),1) -> 0 | N54: =-L53*('Financing Inputs'!$L$33)-IF(Financials!Z$6>'Financing Inputs'!$J$34,'Financing Inputs'!$L$34*L53,0)/IF(YEAR(Financials!Z$6)=YEAR('Financing Inputs'!$J$34),IFERROR(12/(ROUND((YEARFRAC('Financing Inputs'!$J$34,Financials!Z$6,1))*12,0)),1),1)-IF(Financials!Z$6>'Financing Inputs'!$J$35,'Financing Inputs'!$L$35*L53,0)/IF(YEAR(Financials!Z$6)=YEAR('Financing Inputs'!$J$35),IFERROR(12/(ROUND((YEARFRAC('Financing Inputs'!$J$35,Financials!Z$6,1))*12,0)),1),1) -> 0 | P54: =-N53*('Financing Inputs'!$L$33)-IF(Financials!AB$6>'Financing Inputs'!$J$34,'Financing Inputs'!$L$34*N53,0)/IF(YEAR(Financials!AB$6)=YEAR('Financing Inputs'!$J$34),IFERROR(12/(ROUND((YEARFRAC('Financing Inputs'!$J$34,Financials!AB$6,1))*12,0)),1),1)-IF(Financials!AB$6>'Financing Inputs'!$J$35,'Financing Inputs'!$L$35*N53,0)/IF(YEAR(Financials!AB$6)=YEAR('Financing Inputs'!$J$35),IFERROR(12/(ROUND((YEARFRAC('Financing Inputs'!$J$35,Financials!AB$6,1))*12,0)),1),1) -> 0 | R54: =-P53*('Financing Inputs'!$L$33)-IF(Financials!AD$6>'Financing Inputs'!$J$34,'Financing Inputs'!$L$34*P53,0)/IF(YEAR(Financials!AD$6)=YEAR('Financing Inputs'!$J$34),IFERROR(12/(ROUND((YEARFRAC('Financing Inputs'!$J$34,Financials!AD$6,1))*12,0)),1),1)-IF(Financials!AD$6>'Financing Inputs'!$J$35,'Financing Inputs'!$L$35*P53,0)/IF(YEAR(Financials!AD$6)=YEAR('Financing Inputs'!$J$35),IFERROR(12/(ROUND((YEARFRAC('Financing Inputs'!$J$35,Financials!AD$6,1))*12,0)),1),1) -> 0 | T54: =-R53*('Financing Inputs'!$L$33)-IF(Financials!AF$6>'Financing Inputs'!$J$34,'Financing Inputs'!$L$34*R53,0)/IF(YEAR(Financials!AF$6)=YEAR('Financing Inputs'!$J$34),IFERROR(12/(ROUND((YEARFRAC('Financing Inputs'!$J$34,Financials!AF$6,1))*12,0)),1),1)-IF(Financials!AF$6>'Financing Inputs'!$J$35,'Financing Inputs'!$L$35*R53,0)/IF(YEAR(Financials!AF$6)=YEAR('Financing Inputs'!$J$35),IFERROR(12/(ROUND((YEARFRAC('Financing Inputs'!$J$35,Financials!AF$6,1))*12,0)),1),1) -> 0 | V54: =-T53*('Financing Inputs'!$L$33)-IF(Financials!AH$6>'Financing Inputs'!$J$34,'Financing Inputs'!$L$34*T53,0)/IF(YEAR(Financials!AH$6)=YEAR('Financing Inputs'!$J$34),IFERROR(12/(ROUND((YEARFRAC('Financing Inputs'!$J$34,Financials!AH$6,1))*12,0)),1),1)-IF(Financials!AH$6>'Financing Inputs'!$J$35,'Financing Inputs'!$L$35*T53,0)/IF(YEAR(Financials!AH$6)=YEAR('Financing Inputs'!$J$35),IFERROR(12/(ROUND((YEARFRAC('Financing Inputs'!$J$35,Financials!AH$6,1))*12,0)),1),1) -> 0 | X54: =-V53*('Financing Inputs'!$L$33)-IF(Financials!AJ$6>'Financing Inputs'!$J$34,'Financing Inputs'!$L$34*V53,0)/IF(YEAR(Financials!AJ$6)=YEAR('Financing Inputs'!$J$34),IFERROR(12/(ROUND((YEARFRAC('Financing Inputs'!$J$34,Financials!AJ$6,1))*12,0)),1),1)-IF(Financials!AJ$6>'Financing Inputs'!$J$35,'Financing Inputs'!$L$35*V53,0)/IF(YEAR(Financials!AJ$6)=YEAR('Financing Inputs'!$J$35),IFERROR(12/(ROUND((YEARFRAC('Financing Inputs'!$J$35,Financials!AJ$6,1))*12,0)),1),1) -> 0 | Z54: =-X53*('Financing Inputs'!$L$33)-IF(Financials!AL$6>'Financing Inputs'!$J$34,'Financing Inputs'!$L$34*X53,0)/IF(YEAR(Financials!AL$6)=YEAR('Financing Inputs'!$J$34),IFERROR(12/(ROUND((YEARFRAC('Financing Inputs'!$J$34,Financials!AL$6,1))*12,0)),1),1)-IF(Financials!AL$6>'Financing Inputs'!$J$35,'Financing Inputs'!$L$35*X53,0)/IF(YEAR(Financials!AL$6)=YEAR('Financing Inputs'!$J$35),IFERROR(12/(ROUND((YEARFRAC('Financing Inputs'!$J$35,Financials!AL$6,1))*12,0)),1),1) -> 0 | AB54: =-Z53*('Financing Inputs'!$L$33)-IF(Financials!AN$6>'Financing Inputs'!$J$34,'Financing Inputs'!$L$34*Z53,0)/IF(YEAR(Financials!AN$6)=YEAR('Financing Inputs'!$J$34),IFERROR(12/(ROUND((YEARFRAC('Financing Inputs'!$J$34,Financials!AN$6,1))*12,0)),1),1)-IF(Financials!AN$6>'Financing Inputs'!$J$35,'Financing Inputs'!$L$35*Z53,0)/IF(YEAR(Financials!AN$6)=YEAR('Financing Inputs'!$J$35),IFERROR(12/(ROUND((YEARFRAC('Financing Inputs'!$J$35,Financials!AN$6,1))*12,0)),1),1) -> 0
