Workbook

Sheet Inputs
A2: LP | B2: Equity Split (A and B) | G2: Project Close Date
A3: GP (ABC) | B3: Equity - A | E3: 0.8 | G3: Close Date | J3: 46387
B4: Equity - B (ABC) | E4: =1-E3 -> 0.2
B6: Profit Waterfall
B8: 1. IRR | E8: 1
B9: 2. Yield
B11: 1. IRR Waterfall | G11: 2. Yield Waterfall
A12: LP Preferred Return (IRR) | F12: LP Preferred Return (Cash Yield)
B13: Equity A Preferred Return (IRR) | E13: 0.05 | G13: Equity A Preferred Return (Cash Yield) | J13: 0.1
A15: LP | B15: Hurdle 1 | F15: LP | G15: Tier 1
A16: GP | B16: Equity - A | E16: 0.8 | F16: GP | G16: Equity - A | J16: 0.7
A17: LP Preferred Return (IRR) | B17: Equity - B | E17: =1-E16 -> 0.2 | G17: Equity - B | J17: =1-J16 -> 0.3
B18: Equity A Preferred Return (IRR) | E18: 0.05
A20: LP | B20: Hurdle 1
A21: GP | B21: Equity - A | E21: 0.7
B22: Equity - B | E22: =1-E21 -> 0.3

Sheet Financials
B2: Month | D2: =EOMONTH(E2,-1) -> 46356 | E2: =Inputs!J3 -> 46387 | F2: =EOMONTH(E2,1) -> 46418 | G2: =EOMONTH(F2,1) -> 46446 | H2: =EOMONTH(G2,1) -> 46477 | I2: =EOMONTH(H2,1) -> 46507 | J2: =EOMONTH(I2,1) -> 46538 | K2: =EOMONTH(J2,1) -> 46568 | L2: =EOMONTH(K2,1) -> 46599 | M2: =EOMONTH(L2,1) -> 46630 | ... KS2: =EOMONTH(KR2,1) -> 55518
B4: Equity Invested | E4: -204000 | F4: 0 | G4: 0 | H4: 0 | I4: 0 | J4: 0 | K4: 0 | L4: 0 | M4: 0 | N4: 0 | O4: 0 | P4: 0 | Q4: 0 | R4: 0 | S4: 0 | T4: 0 | U4: 0 | V4: 0 | W4: 0 | X4: 0 | Y4: 0 | Z4: 0 | AA4: 0 | AB4: 0 | AC4: 0 | AD4: 0 | AE4: 0 | AF4: 0 | AG4: 0 | AH4: 0 | AI4: 0 | AJ4: 0 | AK4: 0 | AL4: 0 | AM4: 0 | AN4: 0 | AO4: 0 | AP4: 0 | AQ4: 0 | AR4: 0 | AS4: 0 | AT4: 0 | AU4: 0 | AV4: 0 | AW4: 0 | AX4: 0 | AY4: 0 | AZ4: 0 | BA4: 0 | BB4: 0 | BC4: 0 | BD4: 0 | BE4: 0 | BF4: 0 | BG4: 0 | BH4: 0 | BI4: 0 | BJ4: 0 | BK4: 0 | BL4: 0 | BM4: 0 | BN4: 0 | BO4: 0 | BP4: 0 | BQ4: 0 | BR4: 0 | BS4: 0 | BT4: 0 | BU4: 0 | BV4: 0 | BW4: 0 | BX4: 0 | BY4: 0 | BZ4: 0 | CA4: 0 | CB4: 0 | CC4: 0 | CD4: 0 | CE4: 0 | CF4: 0 | CG4: 0 | CH4: 0 | CI4: 0 | CJ4: 0 | CK4: 0 | CL4: 0 | CM4: 0 | CN4: 0 | CO4: 0 | CP4: 0 | CQ4: 0 | CR4: 0 | CS4: 0 | CT4: 0 | CU4: 0 | CV4: 0 | CW4: 0 | CX4: 0 | CY4: 0 | CZ4: 0 | DA4: 0 | DB4: 0 | DC4: 0 | DD4: 0 | DE4: 0 | DF4: 0 | DG4: 0 | DH4: 0 | DI4: 0 | DJ4: 0 | DK4: 0 | DL4: 0 | DM4: 0 | DN4: 0 | DO4: 0 | DP4: 0 | DQ4: 0 | DR4: 0 | DS4: 0 | DT4: 0 | DU4: 0 | DV4: 0 | DW4: 0 | DX4: 0 | DY4: 0 | DZ4: 0 | EA4: 0 | EB4: 0 | EC4: 0 | ED4: 0 | EE4: 0 | EF4: 0 | EG4: 0 | EH4: 0 | EI4: 0 | EJ4: 0 | EK4: 0 | EL4: 0 | EM4: 0 | EN4: 0 | EO4: 0 | EP4: 0 | EQ4: 0 | ER4: 0 | ES4: 0 | ET4: 0 | EU4: 0 | EV4: 0 | EW4: 0 | EX4: 0 | EY4: 0 | EZ4: 0 | FA4: 0 | FB4: 0 | FC4: 0 | FD4: 0 | FE4: 0 | FF4: 0 | FG4: 0 | FH4: 0 | FI4: 0 | FJ4: 0 | FK4: 0 | FL4: 0 | FM4: 0 | FN4: 0 | FO4: 0 | FP4: 0 | FQ4: 0 | FR4: 0 | FS4: 0 | FT4: 0 | FU4: 0 | FV4: 0 | FW4: 0 | FX4: 0 | FY4: 0 | FZ4: 0 | GA4: 0 | GB4: 0 | GC4: 0 | GD4: 0 | GE4: 0 | GF4: 0 | GG4: 0 | GH4: 0 | GI4: 0 | GJ4: 0 | GK4: 0 | GL4: 0 | GM4: 0 | GN4: 0 | GO4: 0 | GP4: 0 | GQ4: 0 | GR4: 0 | GS4: 0 | GT4: 0 | GU4: 0 | GV4: 0 | GW4: 0 | GX4: 0 | GY4: 0 | GZ4: 0 | HA4: 0 | HB4: 0 | HC4: 0 | HD4: 0 | HE4: 0 | HF4: 0 | HG4: 0 | HH4: 0 | HI4: 0 | HJ4: 0 | HK4: 0 | HL4: 0 | HM4: 0 | HN4: 0 | HO4: 0 | HP4: 0 | HQ4: 0 | HR4: 0 | HS4: 0 | HT4: 0 | HU4: 0 | HV4: 0 | HW4: 0 | HX4: 0 | HY4: 0 | HZ4: 0 | IA4: 0 | IB4: 0 | IC4: 0 | ID4: 0 | IE4: 0 | IF4: 0 | IG4: 0 | IH4: 0 | II4: 0 | IJ4: 0 | IK4: 0 | IL4: 0 | IM4: 0 | IN4: 0 | IO4: 0 | IP4: 0 | IQ4: 0 | IR4: 0 | IS4: 0 | IT4: 0 | IU4: 0 | IV4: 0 | IW4: 0 | IX4: 0 | IY4: 0 | IZ4: 0 | JA4: 0 | JB4: 0 | JC4: 0 | JD4: 0 | JE4: 0 | JF4: 0 | JG4: 0 | JH4: 0 | JI4: 0 | JJ4: 0 | JK4: 0 | JL4: 0 | JM4: 0 | JN4: 0 | JO4: 0 | JP4: 0 | JQ4: 0 | JR4: 0 | JS4: 0 | JT4: 0 | JU4: 0 | JV4: 0 | JW4: 0 | JX4: 0 | JY4: 0 | JZ4: 0 | KA4: 0 | KB4: 0 | KC4: 0 | KD4: 0 | KE4: 0 | KF4: 0 | KG4: 0 | KH4: 0 | KI4: 0 | KJ4: 0 | KK4: 0 | KL4: 0 | KM4: 0 | KN4: 0 | KO4: 0 | KP4: 0 | KQ4: 0 | KR4: 0
B5: Equity Returned | E5: 0 | F5: 1650 | G5: 1650 | H5: 1650 | I5: 1650 | J5: 1650 | K5: 1650 | L5: 1650 | M5: 1650 | N5: 1650 | O5: 1650 | P5: 2165 | Q5: 2321 | R5: 2321 | S5: 2321 | T5: 2321 | U5: 2321 | V5: 2321 | W5: 2321 | X5: 2321 | Y5: 2321 | Z5: 2321 | AA5: 2321 | AB5: 2321 | AC5: 2480.12 | AD5: 2480.12 | AE5: 2480.12 | AF5: 2480.12 | AG5: 2480.12 | AH5: 2480.12 | AI5: 2480.12 | AJ5: 2480.12 | AK5: 2480.12 | AL5: 2480.12 | AM5: 2480.12 | AN5: 2480.12 | AO5: 258.6878 | AP5: 1308.6228 | AQ5: 861.13809 | AR5: 494.80501 | AS5: 1472.1238 | AT5: 147.37223 | AU5: 1275.2013 | AV5: 1024.5622 | AW5: 1488.3227 | AX5: 1699.7643 | AY5: 2642.3756 | AZ5: 2642.3756 | BA5: 2807.779 | BB5: 2807.779 | BC5: 2807.779 | BD5: 2807.779 | BE5: 2807.779 | BF5: 2807.779 | BG5: 2807.779 | BH5: 2807.779 | BI5: 2807.779 | BJ5: 2807.779 | BK5: 2807.779 | BL5: 2807.779 | BM5: 2976.3385 | BN5: 2976.3385 | BO5: 2976.3385 | BP5: 2976.3385 | BQ5: 2976.3385 | BR5: 2976.3385 | BS5: 2976.3385 | BT5: 2976.3385 | BU5: 2976.3385 | BV5: 2976.3385 | BW5: 2976.3385 | BX5: 2976.3385 | BY5: 3148.0587 | BZ5: 3148.0587 | CA5: 3148.0587 | CB5: 3148.0587 | CC5: 3148.0587 | CD5: 3148.0587 | CE5: 3148.0587 | CF5: 3148.0587 | CG5: 3148.0587 | CH5: 3148.0587 | CI5: 3148.0587 | CJ5: 3148.0587 | CK5: 3322.9395 | CL5: 3322.9395 | CM5: 3322.9395 | CN5: 3322.9395 | CO5: 3322.9395 | CP5: 3322.9395 | CQ5: 3322.9395 | CR5: 3322.9395 | CS5: 3322.9395 | CT5: 3322.9395 | CU5: 3322.9395 | CV5: 3322.9395 | CW5: 687.98807 | CX5: 237.94278 | CY5: 797.55877 | CZ5: 558.2947 | DA5: 698.75496 | DB5: 639.42413 | DC5: 645.12025 | DD5: 126.9446 | DE5: 3500.9761 | DF5: 3500.9761 | DG5: 3500.9761 | DH5: 3500.9761 | DI5: 3682.1588 | DJ5: 3682.1588 | DK5: 3682.1588 | DL5: 3682.1588 | DM5: 3682.1588 | DN5: 3682.1588 | DO5: 3682.1588 | DP5: 3682.1588 | DQ5: 3682.1588 | DR5: 3682.1588 | DS5: 3682.1588 | DT5: 3682.1588 | DU5: 3866.4721 | DV5: 3866.4721 | DW5: 3866.4721 | DX5: 3866.4721 | DY5: 3866.4721 | DZ5: 3866.4721 | EA5: 3866.4721 | EB5: 3866.4721 | EC5: 3866.4721 | ED5: 3866.4721 | EE5: 3866.4721 | EF5: 3866.4721 | EG5: 4053.8948 | EH5: 4053.8948 | EI5: 4053.8948 | EJ5: 4053.8948 | EK5: 4053.8948 | EL5: 4053.8948 | EM5: 4053.8948 | EN5: 4053.8948 | EO5: 4053.8948 | EP5: 4053.8948 | EQ5: 4053.8948 | ER5: 4053.8948 | ES5: 4244.399 | ET5: 4244.399 | EU5: 4244.399 | EV5: 4244.399 | EW5: 4244.399 | EX5: 4244.399 | EY5: 4244.399 | EZ5: 4244.399 | FA5: 4244.399 | FB5: 4244.399 | FC5: 4244.399 | FD5: 4244.399 | FE5: 1156.4751 | FF5: 4238.2327 | FG5: 2315.6903 | FH5: 2897.7458 | FI5: 4485.1622 | FJ5: 988.78968 | FK5: 1625.7974 | FL5: 4148.2854 | FM5: 4437.9503 | FN5: 4437.9503 | FO5: 4437.9503 | FP5: 4437.9503 | FQ5: 4634.5066 | FR5: 4634.5066 | FS5: 4634.5066 | FT5: 4634.5066 | FU5: 4634.5066 | FV5: 4634.5066 | FW5: 4634.5066 | FX5: 4634.5066 | FY5: 4634.5066 | FZ5: 4634.5066 | GA5: 4634.5066 | GB5: 4634.5066 | GC5: 4834.0179 | GD5: 4834.0179 | GE5: 4834.0179 | GF5: 4834.0179 | GG5: 4834.0179 | GH5: 4834.0179 | GI5: 4834.0179 | GJ5: 4834.0179 | GK5: 4834.0179 | GL5: 4834.0179 | GM5: 4834.0179 | GN5: 4834.0179 | GO5: 5036.4259 | GP5: 5036.4259 | GQ5: 5036.4259 | GR5: 5036.4259 | GS5: 5036.4259 | GT5: 5036.4259 | GU5: 5036.4259 | GV5: 5036.4259 | GW5: 5036.4259 | GX5: 5036.4259 | GY5: 5036.4259 | GZ5: 5036.4259 | HA5: 5241.663 | HB5: 5241.663 | HC5: 5241.663 | HD5: 5241.663 | HE5: 5241.663 | HF5: 5241.663 | HG5: 5241.663 | HH5: 5241.663 | HI5: 5241.663 | HJ5: 5241.663 | HK5: 5241.663 | HL5: 5241.663 | HM5: 1662.3259 | HN5: 1626.0966 | HO5: 2239.8033 | HP5: 1959.1741 | HQ5: 1812.3502 | HR5: 1442.2683 | HS5: 2978.9633 | HT5: 5449.6519 | HU5: 5449.6519 | HV5: 5449.6519 | HW5: 5449.6519 | HX5: 5449.6519 | HY5: 5660.3049 | HZ5: 5660.3049 | IA5: 5660.3049 | IB5: 5660.3049 | IC5: 5660.3049 | ID5: 5660.3049 | IE5: 5660.3049 | IF5: 5660.3049 | IG5: 5660.3049 | IH5: 5660.3049 | II5: 5660.3049 | IJ5: 5660.3049 | IK5: 5873.5232 | IL5: 5873.5232 | IM5: 5873.5232 | IN5: 5873.5232 | IO5: 5873.5232 | IP5: 5873.5232 | IQ5: 5873.5232 | IR5: 5873.5232 | IS5: 5873.5232 | IT5: 5873.5232 | IU5: 5873.5232 | IV5: 5873.5232 | IW5: 6089.196 | IX5: 6089.196 | IY5: 6089.196 | IZ5: 6089.196 | JA5: 6089.196 | JB5: 6089.196 | JC5: 6089.196 | JD5: 6089.196 | JE5: 6089.196 | JF5: 6089.196 | JG5: 6089.196 | JH5: 6089.196 | JI5: 6307.1999 | JJ5: 6307.1999 | JK5: 6307.1999 | JL5: 6307.1999 | JM5: 6307.1999 | JN5: 6307.1999 | JO5: 6307.1999 | JP5: 6307.1999 | JQ5: 6307.1999 | JR5: 6307.1999 | JS5: 6307.1999 | JT5: 6307.1999 | JU5: 2201.1989 | JV5: 6527.3977 | JW5: 6527.3977 | JX5: 6527.3977 | JY5: 6527.3977 | JZ5: 6527.3977 | KA5: 6527.3977 | KB5: 6527.3977 | KC5: 6527.3977 | KD5: 6527.3977 | KE5: 6527.3977 | KF5: 6527.3977 | KG5: 6749.6381 | KH5: 6749.6381 | KI5: 6749.6381 | KJ5: 6749.6381 | KK5: 6749.6381 | KL5: 6749.6381 | KM5: 6749.6381 | KN5: 6749.6381 | KO5: 6749.6381 | KP5: 6749.6381 | KQ5: 6749.6381 | KR5: 6749.6381 | KS5: 6973.7541
B9: Profit Waterfall
B10: =Inputs!B11 -> 1. IRR Waterfall
B12: Pref Hurdle :
B13: Opening Balance | E13: =D17 -> 0 | F13: =E17 -> 163200 | G13: =F17 -> 162230 | H13: =G17 -> 161255.96 | I13: =H17 -> 160277.86 | J13: =I17 -> 159295.68 | K13: =J17 -> 158309.41 | L13: =K17 -> 157319.04 | ... KS13: =KR17 -> 0
B14: Addition to Equity | E14: =IF(Inputs!$E$8=1,-E4,0)*Inputs!$E$3 -> 163200 | F14: =IF(Inputs!$E$8=1,-F4,0)*Inputs!$E$3 -> 0 | G14: =IF(Inputs!$E$8=1,-G4,0)*Inputs!$E$3 -> 0 | H14: =IF(Inputs!$E$8=1,-H4,0)*Inputs!$E$3 -> 0 | I14: =IF(Inputs!$E$8=1,-I4,0)*Inputs!$E$3 -> 0 | J14: =IF(Inputs!$E$8=1,-J4,0)*Inputs!$E$3 -> 0 | K14: =IF(Inputs!$E$8=1,-K4,0)*Inputs!$E$3 -> 0 | L14: =IF(Inputs!$E$8=1,-L4,0)*Inputs!$E$3 -> 0 | ... KS14: =IF(Inputs!$E$8=1,-KS4,0)*Inputs!$E$3 -> 0
B15: Preferred Return | C15: =IF(Inputs!$E$8=1,Inputs!E13,0) -> 0.05 | E15: 0 | F15: =ROUND(IF(((F14+F13)*$C15/12)<0,0,((F14+F13)*$C15/12)),5) -> 680 | G15: =ROUND(IF(((G14+G13)*$C15/12)<0,0,((G14+G13)*$C15/12)),5) -> 675.95833 | H15: =ROUND(IF(((H14+H13)*$C15/12)<0,0,((H14+H13)*$C15/12)),5) -> 671.89983 | I15: =ROUND(IF(((I14+I13)*$C15/12)<0,0,((I14+I13)*$C15/12)),5) -> 667.82441 | J15: =ROUND(IF(((J14+J13)*$C15/12)<0,0,((J14+J13)*$C15/12)),5) -> 663.73201 | K15: =ROUND(IF(((K14+K13)*$C15/12)<0,0,((K14+K13)*$C15/12)),5) -> 659.62256 | L15: =ROUND(IF(((L14+L13)*$C15/12)<0,0,((L14+L13)*$C15/12)),5) -> 655.49599 | M15: =ROUND(IF(((M14+M13)*$C15/12)<0,0,((M14+M13)*$C15/12)),5) -> 651.35222 | ... KS15: =ROUND(IF(((KS14+KS13)*$C15/12)<0,0,((KS14+KS13)*$C15/12)),5) -> 0
B16: Preferred Return Paid | E16: =-IF($C15=0%,0,MIN(E13+E14+E15,E5)) -> 0 | F16: =-IF($C15=0%,0,MIN(F13+F14+F15,F5)) -> -1650 | G16: =-IF($C15=0%,0,MIN(G13+G14+G15,G5)) -> -1650 | H16: =-IF($C15=0%,0,MIN(H13+H14+H15,H5)) -> -1650 | I16: =-IF($C15=0%,0,MIN(I13+I14+I15,I5)) -> -1650 | J16: =-IF($C15=0%,0,MIN(J13+J14+J15,J5)) -> -1650 | K16: =-IF($C15=0%,0,MIN(K13+K14+K15,K5)) -> -1650 | L16: =-IF($C15=0%,0,MIN(L13+L14+L15,L5)) -> -1650 | ... KS16: =-IF($C15=0%,0,MIN(KS13+KS14+KS15,KS5)) -> 0
B17: Closing Balance | E17: =SUM(E13:E16) -> 163200 | F17: =SUM(F13:F16) -> 162230 | G17: =SUM(G13:G16) -> 161255.96 | H17: =SUM(H13:H16) -> 160277.86 | I17: =SUM(I13:I16) -> 159295.68 | J17: =SUM(J13:J16) -> 158309.41 | K17: =SUM(K13:K16) -> 157319.04 | L17: =SUM(L13:L16) -> 156324.53 | ... KS17: =SUM(KS13:KS16) -> 0
B19: IRR Parity | C19: =IRR(E19:KS19)*12 -> 0.05 | E19: =-E14-E16 -> -163200 | F19: =-F14-F16 -> 1650 | G19: =-G14-G16 -> 1650 | H19: =-H14-H16 -> 1650 | I19: =-I14-I16 -> 1650 | J19: =-J14-J16 -> 1650 | K19: =-K14-K16 -> 1650 | L19: =-L14-L16 -> 1650 | ... KS19: =-KS14-KS16 -> 0
B21: Balance after Preferred Return | E21: =IF(Inputs!$E$8=1,E5+E16+IF(E4>0,E4,0),0) -> 0 | F21: =IF(Inputs!$E$8=1,F5+F16+IF(F4>0,F4,0),0) -> 0 | G21: =IF(Inputs!$E$8=1,G5+G16+IF(G4>0,G4,0),0) -> 0 | H21: =IF(Inputs!$E$8=1,H5+H16+IF(H4>0,H4,0),0) -> 0 | I21: =IF(Inputs!$E$8=1,I5+I16+IF(I4>0,I4,0),0) -> 0 | J21: =IF(Inputs!$E$8=1,J5+J16+IF(J4>0,J4,0),0) -> 0 | K21: =IF(Inputs!$E$8=1,K5+K16+IF(K4>0,K4,0),0) -> 0 | L21: =IF(Inputs!$E$8=1,L5+L16+IF(L4>0,L4,0),0) -> 0 | ... KS21: =IF(Inputs!$E$8=1,KS5+KS16+IF(KS4>0,KS4,0),0) -> 6973.7541
B23: Pref Hurdle :
B24: Opening Balance | E24: =D28 -> 0 | F24: =E28 -> 163880 | G24: =F28 -> 162912.83 | H24: =G28 -> 161941.64 | I24: =H28 -> 160966.39 | J24: =I28 -> 159987.09 | K24: =J28 -> 159003.7 | L24: =K28 -> 158016.22 | ... KS24: =KR28 -> 0
B25: Addition to Equity | E25: =IF(Inputs!$E$8=1,-E4,0)*Inputs!$E$3 -> 163200 | F25: =IF(Inputs!$E$8=1,-F4,0)*Inputs!$E$3 -> 0 | G25: =IF(Inputs!$E$8=1,-G4,0)*Inputs!$E$3 -> 0 | H25: =IF(Inputs!$E$8=1,-H4,0)*Inputs!$E$3 -> 0 | I25: =IF(Inputs!$E$8=1,-I4,0)*Inputs!$E$3 -> 0 | J25: =IF(Inputs!$E$8=1,-J4,0)*Inputs!$E$3 -> 0 | K25: =IF(Inputs!$E$8=1,-K4,0)*Inputs!$E$3 -> 0 | L25: =IF(Inputs!$E$8=1,-L4,0)*Inputs!$E$3 -> 0 | ... KS25: =IF(Inputs!$E$8=1,-KS4,0)*Inputs!$E$3 -> 0
B26: Preferred Return | C26: =IF(Inputs!$E$8=1,Inputs!E18,0) -> 0.05 | E26: =IF(((E25+E24)*$C26/12)<0,0,((E25+E24)*$C26/12)) -> 680 | F26: =IF(((F25+F24)*$C26/12)<0,0,((F25+F24)*$C26/12)) -> 682.83333 | G26: =IF(((G25+G24)*$C26/12)<0,0,((G25+G24)*$C26/12)) -> 678.80347 | H26: =IF(((H25+H24)*$C26/12)<0,0,((H25+H24)*$C26/12)) -> 674.75682 | I26: =IF(((I25+I24)*$C26/12)<0,0,((I25+I24)*$C26/12)) -> 670.69331 | J26: =IF(((J25+J24)*$C26/12)<0,0,((J25+J24)*$C26/12)) -> 666.61286 | K26: =IF(((K25+K24)*$C26/12)<0,0,((K25+K24)*$C26/12)) -> 662.51542 | L26: =IF(((L25+L24)*$C26/12)<0,0,((L25+L24)*$C26/12)) -> 658.4009 | ... KS26: =IF(((KS25+KS24)*$C26/12)<0,0,((KS25+KS24)*$C26/12)) -> 0
B27: Preferred Return Paid | E27: =-IF($C26=0%,0,MIN(E24+E25+E26,E5)) -> 0 | F27: =-IF($C26=0%,0,MIN(F24+F25+F26,F5)) -> -1650 | G27: =-IF($C26=0%,0,MIN(G24+G25+G26,G5)) -> -1650 | H27: =-IF($C26=0%,0,MIN(H24+H25+H26,H5)) -> -1650 | I27: =-IF($C26=0%,0,MIN(I24+I25+I26,I5)) -> -1650 | J27: =-IF($C26=0%,0,MIN(J24+J25+J26,J5)) -> -1650 | K27: =-IF($C26=0%,0,MIN(K24+K25+K26,K5)) -> -1650 | L27: =-IF($C26=0%,0,MIN(L24+L25+L26,L5)) -> -1650 | ... KS27: =-IF($C26=0%,0,MIN(KS24+KS25+KS26,KS5)) -> 0
B28: Closing Balance | E28: =SUM(E24:E27) -> 163880 | F28: =SUM(F24:F27) -> 162912.83 | G28: =SUM(G24:G27) -> 161941.64 | H28: =SUM(H24:H27) -> 160966.39 | I28: =SUM(I24:I27) -> 159987.09 | J28: =SUM(J24:J27) -> 159003.7 | K28: =SUM(K24:K27) -> 158016.22 | L28: =SUM(L24:L27) -> 157024.62 | ... KS28: =SUM(KS24:KS27) -> 0
B30: LP Distribution | E30: =E16-E27 -> 0 | F30: =F16-F27 -> 0 | G30: =G16-G27 -> 0 | H30: =H16-H27 -> 0 | I30: =I16-I27 -> 0 | J30: =J16-J27 -> 0 | K30: =K16-K27 -> 0 | L30: =L16-L27 -> 0 | ... KS30: =KS16-KS27 -> 0
B32: IRR Parity | C32: =IRR(E32:KS32)*12 -> 0.051148063 | E32: =-E25-E27 -> -163200 | F32: =-F25-F27 -> 1650 | G32: =-G25-G27 -> 1650 | H32: =-H25-H27 -> 1650 | I32: =-I25-I27 -> 1650 | J32: =-J25-J27 -> 1650 | K32: =-K25-K27 -> 1650 | L32: =-L25-L27 -> 1650 | ... KS32: =-KS25-KS27 -> 0
B34: Tier 1:
B35: LP | C35: =IF(Inputs!$E$8=1,Inputs!E3,0) -> 0.8 | E35: =E30*$C$35 -> 0 | F35: =F30*$C$35 -> 0 | G35: =G30*$C$35 -> 0 | H35: =H30*$C$35 -> 0 | I35: =I30*$C$35 -> 0 | J35: =J30*$C$35 -> 0 | K35: =K30*$C$35 -> 0 | L35: =L30*$C$35 -> 0 | ... KS35: =KS30*$C$35 -> 0
B36: GP | C36: =IF(Inputs!$E$8=1,Inputs!E4,0) -> 0.2 | E36: =E30*$C$36 -> 0 | F36: =F30*$C$36 -> 0 | G36: =G30*$C$36 -> 0 | H36: =H30*$C$36 -> 0 | I36: =I30*$C$36 -> 0 | J36: =J30*$C$36 -> 0 | K36: =K30*$C$36 -> 0 | L36: =L30*$C$36 -> 0 | ... KS36: =KS30*$C$36 -> 0
B38: Balance after Tier 1 | E38: =+E21-E35-E36 -> 0 | F38: =+F21-F35-F36 -> 0 | G38: =+G21-G35-G36 -> 0 | H38: =+H21-H35-H36 -> 0 | I38: =+I21-I35-I36 -> 0 | J38: =+J21-J35-J36 -> 0 | K38: =+K21-K35-K36 -> 0 | L38: =+L21-L35-L36 -> 0 | ... KS38: =+KS21-KS35-KS36 -> 6973.7541
B40: Tier 2:
B41: LP | C41: =Inputs!E21 -> 0.7 | E41: =E38*$C$41 -> 0 | F41: =F38*$C$41 -> 0 | G41: =G38*$C$41 -> 0 | H41: =H38*$C$41 -> 0 | I41: =I38*$C$41 -> 0 | J41: =J38*$C$41 -> 0 | K41: =K38*$C$41 -> 0 | L41: =L38*$C$41 -> 0 | ... KS41: =KS38*$C$41 -> 4881.6279
B42: GP | C42: =Inputs!E22 -> 0.3 | E42: =E38*$C$42 -> 0 | F42: =F38*$C$42 -> 0 | G42: =G38*$C$42 -> 0 | H42: =H38*$C$42 -> 0 | I42: =I38*$C$42 -> 0 | J42: =J38*$C$42 -> 0 | K42: =K38*$C$42 -> 0 | L42: =L38*$C$42 -> 0 | ... KS42: =KS38*$C$42 -> 2092.1262
B45: Do Not delete | E45: 0 | F45: =IF(MONTH(F2)=MONTH(Inputs!$J$3),1,E45+1) -> 1 | G45: =IF(MONTH(G2)=MONTH(Inputs!$J$3),1,F45+1) -> 2 | H45: =IF(MONTH(H2)=MONTH(Inputs!$J$3),1,G45+1) -> 3 | I45: =IF(MONTH(I2)=MONTH(Inputs!$J$3),1,H45+1) -> 4 | J45: =IF(MONTH(J2)=MONTH(Inputs!$J$3),1,I45+1) -> 5 | K45: =IF(MONTH(K2)=MONTH(Inputs!$J$3),1,J45+1) -> 6 | L45: =IF(MONTH(L2)=MONTH(Inputs!$J$3),1,K45+1) -> 7 | M45: =IF(MONTH(M2)=MONTH(Inputs!$J$3),1,L45+1) -> 8 | ... KS45: =IF(MONTH(KS2)=MONTH(Inputs!$J$3),1,KR45+1) -> 1
B46: =Inputs!G11 -> 2. Yield Waterfall
B48: Pref Hurdle
B49: Opening Balance | E49: =D52 -> 0 | F49: =E52 -> 0 | G49: =F52 -> 0 | H49: =G52 -> 0 | I49: =H52 -> 0 | J49: =I52 -> 0 | K49: =J52 -> 0 | L49: =K52 -> 0 | ... KS49: =KR52 -> 0
B50: Add: Current Period Pref return | C50: =IF(Inputs!$E$8=2,Inputs!J13,0) -> 0 | E50: {=IF(E45=1,SUM(-$E$4:E4)*$C$50*Inputs!$E$3,0)} -> 0 | F50: {=IF(F45=1,SUM(-$E$4:F4)*$C$50*Inputs!$E$3,0)} -> 0 | G50: {=IF(G45=1,SUM(-$E$4:G4)*$C$50*Inputs!$E$3,0)} -> 0 | H50: {=IF(H45=1,SUM(-$E$4:H4)*$C$50*Inputs!$E$3,0)} -> 0 | I50: {=IF(I45=1,SUM(-$E$4:I4)*$C$50*Inputs!$E$3,0)} -> 0 | J50: {=IF(J45=1,SUM(-$E$4:J4)*$C$50*Inputs!$E$3,0)} -> 0 | K50: {=IF(K45=1,SUM(-$E$4:K4)*$C$50*Inputs!$E$3,0)} -> 0 | L50: {=IF(L45=1,SUM(-$E$4:L4)*$C$50*Inputs!$E$3,0)} -> 0 | ... KS50: {=IF(KS45=1,SUM(-$E$4:KS4)*$C$50*Inputs!$E$3,0)} -> 0
B51: Less: Pref Return Paid amount | E51: =-MIN(E49+E50,E5) -> 0 | F51: =-MIN(F49+F50,F5) -> 0 | G51: =-MIN(G49+G50,G5) -> 0 | H51: =-MIN(H49+H50,H5) -> 0 | I51: =-MIN(I49+I50,I5) -> 0 | J51: =-MIN(J49+J50,J5) -> 0 | K51: =-MIN(K49+K50,K5) -> 0 | L51: =-MIN(L49+L50,L5) -> 0 | ... KS51: =-MIN(KS49+KS50,KS5) -> 0
B52: Shortfall (if any) / Closing Amount | E52: =SUM(E49:E51) -> 0 | F52: =SUM(F49:F51) -> 0 | G52: =SUM(G49:G51) -> 0 | H52: =SUM(H49:H51) -> 0 | I52: =SUM(I49:I51) -> 0 | J52: =SUM(J49:J51) -> 0 | K52: =SUM(K49:K51) -> 0 | L52: =SUM(L49:L51) -> 0 | ... KS52: =SUM(KS49:KS51) -> 0
B54: Net Amount Available after Pref Return is Paid | E54: =IF(Inputs!$E$8=2,E5+E51,0) -> 0 | F54: =IF(Inputs!$E$8=2,F5+F51,0) -> 0 | G54: =IF(Inputs!$E$8=2,G5+G51,0) -> 0 | H54: =IF(Inputs!$E$8=2,H5+H51,0) -> 0 | I54: =IF(Inputs!$E$8=2,I5+I51,0) -> 0 | J54: =IF(Inputs!$E$8=2,J5+J51,0) -> 0 | K54: =IF(Inputs!$E$8=2,K5+K51,0) -> 0 | L54: =IF(Inputs!$E$8=2,L5+L51,0) -> 0 | ... KS54: =IF(Inputs!$E$8=2,KS5+KS51,0) -> 0
B56: Tier 1
B57: LP | C57: =IF(Inputs!$E$8=2,Inputs!J16,0) -> 0 | E57: =E54*$C$57 -> 0 | F57: =F54*$C$57 -> 0 | G57: =G54*$C$57 -> 0 | H57: =H54*$C$57 -> 0 | I57: =I54*$C$57 -> 0 | J57: =J54*$C$57 -> 0 | K57: =K54*$C$57 -> 0 | L57: =L54*$C$57 -> 0 | ... KS57: =KS54*$C$57 -> 0
B58: GP | C58: =IF(Inputs!$E$8=2,Inputs!J17,0) -> 0 | E58: =E54*$C$58 -> 0 | F58: =F54*$C$58 -> 0 | G58: =G54*$C$58 -> 0 | H58: =H54*$C$58 -> 0 | I58: =I54*$C$58 -> 0 | J58: =J54*$C$58 -> 0 | K58: =K54*$C$58 -> 0 | L58: =L54*$C$58 -> 0 | ... KS58: =KS54*$C$58 -> 0
B61: Total Return to LP
B62: Equity Invested | C62: =-SUMIF(F62:KS62,"<0")-E62 -> 163200 | E62: =E4*Inputs!$E$3 -> -163200 | F62: =F4*Inputs!$E$3 -> 0 | G62: =G4*Inputs!$E$3 -> 0 | H62: =H4*Inputs!$E$3 -> 0 | I62: =I4*Inputs!$E$3 -> 0 | J62: =J4*Inputs!$E$3 -> 0 | K62: =K4*Inputs!$E$3 -> 0 | L62: =L4*Inputs!$E$3 -> 0 | ... KS62: =KS4*Inputs!$E$3 -> 0
B63: Equity Returned | C63: =+SUM(E63:KS63)+SUMIF(E62:KS62,">0") -> 908779.78 | E63: =-E16+E35+E41-E51+E57 -> 0 | F63: =-F16+F35+F41-F51+F57 -> 1650 | G63: =-G16+G35+G41-G51+G57 -> 1650 | H63: =-H16+H35+H41-H51+H57 -> 1650 | I63: =-I16+I35+I41-I51+I57 -> 1650 | J63: =-J16+J35+J41-J51+J57 -> 1650 | K63: =-K16+K35+K41-K51+K57 -> 1650 | L63: =-L16+L35+L41-L51+L57 -> 1650 | ... KS63: =-KS16+KS35+KS41-KS51+KS57 -> 4881.6279
B64: Net cash | E64: =SUM(E62:E63) -> -163200 | F64: =SUM(F62:F63) -> 1650 | G64: =SUM(G62:G63) -> 1650 | H64: =SUM(H62:H63) -> 1650 | I64: =SUM(I62:I63) -> 1650 | J64: =SUM(J62:J63) -> 1650 | K64: =SUM(K62:K63) -> 1650 | L64: =SUM(L62:L63) -> 1650 | ... KS64: =SUM(KS62:KS63) -> 4881.6279
B65: XIRR | C65: =XIRR(E64:KS64,$E$2:$KS$2) -> 0.18577688
B67: Total Return to GP
B68: Equity Invested | C68: =-SUMIF(F68:KS68,"<0")-E68 -> 40800 | E68: =E4*Inputs!$E$4 -> -40800 | F68: =F4*Inputs!$E$4 -> 0 | G68: =G4*Inputs!$E$4 -> 0 | H68: =H4*Inputs!$E$4 -> 0 | I68: =I4*Inputs!$E$4 -> 0 | J68: =J4*Inputs!$E$4 -> 0 | K68: =K4*Inputs!$E$4 -> 0 | L68: =L4*Inputs!$E$4 -> 0 | ... KS68: =KS4*Inputs!$E$4 -> 0
B69: Equity Returned | C69: =+SUM(E69:KS69)+SUMIF(E68:KS68,">0") -> 305105.68 | E69: =E36+E58+E42 -> 0 | F69: =F36+F58+F42 -> 0 | G69: =G36+G58+G42 -> 0 | H69: =H36+H58+H42 -> 0 | I69: =I36+I58+I42 -> 0 | J69: =J36+J58+J42 -> 0 | K69: =K36+K58+K42 -> 0 | L69: =L36+L58+L42 -> 0 | ... KS69: =KS36+KS58+KS42 -> 2092.1262
B70: Net cash | E70: =SUM(E68:E69) -> -40800 | F70: =SUM(F68:F69) -> 0 | G70: =SUM(G68:G69) -> 0 | H70: =SUM(H68:H69) -> 0 | I70: =SUM(I68:I69) -> 0 | J70: =SUM(J68:J69) -> 0 | K70: =SUM(K68:K69) -> 0 | L70: =SUM(L68:L69) -> 0 | ... KS70: =SUM(KS68:KS69) -> 2092.1262
B71: XIRR | C71: =XIRR(E70:KS70,$E$2:$KS$2) -> 0.13769023
E72: =E62+E68-E4 -> 0 | F72: =F62+F68-F4 -> 0 | G72: =G62+G68-G4 -> 0 | H72: =H62+H68-H4 -> 0 | I72: =I62+I68-I4 -> 0 | J72: =J62+J68-J4 -> 0 | K72: =K62+K68-K4 -> 0 | L72: =L62+L68-L4 -> 0 | ... KS72: =KS62+KS68-KS4 -> 0
E73: =E63+E69-E5 -> 0 | F73: =F63+F69-F5 -> 0 | G73: =G63+G69-G5 -> 0 | H73: =H63+H69-H5 -> 0 | I73: =I63+I69-I5 -> 0 | J73: =J63+J69-J5 -> 0 | K73: =K63+K69-K5 -> 0 | L73: =L63+L69-L5 -> 0 | ... KS73: =KS63+KS69-KS5 -> 0
B106: Debt Calculations
B108: 1. X Debt
B109: Opening Balance | E109: =D113 -> 0 | F109: =E113 -> #REF! | G109: =F113 -> #REF! | H109: =G113 -> #REF! | I109: =H113 -> #REF! | J109: =I113 -> #REF! | K109: =J113 -> #REF! | L109: =K113 -> #REF! | ... KS109: =KR113 -> #REF!
B110: Debt Addition | E110: =IF(Inputs!#REF!=1,IF(E2=Inputs!#REF!,Inputs!#REF!,0),0) -> #REF! | F110: =IF(F2=Inputs!#REF!,Inputs!#REF!,0) -> #REF! | G110: =IF(G2=Inputs!#REF!,Inputs!#REF!,0) -> #REF! | H110: =IF(H2=Inputs!#REF!,Inputs!#REF!,0) -> #REF! | I110: =IF(I2=Inputs!#REF!,Inputs!#REF!,0) -> #REF! | J110: =IF(J2=Inputs!#REF!,Inputs!#REF!,0) -> #REF! | K110: =IF(K2=Inputs!#REF!,Inputs!#REF!,0) -> #REF! | L110: =IF(L2=Inputs!#REF!,Inputs!#REF!,0) -> #REF! | M110: =IF(M2=Inputs!#REF!,Inputs!#REF!,0) -> #REF! | ... KS110: =IF(KS2=Inputs!#REF!,Inputs!#REF!,0) -> #REF!
B111: Amortization | C111: =IF(Inputs!#REF!=1,-PMT(Inputs!#REF!/12,Inputs!#REF!*12,Inputs!#REF!),0) -> #REF! | E111: 0 | F111: =-MIN(F109,$C$111+F114) -> #REF! | G111: =-MIN(G109,$C$111+G114) -> #REF! | H111: =-MIN(H109,$C$111+H114) -> #REF! | I111: =-MIN(I109,$C$111+I114) -> #REF! | J111: =-MIN(J109,$C$111+J114) -> #REF! | K111: =-MIN(K109,$C$111+K114) -> #REF! | L111: =-MIN(L109,$C$111+L114) -> #REF! | M111: =-MIN(M109,$C$111+M114) -> #REF! | ... KS111: =-MIN(KS109,$C$111+KS114) -> #REF!
B112: Ballon Payment | E112: =IF(E$2=MIN(Inputs!#REF!,Inputs!#REF!),-(E109+E111),0) -> #REF! | F112: =IF(F$2=MIN(Inputs!#REF!,Inputs!#REF!),-(F109+F111),0) -> #REF! | G112: =IF(G$2=MIN(Inputs!#REF!,Inputs!#REF!),-(G109+G111),0) -> #REF! | H112: =IF(H$2=MIN(Inputs!#REF!,Inputs!#REF!),-(H109+H111),0) -> #REF! | I112: =IF(I$2=MIN(Inputs!#REF!,Inputs!#REF!),-(I109+I111),0) -> #REF! | J112: =IF(J$2=MIN(Inputs!#REF!,Inputs!#REF!),-(J109+J111),0) -> #REF! | K112: =IF(K$2=MIN(Inputs!#REF!,Inputs!#REF!),-(K109+K111),0) -> #REF! | L112: =IF(L$2=MIN(Inputs!#REF!,Inputs!#REF!),-(L109+L111),0) -> #REF! | ... KS112: =IF(KS$2=MIN(Inputs!#REF!,Inputs!#REF!),-(KS109+KS111),0) -> #REF!
B113: Closing Balance | E113: =SUM(E109:E112) -> #REF! | F113: =SUM(F109:F112) -> #REF! | G113: =SUM(G109:G112) -> #REF! | H113: =SUM(H109:H112) -> #REF! | I113: =SUM(I109:I112) -> #REF! | J113: =SUM(J109:J112) -> #REF! | K113: =SUM(K109:K112) -> #REF! | L113: =SUM(L109:L112) -> #REF! | ... KS113: =SUM(KS109:KS112) -> #REF!
B114: Interest | E114: =-D113*(Inputs!#REF!/12) -> #REF! | F114: =-E113*(Inputs!#REF!/12) -> #REF! | G114: =-F113*(Inputs!#REF!/12) -> #REF! | H114: =-G113*(Inputs!#REF!/12) -> #REF! | I114: =-H113*(Inputs!#REF!/12) -> #REF! | J114: =-I113*(Inputs!#REF!/12) -> #REF! | K114: =-J113*(Inputs!#REF!/12) -> #REF! | L114: =-K113*(Inputs!#REF!/12) -> #REF! | ... KS114: =-KR113*(Inputs!#REF!/12) -> #REF!
B116: 2. Y Debt
B117: Opening Balance | E117: =D121 -> 0 | F117: =E121 -> #REF! | G117: =F121 -> #REF! | H117: =G121 -> #REF! | I117: =H121 -> #REF! | J117: =I121 -> #REF! | K117: =J121 -> #REF! | L117: =K121 -> #REF! | ... KS117: =KR121 -> #REF!
B118: Debt Addition | E118: =IF(Inputs!#REF!=2,IF(E2=Inputs!#REF!,Inputs!#REF!,0),0) -> #REF! | F118: =IF(Inputs!#REF!=2,IF(F2=Inputs!#REF!,Inputs!#REF!,0),0) -> #REF! | G118: =IF(Inputs!#REF!=2,IF(G2=Inputs!#REF!,Inputs!#REF!,0),0) -> #REF! | H118: =IF(Inputs!#REF!=2,IF(H2=Inputs!#REF!,Inputs!#REF!,0),0) -> #REF! | I118: =IF(Inputs!#REF!=2,IF(I2=Inputs!#REF!,Inputs!#REF!,0),0) -> #REF! | J118: =IF(Inputs!#REF!=2,IF(J2=Inputs!#REF!,Inputs!#REF!,0),0) -> #REF! | K118: =IF(Inputs!#REF!=2,IF(K2=Inputs!#REF!,Inputs!#REF!,0),0) -> #REF! | L118: =IF(Inputs!#REF!=2,IF(L2=Inputs!#REF!,Inputs!#REF!,0),0) -> #REF! | ... KS118: =IF(Inputs!#REF!=2,IF(KS2=Inputs!#REF!,Inputs!#REF!,0),0) -> #REF!
B119: Amortization | C119: =IF(Inputs!#REF!=2,Inputs!#REF!*Inputs!#REF!,0)/12 -> #REF! | E119: =-IF(E$2>=Inputs!#REF!,MIN(E117,$C$119),0) -> #REF! | F119: =-IF(F$2>=Inputs!#REF!,MIN(F117,$C$119),0) -> #REF! | G119: =-IF(G$2>=Inputs!#REF!,MIN(G117,$C$119),0) -> #REF! | H119: =-IF(H$2>=Inputs!#REF!,MIN(H117,$C$119),0) -> #REF! | I119: =-IF(I$2>=Inputs!#REF!,MIN(I117,$C$119),0) -> #REF! | J119: =-IF(J$2>=Inputs!#REF!,MIN(J117,$C$119),0) -> #REF! | K119: =-IF(K$2>=Inputs!#REF!,MIN(K117,$C$119),0) -> #REF! | L119: =-IF(L$2>=Inputs!#REF!,MIN(L117,$C$119),0) -> #REF! | ... KS119: =-IF(KS$2>=Inputs!#REF!,MIN(KS117,$C$119),0) -> #REF!
B120: Ballon Payment | E120: =IF(E$2=MIN(Inputs!#REF!,Inputs!#REF!),-(E117+E119),0) -> #REF! | F120: =IF(F$2=MIN(Inputs!#REF!,Inputs!#REF!),-(F117+F119),0) -> #REF! | G120: =IF(G$2=MIN(Inputs!#REF!,Inputs!#REF!),-(G117+G119),0) -> #REF! | H120: =IF(H$2=MIN(Inputs!#REF!,Inputs!#REF!),-(H117+H119),0) -> #REF! | I120: =IF(I$2=MIN(Inputs!#REF!,Inputs!#REF!),-(I117+I119),0) -> #REF! | J120: =IF(J$2=MIN(Inputs!#REF!,Inputs!#REF!),-(J117+J119),0) -> #REF! | K120: =IF(K$2=MIN(Inputs!#REF!,Inputs!#REF!),-(K117+K119),0) -> #REF! | L120: =IF(L$2=MIN(Inputs!#REF!,Inputs!#REF!),-(L117+L119),0) -> #REF! | ... KS120: =IF(KS$2=MIN(Inputs!#REF!,Inputs!#REF!),-(KS117+KS119),0) -> #REF!
B121: Closing Balance | E121: =SUM(E117:E120) -> #REF! | F121: =SUM(F117:F120) -> #REF! | G121: =SUM(G117:G120) -> #REF! | H121: =SUM(H117:H120) -> #REF! | I121: =SUM(I117:I120) -> #REF! | J121: =SUM(J117:J120) -> #REF! | K121: =SUM(K117:K120) -> #REF! | L121: =SUM(L117:L120) -> #REF! | ... KS121: =SUM(KS117:KS120) -> #REF!
B122: Interest | E122: =-D121*(Inputs!#REF!+IF(E$2>=Inputs!#REF!,Inputs!#REF!,0))/12 -> #REF! | F122: =-E121*(Inputs!#REF!+IF(F$2>=Inputs!#REF!,Inputs!#REF!,0))/12 -> #REF! | G122: =-F121*(Inputs!#REF!+IF(G$2>=Inputs!#REF!,Inputs!#REF!,0))/12 -> #REF! | H122: =-G121*(Inputs!#REF!+IF(H$2>=Inputs!#REF!,Inputs!#REF!,0))/12 -> #REF! | I122: =-H121*(Inputs!#REF!+IF(I$2>=Inputs!#REF!,Inputs!#REF!,0))/12 -> #REF! | J122: =-I121*(Inputs!#REF!+IF(J$2>=Inputs!#REF!,Inputs!#REF!,0))/12 -> #REF! | K122: =-J121*(Inputs!#REF!+IF(K$2>=Inputs!#REF!,Inputs!#REF!,0))/12 -> #REF! | L122: =-K121*(Inputs!#REF!+IF(L$2>=Inputs!#REF!,Inputs!#REF!,0))/12 -> #REF! | ... KS122: =-KR121*(Inputs!#REF!+IF(KS$2>=Inputs!#REF!,Inputs!#REF!,0))/12 -> #REF!
B125: Downtime Days Calculations
B126: Estimated Working Days In Months | E126: =IF(OR(E2>Inputs!#REF!,E2<=Inputs!#REF!),0,Inputs!#REF!) -> #REF! | F126: =IF(OR(F2>Inputs!#REF!,F2<=Inputs!#REF!),0,Inputs!#REF!) -> #REF! | G126: =IF(OR(G2>Inputs!#REF!,G2<=Inputs!#REF!),0,Inputs!#REF!) -> #REF! | H126: =IF(OR(H2>Inputs!#REF!,H2<=Inputs!#REF!),0,Inputs!#REF!) -> #REF! | I126: =IF(OR(I2>Inputs!#REF!,I2<=Inputs!#REF!),0,Inputs!#REF!) -> #REF! | J126: =IF(OR(J2>Inputs!#REF!,J2<=Inputs!#REF!),0,Inputs!#REF!) -> #REF! | K126: =IF(OR(K2>Inputs!#REF!,K2<=Inputs!#REF!),0,Inputs!#REF!) -> #REF! | L126: =IF(OR(L2>Inputs!#REF!,L2<=Inputs!#REF!),0,Inputs!#REF!) -> #REF! | ... KS126: =IF(OR(KS2>Inputs!#REF!,KS2<=Inputs!#REF!),0,Inputs!#REF!) -> #REF!
B127: Downtime Days | E127: =-_xlfn.XLOOKUP(E2,Inputs!#REF!,Inputs!#REF!,0,0)+IF(D128<0,D128,0) -> #REF! | F127: =-_xlfn.XLOOKUP(F2,Inputs!#REF!,Inputs!#REF!,0,0)+IF(E128<0,E128,0) -> #REF! | G127: =-_xlfn.XLOOKUP(G2,Inputs!#REF!,Inputs!#REF!,0,0)+IF(F128<0,F128,0) -> #REF! | H127: =-_xlfn.XLOOKUP(H2,Inputs!#REF!,Inputs!#REF!,0,0)+IF(G128<0,G128,0) -> #REF! | I127: =-_xlfn.XLOOKUP(I2,Inputs!#REF!,Inputs!#REF!,0,0)+IF(H128<0,H128,0) -> #REF! | J127: =-_xlfn.XLOOKUP(J2,Inputs!#REF!,Inputs!#REF!,0,0)+IF(I128<0,I128,0) -> #REF! | K127: =-_xlfn.XLOOKUP(K2,Inputs!#REF!,Inputs!#REF!,0,0)+IF(J128<0,J128,0) -> #REF! | L127: =-_xlfn.XLOOKUP(L2,Inputs!#REF!,Inputs!#REF!,0,0)+IF(K128<0,K128,0) -> #REF! | ... KS127: =-_xlfn.XLOOKUP(KS2,Inputs!#REF!,Inputs!#REF!,0,0)+IF(KR128<0,KR128,0) -> #REF!
B128: Net Days | E128: =E126+E127 -> #REF! | F128: =F126+F127 -> #REF! | G128: =G126+G127 -> #REF! | H128: =H126+H127 -> #REF! | I128: =I126+I127 -> #REF! | J128: =J126+J127 -> #REF! | K128: =K126+K127 -> #REF! | L128: =L126+L127 -> #REF! | ... KS128: =KS126+KS127 -> #REF!
E129: =IF(E128<0,0,E128) -> #REF! | F129: =IF(F128<0,0,F128) -> #REF! | G129: =IF(G128<0,0,G128) -> #REF! | H129: =IF(H128<0,0,H128) -> #REF! | I129: =IF(I128<0,0,I128) -> #REF! | J129: =IF(J128<0,0,J128) -> #REF! | K129: =IF(K128<0,0,K128) -> #REF! | L129: =IF(L128<0,0,L128) -> #REF! | ... KS129: =IF(KS128<0,0,KS128) -> #REF!
B131: Cumulative Equity | E131: =SUM(#REF!) -> #REF! | F131: =SUM(#REF!) -> #REF! | G131: =SUM(#REF!) -> #REF! | H131: =SUM(#REF!) -> #REF! | I131: =SUM(#REF!) -> #REF! | J131: =SUM(#REF!) -> #REF! | K131: =SUM(#REF!) -> #REF! | L131: =SUM(#REF!) -> #REF! | ... KS131: =SUM(#REF!) -> #REF!
B132: Proceeds from Sale of Assets, net | E132: =#REF!+#REF! -> #REF! | F132: =#REF!+#REF! -> #REF! | G132: =#REF!+#REF! -> #REF! | H132: =#REF!+#REF! -> #REF! | I132: =#REF!+#REF! -> #REF! | J132: =#REF!+#REF! -> #REF! | K132: =#REF!+#REF! -> #REF! | L132: =#REF!+#REF! -> #REF! | ... KS132: =#REF!+#REF! -> #REF!
B133: Minimum of the above | E133: =MIN(MAX(E132,0),D131) -> #REF! | F133: =MIN(MAX(F132,0),E131) -> #REF! | G133: =MIN(MAX(G132,0),F131) -> #REF! | H133: =MIN(MAX(H132,0),G131) -> #REF! | I133: =MIN(MAX(I132,0),H131) -> #REF! | J133: =MIN(MAX(J132,0),I131) -> #REF! | K133: =MIN(MAX(K132,0),J131) -> #REF! | L133: =MIN(MAX(L132,0),K131) -> #REF! | ... KS133: =MIN(MAX(KS132,0),KR131) -> #REF!
B135: Negative Balance | E135: =#REF!+#REF! -> #REF! | F135: =#REF!+#REF! -> #REF! | G135: =#REF!+#REF! -> #REF! | H135: =#REF!+#REF! -> #REF! | I135: =#REF!+#REF! -> #REF! | J135: =#REF!+#REF! -> #REF! | K135: =#REF!+#REF! -> #REF! | L135: =#REF!+#REF! -> #REF! | ... KS135: =#REF!+#REF! -> #REF!
B137: Downtime Reserve | E137: {=ROUND(-IF(E2>Inputs!#REF!,0,SUMPRODUCT((E$2>Inputs!#REF!)*(E$2<Inputs!#REF!)*Inputs!#REF!)),5)*IF(Inputs!#REF!=1,0,1)} -> #REF! | F137: {=ROUND(-IF(F2>Inputs!#REF!,0,SUMPRODUCT((F$2>Inputs!#REF!)*(F$2<Inputs!#REF!)*Inputs!#REF!)),5)*IF(Inputs!#REF!=1,0,1)} -> #REF! | G137: {=ROUND(-IF(G2>Inputs!#REF!,0,SUMPRODUCT((G$2>Inputs!#REF!)*(G$2<Inputs!#REF!)*Inputs!#REF!)),5)*IF(Inputs!#REF!=1,0,1)} -> #REF! | H137: {=ROUND(-IF(H2>Inputs!#REF!,0,SUMPRODUCT((H$2>Inputs!#REF!)*(H$2<Inputs!#REF!)*Inputs!#REF!)),5)*IF(Inputs!#REF!=1,0,1)} -> #REF! | I137: {=ROUND(-IF(I2>Inputs!#REF!,0,SUMPRODUCT((I$2>Inputs!#REF!)*(I$2<Inputs!#REF!)*Inputs!#REF!)),5)*IF(Inputs!#REF!=1,0,1)} -> #REF! | J137: {=ROUND(-IF(J2>Inputs!#REF!,0,SUMPRODUCT((J$2>Inputs!#REF!)*(J$2<Inputs!#REF!)*Inputs!#REF!)),5)*IF(Inputs!#REF!=1,0,1)} -> #REF! | K137: {=ROUND(-IF(K2>Inputs!#REF!,0,SUMPRODUCT((K$2>Inputs!#REF!)*(K$2<Inputs!#REF!)*Inputs!#REF!)),5)*IF(Inputs!#REF!=1,0,1)} -> #REF! | L137: {=ROUND(-IF(L2>Inputs!#REF!,0,SUMPRODUCT((L$2>Inputs!#REF!)*(L$2<Inputs!#REF!)*Inputs!#REF!)),5)*IF(Inputs!#REF!=1,0,1)} -> #REF! | ... KS137: {=ROUND(-IF(KS2>Inputs!#REF!,0,SUMPRODUCT((KS$2>Inputs!#REF!)*(KS$2<Inputs!#REF!)*Inputs!#REF!)),5)*IF(Inputs!#REF!=1,0,1)} -> #REF!
B138: Cumulative Reserve | F138: =IF(E138=-F137,0,MIN(-F137-E138,IF(SUM(#REF!,#REF!)>0,SUM(#REF!,#REF!),0)))+E138 -> #REF! | G138: =IF(F138=-G137,0,MIN(-G137-F138,IF(SUM(#REF!,#REF!)>0,SUM(#REF!,#REF!),0)))+F138 -> #REF! | H138: =IF(G138=-H137,0,MIN(-H137-G138,IF(SUM(#REF!,#REF!)>0,SUM(#REF!,#REF!),0)))+G138 -> #REF! | I138: =IF(H138=-I137,0,MIN(-I137-H138,IF(SUM(#REF!,#REF!)>0,SUM(#REF!,#REF!),0)))+H138 -> #REF! | J138: =IF(I138=-J137,0,MIN(-J137-I138,IF(SUM(#REF!,#REF!)>0,SUM(#REF!,#REF!),0)))+I138 -> #REF! | K138: =IF(J138=-K137,0,MIN(-K137-J138,IF(SUM(#REF!,#REF!)>0,SUM(#REF!,#REF!),0)))+J138 -> #REF! | L138: =IF(K138=-L137,0,MIN(-L137-K138,IF(SUM(#REF!,#REF!)>0,SUM(#REF!,#REF!),0)))+K138 -> #REF! | M138: =IF(L138=-M137,0,MIN(-M137-L138,IF(SUM(#REF!,#REF!)>0,SUM(#REF!,#REF!),0)))+L138 -> #REF! | ... KS138: =IF(KR138=-KS137,0,MIN(-KS137-KR138,IF(SUM(#REF!,#REF!)>0,SUM(#REF!,#REF!),0)))+KR138 -> #REF!
